Workbook

Sheet Tổng quan
A1: TỐI ƯU TÁC TỬ (AGENT) EIDE v3 — TỔNG QUAN
A2: Đối chiếu mã nguồn EIDE v3 (src/eide, ~70 nghìn dòng toàn dự án) với 18 mẫu kiến trúc agent trong tài liệu 'Kiến trúc AI Agent'. Ngày rà soát: 06/10/2026.
A4: 1. Số đề xuất theo mảng và mức ưu tiên
A5: Mảng | B5: P0 | C5: P1 | D5: P2 | E5: P3 | F5: Tổng
A6: 1. Lõi tác tử | B6: =COUNTIFS('Danh mục tối ưu'!$B$5:$B$110,$A6,'Danh mục tối ưu'!$K$5:$K$110,"P0") | C6: =COUNTIFS('Danh mục tối ưu'!$B$5:$B$110,$A6,'Danh mục tối ưu'!$K$5:$K$110,"P1") | D6: =COUNTIFS('Danh mục tối ưu'!$B$5:$B$110,$A6,'Danh mục tối ưu'!$K$5:$K$110,"P2") | E6: =COUNTIFS('Danh mục tối ưu'!$B$5:$B$110,$A6,'Danh mục tối ưu'!$K$5:$K$110,"P3") | F6: =SUM(B6:E6)
A7: 2. Phân tích & thiết kế phần mềm | B7: =COUNTIFS('Danh mục tối ưu'!$B$5:$B$110,$A7,'Danh mục tối ưu'!$K$5:$K$110,"P0") | C7: =COUNTIFS('Danh mục tối ưu'!$B$5:$B$110,$A7,'Danh mục tối ưu'!$K$5:$K$110,"P1") | D7: =COUNTIFS('Danh mục tối ưu'!$B$5:$B$110,$A7,'Danh mục tối ưu'!$K$5:$K$110,"P2") | E7: =COUNTIFS('Danh mục tối ưu'!$B$5:$B$110,$A7,'Danh mục tối ưu'!$K$5:$K$110,"P3") | F7: =SUM(B7:E7)
A8: 3. Mạch, ERC, HDL/FPGA | B8: =COUNTIFS('Danh mục tối ưu'!$B$5:$B$110,$A8,'Danh mục tối ưu'!$K$5:$K$110,"P0") | C8: =COUNTIFS('Danh mục tối ưu'!$B$5:$B$110,$A8,'Danh mục tối ưu'!$K$5:$K$110,"P1") | D8: =COUNTIFS('Danh mục tối ưu'!$B$5:$B$110,$A8,'Danh mục tối ưu'!$K$5:$K$110,"P2") | E8: =COUNTIFS('Danh mục tối ưu'!$B$5:$B$110,$A8,'Danh mục tối ưu'!$K$5:$K$110,"P3") | F8: =SUM(B8:E8)
A9: 4. Kiểm thử & kiểm chứng | B9: =COUNTIFS('Danh mục tối ưu'!$B$5:$B$110,$A9,'Danh mục tối ưu'!$K$5:$K$110,"P0") | C9: =COUNTIFS('Danh mục tối ưu'!$B$5:$B$110,$A9,'Danh mục tối ưu'!$K$5:$K$110,"P1") | D9: =COUNTIFS('Danh mục tối ưu'!$B$5:$B$110,$A9,'Danh mục tối ưu'!$K$5:$K$110,"P2") | E9: =COUNTIFS('Danh mục tối ưu'!$B$5:$B$110,$A9,'Danh mục tối ưu'!$K$5:$K$110,"P3") | F9: =SUM(B9:E9)
A10: 5. Tri thức, RAG & bộ nhớ | B10: =COUNTIFS('Danh mục tối ưu'!$B$5:$B$110,$A10,'Danh mục tối ưu'!$K$5:$K$110,"P0") | C10: =COUNTIFS('Danh mục tối ưu'!$B$5:$B$110,$A10,'Danh mục tối ưu'!$K$5:$K$110,"P1") | D10: =COUNTIFS('Danh mục tối ưu'!$B$5:$B$110,$A10,'Danh mục tối ưu'!$K$5:$K$110,"P2") | E10: =COUNTIFS('Danh mục tối ưu'!$B$5:$B$110,$A10,'Danh mục tối ưu'!$K$5:$K$110,"P3") | F10: =SUM(B10:E10)
A11: Tổng | B11: =SUM(B6:B10) | C11: =SUM(C6:C10) | D11: =SUM(D6:D10) | E11: =SUM(E6:E10) | F11: =SUM(F6:F10)
A13: 2. Lộ trình theo giai đoạn (tự tính từ Ưu tiên + Công sức)
A14: Giai đoạn | B14: Số đề xuất | C14: Đã xong | D14: % xong
A15: GĐ1 — Làm ngay (0–2 tuần): P0, công sức S/M | B15: =COUNTIF('Danh mục tối ưu'!$M$5:$M$110,"GĐ1") | C15: =COUNTIFS('Danh mục tối ưu'!$M$5:$M$110,"GĐ1",'Danh mục tối ưu'!$Q$5:$Q$110,"Xong") | D15: =IF(B15=0,0,C15/B15)
A16: GĐ2 — Ngắn hạn (2–6 tuần): P0 công sức L, P1 công sức S | B16: =COUNTIF('Danh mục tối ưu'!$M$5:$M$110,"GĐ2") | C16: =COUNTIFS('Danh mục tối ưu'!$M$5:$M$110,"GĐ2",'Danh mục tối ưu'!$Q$5:$Q$110,"Xong") | D16: =IF(B16=0,0,C16/B16)
A17: GĐ3 — Trung hạn (6–12 tuần): P1 công sức M/L | B17: =COUNTIF('Danh mục tối ưu'!$M$5:$M$110,"GĐ3") | C17: =COUNTIFS('Danh mục tối ưu'!$M$5:$M$110,"GĐ3",'Danh mục tối ưu'!$Q$5:$Q$110,"Xong") | D17: =IF(B17=0,0,C17/B17)
A18: GĐ4 — Có thì tốt: P2/P3 | B18: =COUNTIF('Danh mục tối ưu'!$M$5:$M$110,"GĐ4") | C18: =COUNTIFS('Danh mục tối ưu'!$M$5:$M$110,"GĐ4",'Danh mục tối ưu'!$Q$5:$Q$110,"Xong") | D18: =IF(B18=0,0,C18/B18)
A20: 3. Số đề xuất theo chủ đề xuyên suốt
A21: Chủ đề | B21: Số đề xuất | C21: Trong đó P0
A22: T01 Giao thức & độ bền vòng lặp | B22: =COUNTIF('Danh mục tối ưu'!$D$5:$D$110,$A22) | C22: =COUNTIFS('Danh mục tối ưu'!$D$5:$D$110,$A22,'Danh mục tối ưu'!$K$5:$K$110,"P0")
A23: T02 Ngữ cảnh, lược đồ công cụ & token | B23: =COUNTIF('Danh mục tối ưu'!$D$5:$D$110,$A23) | C23: =COUNTIFS('Danh mục tối ưu'!$D$5:$D$110,$A23,'Danh mục tối ưu'!$K$5:$K$110,"P0")
A24: T03 Tác tử con & điều phối song song | B24: =COUNTIF('Danh mục tối ưu'!$D$5:$D$110,$A24) | C24: =COUNTIFS('Danh mục tối ưu'!$D$5:$D$110,$A24,'Danh mục tối ưu'!$K$5:$K$110,"P0")
A25: T04 Kiểm chứng độc lập (verifier) | B25: =COUNTIF('Danh mục tối ưu'!$D$5:$D$110,$A25) | C25: =COUNTIFS('Danh mục tối ưu'!$D$5:$D$110,$A25,'Danh mục tối ưu'!$K$5:$K$110,"P0")
A26: T05 Lập kế hoạch & thực thi theo bước | B26: =COUNTIF('Danh mục tối ưu'!$D$5:$D$110,$A26) | C26: =COUNTIFS('Danh mục tối ưu'!$D$5:$D$110,$A26,'Danh mục tối ưu'!$K$5:$K$110,"P0")
A27: T06 Reflexion – bài học dài hạn | B27: =COUNTIF('Danh mục tối ưu'!$D$5:$D$110,$A27) | C27: =COUNTIFS('Danh mục tối ưu'!$D$5:$D$110,$A27,'Danh mục tối ưu'!$K$5:$K$110,"P0")
A28: T07 Phản biện thiết kế (Debate/ToT) | B28: =COUNTIF('Danh mục tối ưu'!$D$5:$D$110,$A28) | C28: =COUNTIFS('Danh mục tối ưu'!$D$5:$D$110,$A28,'Danh mục tối ưu'!$K$5:$K$110,"P0")
A29: T08 Yêu cầu & truy vết | B29: =COUNTIF('Danh mục tối ưu'!$D$5:$D$110,$A29) | C29: =COUNTIFS('Danh mục tối ưu'!$D$5:$D$110,$A29,'Danh mục tối ưu'!$K$5:$K$110,"P0")
A30: T09 Phân tích mã tĩnh & CodeAct | B30: =COUNTIF('Danh mục tối ưu'!$D$5:$D$110,$A30) | C30: =COUNTIFS('Danh mục tối ưu'!$D$5:$D$110,$A30,'Danh mục tối ưu'!$K$5:$K$110,"P0")
A31: T10 ERC & thiết kế mạch | B31: =COUNTIF('Danh mục tối ưu'!$D$5:$D$110,$A31) | C31: =COUNTIFS('Danh mục tối ưu'!$D$5:$D$110,$A31,'Danh mục tối ưu'!$K$5:$K$110,"P0")
A32: T11 HDL/FPGA | B32: =COUNTIF('Danh mục tối ưu'!$D$5:$D$110,$A32) | C32: =COUNTIFS('Danh mục tối ưu'!$D$5:$D$110,$A32,'Danh mục tối ưu'!$K$5:$K$110,"P0")
A33: T12 Kiểm thử sản phẩm (unit, đột biến, hồi quy, HIL) | B33: =COUNTIF('Danh mục tối ưu'!$D$5:$D$110,$A33) | C33: =COUNTIFS('Danh mục tối ưu'!$D$5:$D$110,$A33,'Danh mục tối ưu'!$K$5:$K$110,"P0")
... A36: T15 Đo lường & bộ đánh giá (eval) | B36: =COUNTIF('Danh mục tối ưu'!$D$5:$D$110,$A36) | C36: =COUNTIFS('Danh mục tối ưu'!$D$5:$D$110,$A36,'Danh mục tối ưu'!$K$5:$K$110,"P0")
A38: 4. Kết luận chính
A39: • Lõi đã có nền rất tốt: vòng ReAct qua ba lớp xác định (hook → policy → hook), thẻ duyệt người (HITL) R0–R4, plan mode khoá công cụ ghi, tiêu chí-trước cho mô phỏng có máy chấm bằng mã, ghi transcript trước (write-ahead), phát hiện quay vòng và lượt im lặng.
A40: • Ba lỗ hổng nền cần vá trước mọi tối ưu khác: (1) lịch sử gọi–trả công cụ lệch cặp với Gemini khi có thẻ cổng giữa lô; (2) tác tử con gọi thẳng registry.run, đi vòng qua hook/policy/plan mode; (3) hook Stop coi MỌI task.run là đã kiểm chứng.
A41: • Nhiều 'ô xanh giả' còn sót ở nơi chưa áp nguyên tắc 'chương trình đo, EIDE phán': unit test tự khai dat, PASS/FAIL HDL dò chuỗi con, độ nhạy HDL tự khai, đột biến không biên dịch được tính là 'bắt được', sch.netlist báo 0 lỗi trong khi phần lớn luật ERC 'chưa đủ dữ kiện'.
A42: • Khoảng trống lớn nhất so với 18 mẫu: Agentic RAG (chỉ có khớp chuỗi trong 1 tài liệu, không SVD, không bảng PDF), Reflexion (không có bài học dài hạn), Parallelization/LLMCompiler (mọi lời gọi tuần tự), Evaluator–Optimizer có vòng sửa (ERC, harden test, verifier bác).
A43: • Chi phí ngữ cảnh: 73 công cụ luôn hiện ≈ 26 nghìn token lược đồ mỗi lời gọi (gấp ~6,5 lần ngân sách 4000 khai trong config nhưng không dùng); khối nhắc mỗi lượt bị lưu lặp vĩnh viễn trong transcript; không có trần token mỗi lượt.
A44: • Mạch & HDL: ERC thiếu luật quá áp, kiểu chân, ngắn mạch nguồn, decoupling/boot; luồng HDL không có cổng giữa chặng, không kiểm ràng buộc chân .cst, không formal. Đây là nơi lỗi đắt nhất (hỏng phần cứng) mà hiện chỉ trông vào trí nhớ của mô hình.
A45: • Nguyên tắc leo thang: làm GĐ1 + bộ đo lường (T15) trước; chỉ thêm mẫu tốn kém (Debate, ToT, song song nhiều worker) khi số đo cho thấy bậc hiện tại chưa đủ.
A47: 5. Chú giải
A48: P0 | B48: Làm ngay — lỗi nền/an toàn hoặc ô xanh giả, ảnh hưởng lớn
A49: P1 | B49: Quan trọng — tăng rõ độ thông minh/độ phủ kiểm thử
A50: P2 | B50: Nên làm — cải thiện chất lượng, ít khẩn
A51: P3 | B51: Có thì tốt
A52: S / M / L / XL | B52: Công sức ước: S ≤ 2 ngày · M ≈ 3–7 ngày · L ≈ 2–4 tuần · XL > 1 tháng
A53: Mã Mx-yy | B53: x = mảng (1 lõi, 2 phân tích–thiết kế PM, 3 mạch–HDL, 4 kiểm thử, 5 tri thức–bộ nhớ); yy = số thứ tự

Sheet Tiến độ 07-10-2026
A1: TIẾN ĐỘ ĐỢT TỐI ƯU TÁC TỬ — chốt ngày 07/10/2026
A2: Mỗi dòng 'Xong' đều có: mục DEV-LOG tra lại được · số ca kiểm trước→sau · một con số đo trên dữ liệu thật · phần còn nợ. Cột chi tiết nằm ở sheet “Danh mục tối ưu”, cột T–Y.
A4: Tổng quan | B4: Số việc | C4: Ghi chú
A5: Xong (đã gộp vào main, đã đẩy) | B5: 14 | C5: 14 việc đầu của Giai đoạn 1, theo đúng thứ tự # của kế hoạch
A6: Đang làm (chưa commit) | B6: 1 | C6: M3-13 — mã và ca kiểm đã có trên nhánh toi-uu/M3-13; còn chạy toàn bộ + DEV-LOG + commit
A7: Chưa làm | B7: 91 | C7: 91 việc còn lại trong 106
A8: TỔNG | B8: 106
A10: Phép đo của cả đợt | B10: Trước (06/10) | C10: Sau (07/10) | D10: Ghi chú
A11: Ca đơn vị Python (pytest -q) | B11: 1 610 | C11: 1 732 | D11: +122 ca; không ca cũ nào đỏ ở bất kỳ bước nào
A12: Ca đơn vị giao diện (swift test) | B12: 43 | C12: 43 | D12: không nhiệm vụ nào đụng ui/ — kiểu khối A2.2 dùng “table”, Swift đã dựng được
A13: kiem_tai_lieu.py | B13: 0 chỗ lệch | C13: 0 chỗ lệch | D13: bắt được 1 đường dẫn tôi ghi sai trong README, đã sửa
A14: thu_sch.py (cờ schematic bật) | B14: 63/63 | C14: 63/63 | D14: chạy ở M3-03 và M3-04, không tụt
A15: Mục DEV-LOG mới | B15: — | C15: DEV-330 → DEV-343 | D15: 14 mục, mỗi việc một mục
A16: Cờ tính năng mới | B16: 1 (schematic) | C16: 7 | D16: 6 cờ mới, TẤT CẢ mặc định TẮT
A17: Mã lỗi mới | B17: — | C17: E4031 · E4032 · E6012 | D17: lấy từ bảng cấp phát §6 của kế hoạch
A19: # | B19: Mã | C19: Mảng | D19: Ưu tiên | E19: DEV-LOG | F19: Ca kiểm | G19: Cờ mặc định
A20: 1 | B20: M1-01 | C20: 1. Lõi tác tử | D20: P0 | E20: DEV-330 | F20: 105/309 phiên thật có lịch sử tự mâu thuẫn — 255 chỗ (156 kết quả thứ hai cùng id, 74 message chen giữa, 24 kết quả lạc lượt, 1 lời gọi không kết quả) | G20: không có cờ — sửa lỗi thuần
A21: 2 | B21: M1-02 | C21: 1. Lõi tác tử | D21: P0 | E21: DEV-331 | F21: lược đồ công cụ thật: 25 869 token/lời gọi (trần tool_schema=4000 chưa dòng mã nào đọc). Cờ bật: 4 475 token, giảm 82,7 %; 73 → 18 công cụ | G21: GON_CONG_CU — TẮT
A22: 3 | B22: M1-03 | C22: 1. Lõi tác tử | D22: P0 | E22: DEV-332 | F22: 1 822 lời gọi của tác tử con trong 26 phiên thật, 0 lần qua lớp luật. Toàn công cụ đọc trừ một build.compile — lỗ hổng chưa bị bước vào, không phải được canh | G22: không có cờ — sửa lỗi thuần
A23: 4 | B23: M2-01 | C23: 2. Phân tích & thiết kế phần mềm | D23: P0 | E23: DEV-333 | F23: kịch bản 3 REQ + 3 phương án + 3 tiêu chí + 3 tệp: sửa MỘT REQ làm 9 hiện vật STALE → còn 3. Phép đo đầu ra 6→2 vì bị hàng rào E4020 chặn, đã sửa kịch bản đo | G23: TRUY_VET — TẮT (phần nền chạy cả khi tắt)
A24: 5 | B24: M2-02 | C24: 2. Phân tích & thiết kế phần mềm | D24: P0 | E24: DEV-334 | F24: 63 kho thật: 5/37 REQ có ít nhất một phép đo; 27 chưa có phương án nào nhận; 0 REQ đi hết chuỗi. Cột 'Mã nguồn' trống ở MỌI dự án vì hien_thuc_req vừa mới tồn tại | G24: REQ_PHU — TẮT (khối A2.2 trên tab không phụ thuộc cờ)
A25: 6 | B25: M2-03 | C25: 2. Phân tích & thiết kế phần mềm | D25: P0 | E25: DEV-335 | F25: 37 REQ thật: 25 sạch (67 %), 11 thiếu tiêu chí đo được, 2 có từ mơ hồ. Lần đo đầu ra 3 từ mơ hồ, một là kêu oan ('ít nhất 2 lần' là mức đo được) — đã vá | G25: REQ_CHAT_LUONG — TẮT (module yeu_cau.py luôn có)
A26: 7 | B26: M2-06 | C26: 2. Phân tích & thiết kế phần mềm | D26: P0 | E26: DEV-336 | F26: sổ cái thật: 26 lần đánh dấu 'xong' ngay sau một lần ghi mã, 19 lần (73 %) không có phép kiểm nào đạt ở giữa. Phép đo đầu ở mức dự án ra 0 — đúng nhưng đo sai câu hỏi | G26: KE_HOACH_CONG_KIEM — TẮT
A27: 8 | B27: M2-08 | C27: 2. Phân tích & thiết kế phần mềm | D27: P0 | E27: DEV-337 | F27: 185 tệp .c thật: 1 758 → 1 786 hàm thấy được (+28 hàm trước đây VÔ HÌNH: 8 ngắt + 20 bị regex tham lam nuốt). 78 hàm nay gắn nhãn 'isr', 70 trong đó vốn đã có trong danh sách | G27: không có cờ — sửa lỗi thuần
A28: 9 | B28: M3-01 | C28: 3. Mạch, ERC, HDL/FPGA | D28: P0 | E28: DEV-338 | F28: 0 phát hiện trên 5 mô hình mạch thật — và lý do đáng hơn con số: 3 kho CÓ Fact v_max thì KHÔNG có mô hình mạch, 5 kho có mạch thì không có Fact ấy; thêm nữa Fact dùng chủ thể chip:X mà ERC không tra tiền tố đó | G28: không có cờ — sửa lỗi thuần
A29: 10 | B29: M3-03 | C29: 3. Mạch, ERC, HDL/FPGA | D29: P0 | E29: DEV-339 | F29: 8 phát hiện trên 5 mạch thật (6 nguon_khong_cap + 2 net_mot_chan), trong đó net clock I2C nối đúng một chân. SÁU trong tám là 'mô hình chưa khai' chứ không phải 'mạch sai'. robot-canbang: 107 Port lá, KHÔNG Port nào là power_out | G29: không có cờ — sửa lỗi thuần
A30: 11 | B30: M3-04 | C30: 3. Mạch, ERC, HDL/FPGA | D30: P0 | E30: DEV-340 | F30: 0 phát hiện trên 5 mạch thật — và đây là con số ĐÚNG (hai lỗi này catastrophic, không bo nào sống tới lúc lưu kho). Đã CẤY hai bộ cấp vào bản sao kho robot-canbang để chứng minh luật sống: nổ đúng 1 blocker trên net +5V thật | G30: không có cờ — sửa lỗi thuần
A31: 12 | B31: M3-07 | C31: 3. Mạch, ERC, HDL/FPGA | D31: P0 | E31: DEV-341 | F31: Fact tới được ERC: 5 → 17 (+12). Ba kho có Fact datasheet thì TOÀN BỘ mang chủ thể chip:, tức trước đó không một Fact nào tới được ERC. Độ phủ 5 mạch thật nay đọc được | G31: không có cờ — sửa lỗi thuần
... A34: 15 | B34: M3-13 | C34: 3. Mạch, ERC, HDL/FPGA | D34: P0 | E34: chưa ghi | F34: testbench Verilog THẬT của bài 3 (lõi RISC-V): pcpi_dot4 bắt 1/1, pcpi_mac bắt 1/1 (phép phá 'đảo điều kiện if' làm bộ kiểm đỏ); pcpi_vmini CHƯA đo được — tb cần thêm mô-đun ram ngoài phần nó tự include | G34: không có cờ (công cụ mới core=False)
A36: Việc còn MỞ (ngoài 91 việc chưa làm) | B36: Vì sao còn mở
A37: Sáu cờ mới đều còn TẮT | B37: GON_CONG_CU · TRUY_VET · REQ_PHU · REQ_CHAT_LUONG · KE_HOACH_CONG_KIEM · ERC_TU_DONG. Cả sáu đổi thứ Agent nhìn thấy hoặc đọc mỗi lượt, nên chỉ bộ 76 ca chạy HAI chế độ mới nói được chúng làm Agent khá hơn hay tệ hơn — bộ ấy tốn tiền mô hình nên chưa chạy.
A38: kiem_cap_goi_tra() chưa thành hàng rào | B38: Soát được mọi phiên đã lưu, nhưng chưa hook nào gọi nó tự động — bắt được chuyện cũ, chưa chặn được chuyện mới.
A39: Luật ERC quá áp chưa nổ trên dữ liệu thật | B39: Đường dẫn đã thông ở M3-07, nhưng ba kho có Fact điện áp thì không có mô hình mạch, và ngược lại. Phải chờ một dự án có cả hai.
A40: Cột “Mã nguồn” của ma trận truy vết trống ở mọi dự án | B40: Nó đọc hien_thuc_req — trường vừa mới tồn tại, chưa tệp nào trên đĩa từng khai. Nên “chưa hiện thực” ở đó nghĩa là “chưa ai KHAI”, không phải “chưa ai viết”.
A41: Lỗi _go_dau trong src/eide/tools/design.py | B41: Viết .replace('d','d') nên 'ổn định' và 'ON DINH' không khớp nhau. Hàm ấy đang dùng cho một phép kiểm an toàn (người có thật sự chọn không). Tìm thấy ở M2-03, CHƯA sửa vì ngoài phạm vi — cần bộ ca kiểm riêng.
A42: subagent req-critic (bước 4 của M2-03) | B42: Kế hoạch ghi “tuỳ chọn, gộp M2-13”. Chưa làm, đúng theo kế hoạch.
A44: Lỗi tìm thấy trong CHÍNH PHÉP ĐO của tôi | B44: Lộ ra ở đâu
A45: Kịch bản đo bị hàng rào của sản phẩm chặn (ghi tệp chưa đọc, E4020) và trả về một con số hợp lý thay vì nổ — 6→2 trông đẹp y như 9→3 đúng | B45: M2-01 · DEV-333
A46: Ca kiểm dựng trên điều tôi tự nhớ sai: “thiết” bỏ dấu KHÔNG chứa “it”; chỗ va thật là bit/unit/init/exit | B46: M2-03 · DEV-335
A47: Phép phá dài ĐÚNG BẰNG mã gốc (0.6 → 0.0) nên __pycache__ cũ còn hiệu lực — phép đo chạy mã khác với mã trong tệp | B47: M2-03 · DEV-335
A48: Phép đo trả lời ĐÚNG một câu hỏi KHÁC: đếm ở mức dự án ra 0 chỗ cần chặn; câu phải hỏi là “lần ghi NÀY đã được kiểm chưa” → 19/26 | B48: M2-06 · DEV-336
... A53: Regex mà KẾ HOẠCH ghi sẵn từ chối oan 588/846 bản ghi thật; và ba ca kiểm xanh vì lý do sai (tệp giả dùng $4 thay $3; “FAILED” chứa “FAIL”) | B53: M3-12 · DEV-343

Sheet Tiến độ 08-10-2026
A1: TIẾN ĐỘ ĐỢT TỐI ƯU TÁC TỬ — chốt ngày 08/10/2026
A2: Mỗi dòng 'Xong' đều có: mục DEV-LOG tra lại được · số ca kiểm trước→sau · một con số đo trên dữ liệu thật · phần còn nợ. Cột chi tiết nằm ở sheet “Danh mục tối ưu”, cột T–Y.
A4: Tổng quan | B4: Số việc | C4: Ghi chú
A5: Xong (đã gộp vào main, đã đẩy) | B5: 16 | C5: 16 việc đầu của Giai đoạn 1, theo đúng thứ tự # của kế hoạch
A6: Đang làm (chưa commit) | B6: 0 | C6: không việc nào đang dở — M3-13 đã chốt và gộp main sáng 08/10
A7: Chưa làm | B7: 90 | C7: 90 việc còn lại trong 106
A8: TỔNG | B8: 106
A10: Phép đo của cả đợt | B10: Trước (06/10) | C10: Sau (08/10) | D10: Ghi chú
A11: Ca đơn vị Python (pytest -q) | B11: 1 610 | C11: 1 773 | D11: +163 ca so với 06/10; không ca cũ nào đỏ ở bất kỳ bước nào
A12: Ca đơn vị giao diện (swift test) | B12: 43 | C12: 43 | D12: không nhiệm vụ nào đụng ui/ — kiểu khối A2.2 dùng “table”, Swift đã dựng được
A13: kiem_tai_lieu.py | B13: 0 chỗ lệch | C13: 0 chỗ lệch | D13: 0 chỗ LỆCH CHẮC CHẮN cả hai lượt. Hôm nay nó bắt đúng chuyện cần bắt: hai công cụ mới làm README lệch số công cụ 127 → 129, và số 'cần đọc lại' nhảy 11 → 15 → về 11 sau khi sửa
A14: thu_sch.py (cờ schematic bật) | B14: 63/63 | C14: 63/63 | D14: chạy ở M3-03 và M3-04, không tụt
A15: Mục DEV-LOG mới | B15: — | C15: DEV-330 → DEV-345 | D15: 16 mục, mỗi việc một mục
A16: Cờ tính năng mới | B16: 1 (schematic) | C16: 7 | D16: 6 cờ mới, TẤT CẢ mặc định TẮT
A17: Mã lỗi mới | B17: — | C17: E4031 · E4032 · E6012 · E4033 | D17: E4033 của M3-18 KHÔNG lấy theo kế hoạch: tôi chọn E4031 trước, rồi grep thấy loop.py:1085 đã dùng E4031 cho 'chưa chạy, vì chờ cổng'
A19: # | B19: Mã | C19: Mảng | D19: Ưu tiên | E19: DEV-LOG | F19: Ca kiểm | G19: Cờ mặc định
A20: 1 | B20: M1-01 | C20: 1. Lõi tác tử | D20: P0 | E20: DEV-330 | F20: 105/309 phiên thật có lịch sử tự mâu thuẫn — 255 chỗ (156 kết quả thứ hai cùng id, 74 message chen giữa, 24 kết quả lạc lượt, 1 lời gọi không kết quả) | G20: không có cờ — sửa lỗi thuần
A21: 2 | B21: M1-02 | C21: 1. Lõi tác tử | D21: P0 | E21: DEV-331 | F21: lược đồ công cụ thật: 25 869 token/lời gọi (trần tool_schema=4000 chưa dòng mã nào đọc). Cờ bật: 4 475 token, giảm 82,7 %; 73 → 18 công cụ | G21: GON_CONG_CU — TẮT
A22: 3 | B22: M1-03 | C22: 1. Lõi tác tử | D22: P0 | E22: DEV-332 | F22: 1 822 lời gọi của tác tử con trong 26 phiên thật, 0 lần qua lớp luật. Toàn công cụ đọc trừ một build.compile — lỗ hổng chưa bị bước vào, không phải được canh | G22: không có cờ — sửa lỗi thuần
A23: 4 | B23: M2-01 | C23: 2. Phân tích & thiết kế phần mềm | D23: P0 | E23: DEV-333 | F23: kịch bản 3 REQ + 3 phương án + 3 tiêu chí + 3 tệp: sửa MỘT REQ làm 9 hiện vật STALE → còn 3. Phép đo đầu ra 6→2 vì bị hàng rào E4020 chặn, đã sửa kịch bản đo | G23: TRUY_VET — TẮT (phần nền chạy cả khi tắt)
A24: 5 | B24: M2-02 | C24: 2. Phân tích & thiết kế phần mềm | D24: P0 | E24: DEV-334 | F24: 63 kho thật: 5/37 REQ có ít nhất một phép đo; 27 chưa có phương án nào nhận; 0 REQ đi hết chuỗi. Cột 'Mã nguồn' trống ở MỌI dự án vì hien_thuc_req vừa mới tồn tại | G24: REQ_PHU — TẮT (khối A2.2 trên tab không phụ thuộc cờ)
A25: 6 | B25: M2-03 | C25: 2. Phân tích & thiết kế phần mềm | D25: P0 | E25: DEV-335 | F25: 37 REQ thật: 25 sạch (67 %), 11 thiếu tiêu chí đo được, 2 có từ mơ hồ. Lần đo đầu ra 3 từ mơ hồ, một là kêu oan ('ít nhất 2 lần' là mức đo được) — đã vá | G25: REQ_CHAT_LUONG — TẮT (module yeu_cau.py luôn có)
A26: 7 | B26: M2-06 | C26: 2. Phân tích & thiết kế phần mềm | D26: P0 | E26: DEV-336 | F26: sổ cái thật: 26 lần đánh dấu 'xong' ngay sau một lần ghi mã, 19 lần (73 %) không có phép kiểm nào đạt ở giữa. Phép đo đầu ở mức dự án ra 0 — đúng nhưng đo sai câu hỏi | G26: KE_HOACH_CONG_KIEM — TẮT
A27: 8 | B27: M2-08 | C27: 2. Phân tích & thiết kế phần mềm | D27: P0 | E27: DEV-337 | F27: 185 tệp .c thật: 1 758 → 1 786 hàm thấy được (+28 hàm trước đây VÔ HÌNH: 8 ngắt + 20 bị regex tham lam nuốt). 78 hàm nay gắn nhãn 'isr', 70 trong đó vốn đã có trong danh sách | G27: không có cờ — sửa lỗi thuần
A28: 9 | B28: M3-01 | C28: 3. Mạch, ERC, HDL/FPGA | D28: P0 | E28: DEV-338 | F28: 0 phát hiện trên 5 mô hình mạch thật — và lý do đáng hơn con số: 3 kho CÓ Fact v_max thì KHÔNG có mô hình mạch, 5 kho có mạch thì không có Fact ấy; thêm nữa Fact dùng chủ thể chip:X mà ERC không tra tiền tố đó | G28: không có cờ — sửa lỗi thuần
A29: 10 | B29: M3-03 | C29: 3. Mạch, ERC, HDL/FPGA | D29: P0 | E29: DEV-339 | F29: 8 phát hiện trên 5 mạch thật (6 nguon_khong_cap + 2 net_mot_chan), trong đó net clock I2C nối đúng một chân. SÁU trong tám là 'mô hình chưa khai' chứ không phải 'mạch sai'. robot-canbang: 107 Port lá, KHÔNG Port nào là power_out | G29: không có cờ — sửa lỗi thuần
A30: 11 | B30: M3-04 | C30: 3. Mạch, ERC, HDL/FPGA | D30: P0 | E30: DEV-340 | F30: 0 phát hiện trên 5 mạch thật — và đây là con số ĐÚNG (hai lỗi này catastrophic, không bo nào sống tới lúc lưu kho). Đã CẤY hai bộ cấp vào bản sao kho robot-canbang để chứng minh luật sống: nổ đúng 1 blocker trên net +5V thật | G30: không có cờ — sửa lỗi thuần
A31: 12 | B31: M3-07 | C31: 3. Mạch, ERC, HDL/FPGA | D31: P0 | E31: DEV-341 | F31: Fact tới được ERC: 5 → 17 (+12). Ba kho có Fact datasheet thì TOÀN BỘ mang chủ thể chip:, tức trước đó không một Fact nào tới được ERC. Độ phủ 5 mạch thật nay đọc được | G31: không có cờ — sửa lỗi thuần
... A34: 15 | B34: M3-13 | C34: 3. Mạch, ERC, HDL/FPGA | D34: P0 | E34: DEV-344 | F34: testbench Verilog THẬT của bài 3: tb_pcpi_dot4 1/1, tb_pcpi_mac 1/1, tb_pcpi_vmini không đo được (tb gọi bản bram HAI CỔNG đã bị bỏ 02/10) — mẫu số là TỆP, không phải phép phá | G34: không có cờ (công cụ mới core=False)
A35: 16 | B35: M3-18 | C35: 3. Mạch, ERC, HDL/FPGA | D35: P0 | E35: DEV-345 | F35: 6 cặp (mạng cổng, .cst) thật → 1 chỗ CHẶN: blinky của riscv-tn20k-b dựng bitstream 4,6 MB với chân đồng hồ do nextpnr tự chọn (rơi đúng chân 4 — bằng may). Cả 7 tệp .cst thật đọc hết, 0 lỗi cú pháp | G35: không có cờ (công cụ mới core=False)
A37: Việc còn MỞ (ngoài 90 việc chưa làm) | B37: Vì sao còn mở
A38: Sáu cờ mới đều còn TẮT | B38: GON_CONG_CU · TRUY_VET · REQ_PHU · REQ_CHAT_LUONG · KE_HOACH_CONG_KIEM · ERC_TU_DONG. Cả sáu đổi thứ Agent nhìn thấy hoặc đọc mỗi lượt, nên chỉ bộ 76 ca chạy HAI chế độ mới nói được chúng làm Agent khá hơn hay tệ hơn — bộ ấy tốn tiền mô hình nên chưa chạy.
A39: kiem_cap_goi_tra() chưa thành hàng rào | B39: Soát được mọi phiên đã lưu, nhưng chưa hook nào gọi nó tự động — bắt được chuyện cũ, chưa chặn được chuyện mới.
A40: Luật ERC quá áp chưa nổ trên dữ liệu thật | B40: Đường dẫn đã thông ở M3-07, nhưng ba kho có Fact điện áp thì không có mô hình mạch, và ngược lại. Phải chờ một dự án có cả hai.
A41: Cột “Mã nguồn” của ma trận truy vết trống ở mọi dự án | B41: Nó đọc hien_thuc_req — trường vừa mới tồn tại, chưa tệp nào trên đĩa từng khai. Nên “chưa hiện thực” ở đó nghĩa là “chưa ai KHAI”, không phải “chưa ai viết”.
A42: Lỗi _go_dau trong src/eide/tools/design.py | B42: Viết .replace('d','d') nên 'ổn định' và 'ON DINH' không khớp nhau. Hàm ấy đang dùng cho một phép kiểm an toàn (người có thật sự chọn không). Tìm thấy ở M2-03, CHƯA sửa vì ngoài phạm vi — cần bộ ca kiểm riêng.
A43: subagent req-critic (bước 4 của M2-03) | B43: Kế hoạch ghi “tuỳ chọn, gộp M2-13”. Chưa làm, đúng theo kế hoạch.
A44: Hai luật kiểm chân FPGA chưa có dữ liệu để nổ | B44: chan_lech_kit và io_type_lech_bank cần Fact chân kit. Không kho nào trong repo có Fact pin:tangnano20k.* hay khoá vccio — nên hôm nay chỉ 3 trong 5 luật của M3-18 kết luận được gì trên dữ liệu thật. Cùng hình dạng với luật ERC quá áp.
A45: Một bitstream cũ đã dựng với chân đồng hồ tự chọn | B45: blinky của du-lieu/riscv-tn20k-b — xem DEV-345 và README §8. Không sửa hiện vật cũ: đó là dữ liệu của những lượt đo đã chốt. Từ nay phép kiểm chặn trước nextpnr.
A46: Hai công cụ mới nhất chưa lượt Agent nào GỌI | B46: hdl.sensitivity và hdl.constraints_check: mã của cả hai đã chạy trên hiện vật thật, nhưng đó là tôi gọi hàm, không phải tác tử gọi công cụ. README §8 đếm cả hai vào phần chưa dùng thật.
A48: Lỗi tìm thấy trong CHÍNH PHÉP ĐO của tôi | B48: Lộ ra ở đâu
A49: Kịch bản đo bị hàng rào của sản phẩm chặn (ghi tệp chưa đọc, E4020) và trả về một con số hợp lý thay vì nổ — 6→2 trông đẹp y như 9→3 đúng | B49: M2-01 · DEV-333
... A61: Một ca kiểm và một phép phá nhắm hai NHÁNH khác nhau, nên ca mới xanh mà phép phá vẫn LỌT. Mất một lượt mới thấy. | B61: M3-18 · DEV-345

Sheet Tiến độ 08-10-2026 (chiều)
A1: TIẾN ĐỘ ĐỢT TỐI ƯU TÁC TỬ — chốt chiều 08/10/2026
A2: Mỗi dòng 'Xong' đều có: mục DEV-LOG tra lại được · số ca kiểm trước→sau · một con số đo trên dữ liệu thật · phần còn nợ. Cột chi tiết nằm ở sheet “Danh mục tối ưu”, cột T–Y.
A4: Tổng quan | B4: Số việc | C4: Ghi chú
A5: Xong (đã gộp vào main, đã đẩy) | B5: 17 | C5: 17 việc đầu của Giai đoạn 1, theo đúng thứ tự # của kế hoạch
A6: Đang làm (chưa commit) | B6: 0 | C6: không việc nào đang dở
A7: Chưa làm | B7: 89 | C7: 89 việc còn lại trong 106
A8: TỔNG | B8: 106
A10: Phép đo của cả đợt | B10: Trước (06/10) | C10: Sau (08/10) | D10: Ghi chú
A11: Ca đơn vị Python (pytest -q) | B11: 1 610 | C11: 1 791 | D11: +181 ca so với 06/10; không ca cũ nào đỏ ở bất kỳ bước nào
A12: Ca đơn vị giao diện (swift test) | B12: 43 | C12: 43 | D12: không nhiệm vụ nào đụng ui/ — kiểu khối A2.2 dùng “table”, Swift đã dựng được
A13: kiem_tai_lieu.py | B13: 0 chỗ lệch | C13: 0 chỗ lệch | D13: 0 chỗ LỆCH CHẮC CHẮN cả hai lượt. Hôm nay nó bắt đúng chuyện cần bắt: hai công cụ mới làm README lệch số công cụ 127 → 129, và số 'cần đọc lại' nhảy 11 → 15 → về 11 sau khi sửa
A14: thu_sch.py (cờ schematic bật) | B14: 63/63 | C14: 63/63 | D14: chạy ở M3-03 và M3-04, không tụt
A15: Mục DEV-LOG mới | B15: — | C15: DEV-330 → DEV-346 | D15: 17 mục, mỗi việc một mục
A16: Cờ tính năng mới | B16: 1 (schematic) | C16: 7 | D16: 6 cờ mới, TẤT CẢ mặc định TẮT
A17: Mã lỗi mới | B17: — | C17: E4031 · E4032 · E6012 · E4033 · E4024 | D17: E4033 (M3-18) và E4024 (M4-01). M4-01 còn DÙNG LẠI E4008/E4009/E4023 của sim.run — cùng một chuyện thì cùng một mã, một mã mới cho cùng một chuyện là bắt người đọc học hai lần
A19: # | B19: Mã | C19: Mảng | D19: Ưu tiên | E19: DEV-LOG | F19: Ca kiểm | G19: Cờ mặc định
A20: 1 | B20: M1-01 | C20: 1. Lõi tác tử | D20: P0 | E20: DEV-330 | F20: 105/309 phiên thật có lịch sử tự mâu thuẫn — 255 chỗ (156 kết quả thứ hai cùng id, 74 message chen giữa, 24 kết quả lạc lượt, 1 lời gọi không kết quả) | G20: không có cờ — sửa lỗi thuần
A21: 2 | B21: M1-02 | C21: 1. Lõi tác tử | D21: P0 | E21: DEV-331 | F21: lược đồ công cụ thật: 25 869 token/lời gọi (trần tool_schema=4000 chưa dòng mã nào đọc). Cờ bật: 4 475 token, giảm 82,7 %; 73 → 18 công cụ | G21: GON_CONG_CU — TẮT
A22: 3 | B22: M1-03 | C22: 1. Lõi tác tử | D22: P0 | E22: DEV-332 | F22: 1 822 lời gọi của tác tử con trong 26 phiên thật, 0 lần qua lớp luật. Toàn công cụ đọc trừ một build.compile — lỗ hổng chưa bị bước vào, không phải được canh | G22: không có cờ — sửa lỗi thuần
A23: 4 | B23: M2-01 | C23: 2. Phân tích & thiết kế phần mềm | D23: P0 | E23: DEV-333 | F23: kịch bản 3 REQ + 3 phương án + 3 tiêu chí + 3 tệp: sửa MỘT REQ làm 9 hiện vật STALE → còn 3. Phép đo đầu ra 6→2 vì bị hàng rào E4020 chặn, đã sửa kịch bản đo | G23: TRUY_VET — TẮT (phần nền chạy cả khi tắt)
A24: 5 | B24: M2-02 | C24: 2. Phân tích & thiết kế phần mềm | D24: P0 | E24: DEV-334 | F24: 63 kho thật: 5/37 REQ có ít nhất một phép đo; 27 chưa có phương án nào nhận; 0 REQ đi hết chuỗi. Cột 'Mã nguồn' trống ở MỌI dự án vì hien_thuc_req vừa mới tồn tại | G24: REQ_PHU — TẮT (khối A2.2 trên tab không phụ thuộc cờ)
A25: 6 | B25: M2-03 | C25: 2. Phân tích & thiết kế phần mềm | D25: P0 | E25: DEV-335 | F25: 37 REQ thật: 25 sạch (67 %), 11 thiếu tiêu chí đo được, 2 có từ mơ hồ. Lần đo đầu ra 3 từ mơ hồ, một là kêu oan ('ít nhất 2 lần' là mức đo được) — đã vá | G25: REQ_CHAT_LUONG — TẮT (module yeu_cau.py luôn có)
A26: 7 | B26: M2-06 | C26: 2. Phân tích & thiết kế phần mềm | D26: P0 | E26: DEV-336 | F26: sổ cái thật: 26 lần đánh dấu 'xong' ngay sau một lần ghi mã, 19 lần (73 %) không có phép kiểm nào đạt ở giữa. Phép đo đầu ở mức dự án ra 0 — đúng nhưng đo sai câu hỏi | G26: KE_HOACH_CONG_KIEM — TẮT
A27: 8 | B27: M2-08 | C27: 2. Phân tích & thiết kế phần mềm | D27: P0 | E27: DEV-337 | F27: 185 tệp .c thật: 1 758 → 1 786 hàm thấy được (+28 hàm trước đây VÔ HÌNH: 8 ngắt + 20 bị regex tham lam nuốt). 78 hàm nay gắn nhãn 'isr', 70 trong đó vốn đã có trong danh sách | G27: không có cờ — sửa lỗi thuần
A28: 9 | B28: M3-01 | C28: 3. Mạch, ERC, HDL/FPGA | D28: P0 | E28: DEV-338 | F28: 0 phát hiện trên 5 mô hình mạch thật — và lý do đáng hơn con số: 3 kho CÓ Fact v_max thì KHÔNG có mô hình mạch, 5 kho có mạch thì không có Fact ấy; thêm nữa Fact dùng chủ thể chip:X mà ERC không tra tiền tố đó | G28: không có cờ — sửa lỗi thuần
A29: 10 | B29: M3-03 | C29: 3. Mạch, ERC, HDL/FPGA | D29: P0 | E29: DEV-339 | F29: 8 phát hiện trên 5 mạch thật (6 nguon_khong_cap + 2 net_mot_chan), trong đó net clock I2C nối đúng một chân. SÁU trong tám là 'mô hình chưa khai' chứ không phải 'mạch sai'. robot-canbang: 107 Port lá, KHÔNG Port nào là power_out | G29: không có cờ — sửa lỗi thuần
A30: 11 | B30: M3-04 | C30: 3. Mạch, ERC, HDL/FPGA | D30: P0 | E30: DEV-340 | F30: 0 phát hiện trên 5 mạch thật — và đây là con số ĐÚNG (hai lỗi này catastrophic, không bo nào sống tới lúc lưu kho). Đã CẤY hai bộ cấp vào bản sao kho robot-canbang để chứng minh luật sống: nổ đúng 1 blocker trên net +5V thật | G30: không có cờ — sửa lỗi thuần
A31: 12 | B31: M3-07 | C31: 3. Mạch, ERC, HDL/FPGA | D31: P0 | E31: DEV-341 | F31: Fact tới được ERC: 5 → 17 (+12). Ba kho có Fact datasheet thì TOÀN BỘ mang chủ thể chip:, tức trước đó không một Fact nào tới được ERC. Độ phủ 5 mạch thật nay đọc được | G31: không có cờ — sửa lỗi thuần
... A34: 15 | B34: M3-13 | C34: 3. Mạch, ERC, HDL/FPGA | D34: P0 | E34: DEV-344 | F34: testbench Verilog THẬT của bài 3: tb_pcpi_dot4 1/1, tb_pcpi_mac 1/1, tb_pcpi_vmini không đo được (tb gọi bản bram HAI CỔNG đã bị bỏ 02/10) — mẫu số là TỆP, không phải phép phá | G34: không có cờ (công cụ mới core=False)
A35: 16 | B35: M3-18 | C35: 3. Mạch, ERC, HDL/FPGA | D35: P0 | E35: DEV-345 | F35: 6 cặp (mạng cổng, .cst) thật → 1 chỗ CHẶN: blinky của riscv-tn20k-b dựng bitstream 4,6 MB với chân đồng hồ do nextpnr tự chọn (rơi đúng chân 4 — bằng may). Cả 7 tệp .cst thật đọc hết, 0 lỗi cú pháp | G35: không có cờ (công cụ mới core=False)
A36: 17 | B36: M4-01 | C36: 4. Kiểm thử & chất lượng | D36: P0 | E36: DEV-346 | F36: 18 ca chạy trình biên dịch C thật: tệp test in số đo {"T1":300} với ngưỡng <=255 → EIDE phán 1 ca HỎNG. Chưa kho cũ nào có tiêu chí unit test để đo lại trên dữ liệu thật | G36: không có cờ (công cụ mới core=False)
A38: Việc còn MỞ (ngoài 89 việc chưa làm) | B38: Vì sao còn mở
A39: Sáu cờ mới đều còn TẮT | B39: GON_CONG_CU · TRUY_VET · REQ_PHU · REQ_CHAT_LUONG · KE_HOACH_CONG_KIEM · ERC_TU_DONG. Cả sáu đổi thứ Agent nhìn thấy hoặc đọc mỗi lượt, nên chỉ bộ 76 ca chạy HAI chế độ mới nói được chúng làm Agent khá hơn hay tệ hơn — bộ ấy tốn tiền mô hình nên chưa chạy.
A40: kiem_cap_goi_tra() chưa thành hàng rào | B40: Soát được mọi phiên đã lưu, nhưng chưa hook nào gọi nó tự động — bắt được chuyện cũ, chưa chặn được chuyện mới.
A41: Luật ERC quá áp chưa nổ trên dữ liệu thật | B41: Đường dẫn đã thông ở M3-07, nhưng ba kho có Fact điện áp thì không có mô hình mạch, và ngược lại. Phải chờ một dự án có cả hai.
A42: Cột “Mã nguồn” của ma trận truy vết trống ở mọi dự án | B42: Nó đọc hien_thuc_req — trường vừa mới tồn tại, chưa tệp nào trên đĩa từng khai. Nên “chưa hiện thực” ở đó nghĩa là “chưa ai KHAI”, không phải “chưa ai viết”.
A43: Lỗi _go_dau trong src/eide/tools/design.py | B43: Viết .replace('d','d') nên 'ổn định' và 'ON DINH' không khớp nhau. Hàm ấy đang dùng cho một phép kiểm an toàn (người có thật sự chọn không). Tìm thấy ở M2-03, CHƯA sửa vì ngoài phạm vi — cần bộ ca kiểm riêng.
A44: subagent req-critic (bước 4 của M2-03) | B44: Kế hoạch ghi “tuỳ chọn, gộp M2-13”. Chưa làm, đúng theo kế hoạch.
A45: Hai luật kiểm chân FPGA chưa có dữ liệu để nổ | B45: chan_lech_kit và io_type_lech_bank cần Fact chân kit. Không kho nào trong repo có Fact pin:tangnano20k.* hay khoá vccio — nên hôm nay chỉ 3 trong 5 luật của M3-18 kết luận được gì trên dữ liệu thật. Cùng hình dạng với luật ERC quá áp.
A46: Một bitstream cũ đã dựng với chân đồng hồ tự chọn | B46: blinky của du-lieu/riscv-tn20k-b — xem DEV-345 và README §8. Không sửa hiện vật cũ: đó là dữ liệu của những lượt đo đã chốt. Từ nay phép kiểm chặn trước nextpnr.
A47: Ba công cụ mới nhất chưa lượt Agent nào GỌI | B47: hdl.sensitivity · hdl.constraints_check · test.criteria. Mã của cả ba đã chạy trên hiện vật thật, nhưng đó là tôi gọi hàm, không phải tác tử gọi công cụ. README §8 đếm cả ba vào phần chưa dùng thật.
A49: Lỗi tìm thấy trong CHÍNH PHÉP ĐO của tôi | B49: Lộ ra ở đâu
A50: Kịch bản đo bị hàng rào của sản phẩm chặn (ghi tệp chưa đọc, E4020) và trả về một con số hợp lý thay vì nổ — 6→2 trông đẹp y như 9→3 đúng | B50: M2-01 · DEV-333
... A64: Một phép phá VÔ HIỆU: `them = [] or [[…]]` không đổi hành vi, nên nó báo LỌT oan và suýt làm tôi viết ca kiểm cho một chỗ vốn đã được canh. | B64: M4-01 · DEV-346

Sheet Tiến độ 08-10-2026 (toi)
A1: TIẾN ĐỘ ĐỢT TỐI ƯU TÁC TỬ — chốt tối 08/10/2026
A2: Mỗi dòng 'Xong' đều có: mục DEV-LOG tra lại được · số ca kiểm trước→sau · một con số đo trên dữ liệu thật · phần còn nợ. Cột chi tiết nằm ở sheet “Danh mục tối ưu”, cột T–Y.
A4: Tổng quan | B4: Số việc | C4: Ghi chú
A5: Xong (đã gộp vào main, đã đẩy) | B5: 18 | C5: 18 việc đầu của Giai đoạn 1, theo đúng thứ tự # của kế hoạch
A6: Đang làm (chưa commit) | B6: 0 | C6: không việc nào đang dở
A7: Chưa làm | B7: 88 | C7: 88 việc còn lại trong 106
A8: TỔNG | B8: 106
A10: Phép đo của cả đợt | B10: Trước (06/10) | C10: Sau (08/10) | D10: Ghi chú
A11: Ca đơn vị Python (pytest -q) | B11: 1 610 | C11: 1 816 | D11: +206 ca so với 06/10; không ca cũ nào đỏ ở bất kỳ bước nào
A12: Ca đơn vị giao diện (swift test) | B12: 43 | C12: 43 | D12: không nhiệm vụ nào đụng ui/ — kiểu khối A2.2 dùng “table”, Swift đã dựng được
A13: kiem_tai_lieu.py | B13: 0 chỗ lệch | C13: 0 chỗ lệch | D13: 0 chỗ LỆCH CHẮC CHẮN cả hai lượt. Hôm nay nó bắt đúng chuyện cần bắt: hai công cụ mới làm README lệch số công cụ 127 → 129, và số 'cần đọc lại' nhảy 11 → 15 → về 11 sau khi sửa
A14: thu_sch.py (cờ schematic bật) | B14: 63/63 | C14: 63/63 | D14: chạy ở M3-03 và M3-04, không tụt
A15: Mục DEV-LOG mới | B15: — | C15: DEV-330 → DEV-347 | D15: 18 mục, mỗi việc một mục
A16: Cờ tính năng mới | B16: 1 (schematic) | C16: 8 | D16: 7 cờ mới, TẤT CẢ mặc định TẮT. Cờ thứ 7 là SIM_RUNNER_GIOI_HAN (M4-02) — nó giới hạn fs.write của sim-runner trong sim/; hàng rào chính của M4-02 (POL-N6-sua-test) thì KHÔNG sau cờ
A17: Mã lỗi mới | B17: — | C17: E4031 · E4032 · E6012 · E4033 · E4024 | D17: M4-02 không thêm mã nào: nó DÙNG LẠI E5006 cho cổng ghi của sim-runner. E4033 (M3-18), E4024 (M4-01)
A19: # | B19: Mã | C19: Mảng | D19: Ưu tiên | E19: DEV-LOG | F19: Ca kiểm | G19: Cờ mặc định
A20: 1 | B20: M1-01 | C20: 1. Lõi tác tử | D20: P0 | E20: DEV-330 | F20: 105/309 phiên thật có lịch sử tự mâu thuẫn — 255 chỗ (156 kết quả thứ hai cùng id, 74 message chen giữa, 24 kết quả lạc lượt, 1 lời gọi không kết quả) | G20: không có cờ — sửa lỗi thuần
A21: 2 | B21: M1-02 | C21: 1. Lõi tác tử | D21: P0 | E21: DEV-331 | F21: lược đồ công cụ thật: 25 869 token/lời gọi (trần tool_schema=4000 chưa dòng mã nào đọc). Cờ bật: 4 475 token, giảm 82,7 %; 73 → 18 công cụ | G21: GON_CONG_CU — TẮT
A22: 3 | B22: M1-03 | C22: 1. Lõi tác tử | D22: P0 | E22: DEV-332 | F22: 1 822 lời gọi của tác tử con trong 26 phiên thật, 0 lần qua lớp luật. Toàn công cụ đọc trừ một build.compile — lỗ hổng chưa bị bước vào, không phải được canh | G22: không có cờ — sửa lỗi thuần
A23: 4 | B23: M2-01 | C23: 2. Phân tích & thiết kế phần mềm | D23: P0 | E23: DEV-333 | F23: kịch bản 3 REQ + 3 phương án + 3 tiêu chí + 3 tệp: sửa MỘT REQ làm 9 hiện vật STALE → còn 3. Phép đo đầu ra 6→2 vì bị hàng rào E4020 chặn, đã sửa kịch bản đo | G23: TRUY_VET — TẮT (phần nền chạy cả khi tắt)
A24: 5 | B24: M2-02 | C24: 2. Phân tích & thiết kế phần mềm | D24: P0 | E24: DEV-334 | F24: 63 kho thật: 5/37 REQ có ít nhất một phép đo; 27 chưa có phương án nào nhận; 0 REQ đi hết chuỗi. Cột 'Mã nguồn' trống ở MỌI dự án vì hien_thuc_req vừa mới tồn tại | G24: REQ_PHU — TẮT (khối A2.2 trên tab không phụ thuộc cờ)
A25: 6 | B25: M2-03 | C25: 2. Phân tích & thiết kế phần mềm | D25: P0 | E25: DEV-335 | F25: 37 REQ thật: 25 sạch (67 %), 11 thiếu tiêu chí đo được, 2 có từ mơ hồ. Lần đo đầu ra 3 từ mơ hồ, một là kêu oan ('ít nhất 2 lần' là mức đo được) — đã vá | G25: REQ_CHAT_LUONG — TẮT (module yeu_cau.py luôn có)
A26: 7 | B26: M2-06 | C26: 2. Phân tích & thiết kế phần mềm | D26: P0 | E26: DEV-336 | F26: sổ cái thật: 26 lần đánh dấu 'xong' ngay sau một lần ghi mã, 19 lần (73 %) không có phép kiểm nào đạt ở giữa. Phép đo đầu ở mức dự án ra 0 — đúng nhưng đo sai câu hỏi | G26: KE_HOACH_CONG_KIEM — TẮT
A27: 8 | B27: M2-08 | C27: 2. Phân tích & thiết kế phần mềm | D27: P0 | E27: DEV-337 | F27: 185 tệp .c thật: 1 758 → 1 786 hàm thấy được (+28 hàm trước đây VÔ HÌNH: 8 ngắt + 20 bị regex tham lam nuốt). 78 hàm nay gắn nhãn 'isr', 70 trong đó vốn đã có trong danh sách | G27: không có cờ — sửa lỗi thuần
A28: 9 | B28: M3-01 | C28: 3. Mạch, ERC, HDL/FPGA | D28: P0 | E28: DEV-338 | F28: 0 phát hiện trên 5 mô hình mạch thật — và lý do đáng hơn con số: 3 kho CÓ Fact v_max thì KHÔNG có mô hình mạch, 5 kho có mạch thì không có Fact ấy; thêm nữa Fact dùng chủ thể chip:X mà ERC không tra tiền tố đó | G28: không có cờ — sửa lỗi thuần
A29: 10 | B29: M3-03 | C29: 3. Mạch, ERC, HDL/FPGA | D29: P0 | E29: DEV-339 | F29: 8 phát hiện trên 5 mạch thật (6 nguon_khong_cap + 2 net_mot_chan), trong đó net clock I2C nối đúng một chân. SÁU trong tám là 'mô hình chưa khai' chứ không phải 'mạch sai'. robot-canbang: 107 Port lá, KHÔNG Port nào là power_out | G29: không có cờ — sửa lỗi thuần
A30: 11 | B30: M3-04 | C30: 3. Mạch, ERC, HDL/FPGA | D30: P0 | E30: DEV-340 | F30: 0 phát hiện trên 5 mạch thật — và đây là con số ĐÚNG (hai lỗi này catastrophic, không bo nào sống tới lúc lưu kho). Đã CẤY hai bộ cấp vào bản sao kho robot-canbang để chứng minh luật sống: nổ đúng 1 blocker trên net +5V thật | G30: không có cờ — sửa lỗi thuần
A31: 12 | B31: M3-07 | C31: 3. Mạch, ERC, HDL/FPGA | D31: P0 | E31: DEV-341 | F31: Fact tới được ERC: 5 → 17 (+12). Ba kho có Fact datasheet thì TOÀN BỘ mang chủ thể chip:, tức trước đó không một Fact nào tới được ERC. Độ phủ 5 mạch thật nay đọc được | G31: không có cờ — sửa lỗi thuần
... A34: 15 | B34: M3-13 | C34: 3. Mạch, ERC, HDL/FPGA | D34: P0 | E34: DEV-344 | F34: testbench Verilog THẬT của bài 3: tb_pcpi_dot4 1/1, tb_pcpi_mac 1/1, tb_pcpi_vmini không đo được (tb gọi bản bram HAI CỔNG đã bị bỏ 02/10) — mẫu số là TỆP, không phải phép phá | G34: không có cờ (công cụ mới core=False)
A35: 16 | B35: M3-18 | C35: 3. Mạch, ERC, HDL/FPGA | D35: P0 | E35: DEV-345 | F35: 6 cặp (mạng cổng, .cst) thật → 1 chỗ CHẶN: blinky của riscv-tn20k-b dựng bitstream 4,6 MB với chân đồng hồ do nextpnr tự chọn (rơi đúng chân 4 — bằng may). Cả 7 tệp .cst thật đọc hết, 0 lỗi cú pháp | G35: không có cờ (công cụ mới core=False)
A36: 17 | B36: M4-01 | C36: 4. Kiểm thử & chất lượng | D36: P0 | E36: DEV-346 | F36: 18 ca chạy trình biên dịch C thật: tệp test in số đo {"T1":300} với ngưỡng <=255 → EIDE phán 1 ca HỎNG. Chưa kho cũ nào có tiêu chí unit test để đo lại trên dữ liệu thật | G36: không có cờ (công cụ mới core=False)
A37: 18 | B37: M4-02 | C37: 4. Kiểm thử & chất lượng | D37: P0 | E37: DEV-347 | F37: 25 ca dựng đúng trạng thái thật (tệp test 3 ca, 1 ca đỏ, hiện vật dat=False) → fs.write còn 1 ca thì test.weakened=True. Và hàng rào cũ criteria.has_result chưa bao giờ nổ ngoài sim-01 | G37: SIM_RUNNER_GIOI_HAN — TẮT
A39: Việc còn MỞ (ngoài 88 việc chưa làm) | B39: Vì sao còn mở
A40: Bảy cờ mới đều còn TẮT | B40: GON_CONG_CU · TRUY_VET · REQ_PHU · REQ_CHAT_LUONG · KE_HOACH_CONG_KIEM · ERC_TU_DONG · SIM_RUNNER_GIOI_HAN. Cả bảy đổi thứ Agent nhìn thấy, đọc, hoặc LÀM ĐƯỢC mỗi lượt, nên chỉ bộ 76 ca chạy hai chế độ mới nói được chúng làm Agent khá hơn hay tệ hơn. Bộ ấy tốn tiền mô hình nên §3.0 bắt hỏi người dùng trước.
A41: kiem_cap_goi_tra() chưa thành hàng rào | B41: Soát được mọi phiên đã lưu, nhưng chưa hook nào gọi nó tự động — bắt được chuyện cũ, chưa chặn được chuyện mới.
A42: Luật ERC quá áp chưa nổ trên dữ liệu thật | B42: Đường dẫn đã thông ở M3-07, nhưng ba kho có Fact điện áp thì không có mô hình mạch, và ngược lại. Phải chờ một dự án có cả hai.
A43: Cột “Mã nguồn” của ma trận truy vết trống ở mọi dự án | B43: Nó đọc hien_thuc_req — trường vừa mới tồn tại, chưa tệp nào trên đĩa từng khai. Nên “chưa hiện thực” ở đó nghĩa là “chưa ai KHAI”, không phải “chưa ai viết”.
A44: Lỗi _go_dau trong src/eide/tools/design.py | B44: Viết .replace('d','d') nên 'ổn định' và 'ON DINH' không khớp nhau. Hàm ấy đang dùng cho một phép kiểm an toàn (người có thật sự chọn không). Tìm thấy ở M2-03, CHƯA sửa vì ngoài phạm vi — cần bộ ca kiểm riêng.
A45: subagent req-critic (bước 4 của M2-03) | B45: Kế hoạch ghi “tuỳ chọn, gộp M2-13”. Chưa làm, đúng theo kế hoạch.
A46: Hai luật kiểm chân FPGA chưa có dữ liệu để nổ | B46: chan_lech_kit và io_type_lech_bank cần Fact chân kit. Không kho nào trong repo có Fact pin:tangnano20k.* hay khoá vccio — nên hôm nay chỉ 3 trong 5 luật của M3-18 kết luận được gì trên dữ liệu thật. Cùng hình dạng với luật ERC quá áp.
A47: Một bitstream cũ đã dựng với chân đồng hồ tự chọn | B47: blinky của du-lieu/riscv-tn20k-b — xem DEV-345 và README §8. Không sửa hiện vật cũ: đó là dữ liệu của những lượt đo đã chốt. Từ nay phép kiểm chặn trước nextpnr.
A48: Ba công cụ mới nhất chưa lượt Agent nào GỌI | B48: hdl.sensitivity · hdl.constraints_check · test.criteria. Mã của cả ba đã chạy trên hiện vật thật, nhưng đó là tôi gọi hàm, không phải tác tử gọi công cụ. README §8 đếm cả ba vào phần chưa dùng thật.
A49: POL-N6-sua-test chưa nổ trên một phiên thật nào | B49: Hook sua_test_sau_do cấp dữ kiện cho lời gọi SẮP xảy ra, nên không soát lại được phiên đã lưu — khác mọi phép đo trước của đợt này. Nó đã có 25 ca kiểm và phá lại 27/27, nhưng chưa lượt tác tử thật nào chạm vào nó. Cùng hình dạng với ba luật kiểm thiếu dữ liệu ở trên, chỉ khác lý do.
A51: Lỗi tìm thấy trong CHÍNH PHÉP ĐO của tôi | B51: Lộ ra ở đâu
... A68: Một luật mới trỏ tới nhóm dữ kiện chưa khai thì DỪNG CẢ LƯỢT bằng ValueError, không phải 'không nổ' — và nhóm `criteria` của hàng rào N6 cũ cũng chưa bao giờ được khai. | B68: M4-02 · DEV-347

Sheet Tiến độ 08-10-2026 (khuya)
A1: TIẾN ĐỘ ĐỢT TỐI ƯU TÁC TỬ — chốt khuya 08/10/2026
A2: Mỗi dòng 'Xong' đều có: mục DEV-LOG tra lại được · số ca kiểm trước→sau · một con số đo trên dữ liệu thật · phần còn nợ. Cột chi tiết nằm ở sheet “Danh mục tối ưu”, cột T–Y.
A4: Tổng quan | B4: Số việc | C4: Ghi chú
A5: Xong (đã gộp vào main, đã đẩy) | B5: 19 | C5: 19 việc đầu của Giai đoạn 1, theo đúng thứ tự # của kế hoạch
A6: Đang làm (chưa commit) | B6: 0 | C6: không việc nào đang dở
A7: Chưa làm | B7: 87 | C7: 87 việc còn lại trong 106
A8: TỔNG | B8: 106
A10: Phép đo của cả đợt | B10: Trước (06/10) | C10: Sau (08/10) | D10: Ghi chú
A11: Ca đơn vị Python (pytest -q) | B11: 1 610 | C11: 1 835 | D11: +225 ca so với 06/10; không ca cũ nào đỏ ở bất kỳ bước nào
A12: Ca đơn vị giao diện (swift test) | B12: 43 | C12: 43 | D12: không nhiệm vụ nào đụng ui/ — kiểu khối A2.2 dùng “table”, Swift đã dựng được
A13: kiem_tai_lieu.py | B13: 0 chỗ lệch | C13: 0 chỗ lệch | D13: 0 chỗ LỆCH CHẮC CHẮN cả hai lượt. Hôm nay nó bắt đúng chuyện cần bắt: hai công cụ mới làm README lệch số công cụ 127 → 129, và số 'cần đọc lại' nhảy 11 → 15 → về 11 sau khi sửa
A14: thu_sch.py (cờ schematic bật) | B14: 63/63 | C14: 63/63 | D14: chạy ở M3-03 và M3-04, không tụt
A15: Mục DEV-LOG mới | B15: — | C15: DEV-330 → DEV-348 | D15: 19 mục, mỗi việc một mục
A16: Cờ tính năng mới | B16: 1 (schematic) | C16: 8 | D16: 7 cờ mới, TẤT CẢ mặc định TẮT. Cờ thứ 7 là SIM_RUNNER_GIOI_HAN (M4-02) — nó giới hạn fs.write của sim-runner trong sim/; hàng rào chính của M4-02 (POL-N6-sua-test) thì KHÔNG sau cờ
A17: Mã lỗi mới | B17: — | C17: E4031 · E4032 · E6012 · E4033 · E4024 | D17: M4-05 không thêm mã nào. M4-02 cũng không (dùng lại E5006). E4033 (M3-18), E4024 (M4-01)
A19: # | B19: Mã | C19: Mảng | D19: Ưu tiên | E19: DEV-LOG | F19: Ca kiểm | G19: Cờ mặc định
A20: 1 | B20: M1-01 | C20: 1. Lõi tác tử | D20: P0 | E20: DEV-330 | F20: 105/309 phiên thật có lịch sử tự mâu thuẫn — 255 chỗ (156 kết quả thứ hai cùng id, 74 message chen giữa, 24 kết quả lạc lượt, 1 lời gọi không kết quả) | G20: không có cờ — sửa lỗi thuần
A21: 2 | B21: M1-02 | C21: 1. Lõi tác tử | D21: P0 | E21: DEV-331 | F21: lược đồ công cụ thật: 25 869 token/lời gọi (trần tool_schema=4000 chưa dòng mã nào đọc). Cờ bật: 4 475 token, giảm 82,7 %; 73 → 18 công cụ | G21: GON_CONG_CU — TẮT
A22: 3 | B22: M1-03 | C22: 1. Lõi tác tử | D22: P0 | E22: DEV-332 | F22: 1 822 lời gọi của tác tử con trong 26 phiên thật, 0 lần qua lớp luật. Toàn công cụ đọc trừ một build.compile — lỗ hổng chưa bị bước vào, không phải được canh | G22: không có cờ — sửa lỗi thuần
A23: 4 | B23: M2-01 | C23: 2. Phân tích & thiết kế phần mềm | D23: P0 | E23: DEV-333 | F23: kịch bản 3 REQ + 3 phương án + 3 tiêu chí + 3 tệp: sửa MỘT REQ làm 9 hiện vật STALE → còn 3. Phép đo đầu ra 6→2 vì bị hàng rào E4020 chặn, đã sửa kịch bản đo | G23: TRUY_VET — TẮT (phần nền chạy cả khi tắt)
A24: 5 | B24: M2-02 | C24: 2. Phân tích & thiết kế phần mềm | D24: P0 | E24: DEV-334 | F24: 63 kho thật: 5/37 REQ có ít nhất một phép đo; 27 chưa có phương án nào nhận; 0 REQ đi hết chuỗi. Cột 'Mã nguồn' trống ở MỌI dự án vì hien_thuc_req vừa mới tồn tại | G24: REQ_PHU — TẮT (khối A2.2 trên tab không phụ thuộc cờ)
A25: 6 | B25: M2-03 | C25: 2. Phân tích & thiết kế phần mềm | D25: P0 | E25: DEV-335 | F25: 37 REQ thật: 25 sạch (67 %), 11 thiếu tiêu chí đo được, 2 có từ mơ hồ. Lần đo đầu ra 3 từ mơ hồ, một là kêu oan ('ít nhất 2 lần' là mức đo được) — đã vá | G25: REQ_CHAT_LUONG — TẮT (module yeu_cau.py luôn có)
A26: 7 | B26: M2-06 | C26: 2. Phân tích & thiết kế phần mềm | D26: P0 | E26: DEV-336 | F26: sổ cái thật: 26 lần đánh dấu 'xong' ngay sau một lần ghi mã, 19 lần (73 %) không có phép kiểm nào đạt ở giữa. Phép đo đầu ở mức dự án ra 0 — đúng nhưng đo sai câu hỏi | G26: KE_HOACH_CONG_KIEM — TẮT
A27: 8 | B27: M2-08 | C27: 2. Phân tích & thiết kế phần mềm | D27: P0 | E27: DEV-337 | F27: 185 tệp .c thật: 1 758 → 1 786 hàm thấy được (+28 hàm trước đây VÔ HÌNH: 8 ngắt + 20 bị regex tham lam nuốt). 78 hàm nay gắn nhãn 'isr', 70 trong đó vốn đã có trong danh sách | G27: không có cờ — sửa lỗi thuần
A28: 9 | B28: M3-01 | C28: 3. Mạch, ERC, HDL/FPGA | D28: P0 | E28: DEV-338 | F28: 0 phát hiện trên 5 mô hình mạch thật — và lý do đáng hơn con số: 3 kho CÓ Fact v_max thì KHÔNG có mô hình mạch, 5 kho có mạch thì không có Fact ấy; thêm nữa Fact dùng chủ thể chip:X mà ERC không tra tiền tố đó | G28: không có cờ — sửa lỗi thuần
A29: 10 | B29: M3-03 | C29: 3. Mạch, ERC, HDL/FPGA | D29: P0 | E29: DEV-339 | F29: 8 phát hiện trên 5 mạch thật (6 nguon_khong_cap + 2 net_mot_chan), trong đó net clock I2C nối đúng một chân. SÁU trong tám là 'mô hình chưa khai' chứ không phải 'mạch sai'. robot-canbang: 107 Port lá, KHÔNG Port nào là power_out | G29: không có cờ — sửa lỗi thuần
A30: 11 | B30: M3-04 | C30: 3. Mạch, ERC, HDL/FPGA | D30: P0 | E30: DEV-340 | F30: 0 phát hiện trên 5 mạch thật — và đây là con số ĐÚNG (hai lỗi này catastrophic, không bo nào sống tới lúc lưu kho). Đã CẤY hai bộ cấp vào bản sao kho robot-canbang để chứng minh luật sống: nổ đúng 1 blocker trên net +5V thật | G30: không có cờ — sửa lỗi thuần
A31: 12 | B31: M3-07 | C31: 3. Mạch, ERC, HDL/FPGA | D31: P0 | E31: DEV-341 | F31: Fact tới được ERC: 5 → 17 (+12). Ba kho có Fact datasheet thì TOÀN BỘ mang chủ thể chip:, tức trước đó không một Fact nào tới được ERC. Độ phủ 5 mạch thật nay đọc được | G31: không có cờ — sửa lỗi thuần
... A34: 15 | B34: M3-13 | C34: 3. Mạch, ERC, HDL/FPGA | D34: P0 | E34: DEV-344 | F34: testbench Verilog THẬT của bài 3: tb_pcpi_dot4 1/1, tb_pcpi_mac 1/1, tb_pcpi_vmini không đo được (tb gọi bản bram HAI CỔNG đã bị bỏ 02/10) — mẫu số là TỆP, không phải phép phá | G34: không có cờ (công cụ mới core=False)
A35: 16 | B35: M3-18 | C35: 3. Mạch, ERC, HDL/FPGA | D35: P0 | E35: DEV-345 | F35: 6 cặp (mạng cổng, .cst) thật → 1 chỗ CHẶN: blinky của riscv-tn20k-b dựng bitstream 4,6 MB với chân đồng hồ do nextpnr tự chọn (rơi đúng chân 4 — bằng may). Cả 7 tệp .cst thật đọc hết, 0 lỗi cú pháp | G35: không có cờ (công cụ mới core=False)
A36: 17 | B36: M4-01 | C36: 4. Kiểm thử & chất lượng | D36: P0 | E36: DEV-346 | F36: 18 ca chạy trình biên dịch C thật: tệp test in số đo {"T1":300} với ngưỡng <=255 → EIDE phán 1 ca HỎNG. Chưa kho cũ nào có tiêu chí unit test để đo lại trên dữ liệu thật | G36: không có cờ (công cụ mới core=False)
A37: 18 | B37: M4-02 | C37: 4. Kiểm thử & chất lượng | D37: P0 | E37: DEV-347 | F37: 25 ca dựng đúng trạng thái thật (tệp test 3 ca, 1 ca đỏ, hiện vật dat=False) → fs.write còn 1 ca thì test.weakened=True. Và hàng rào cũ criteria.has_result chưa bao giờ nổ ngoài sim-01 | G37: SIM_RUNNER_GIOI_HAN — TẮT
A38: 19 | B38: M4-05 | C38: 4. Kiểm thử & chất lượng | D38: P1 | E38: DEV-348 | F38: du-lieu/rtos-sinhvien, chạy CẢ HAI hành vi: cũ so_thay=1, mới so_thay=0 — logo_ptit.c từ 'bộ kiểm ĐỎ' thành 'mọi đột biến đều làm hỏng biên dịch'. Một ô xanh giả, đã sửa | G38: không có cờ — sửa lỗi thuần
A40: Việc còn MỞ (ngoài 87 việc chưa làm) | B40: Vì sao còn mở
A41: Bảy cờ mới đều còn TẮT | B41: GON_CONG_CU · TRUY_VET · REQ_PHU · REQ_CHAT_LUONG · KE_HOACH_CONG_KIEM · ERC_TU_DONG · SIM_RUNNER_GIOI_HAN. Cả bảy đổi thứ Agent nhìn thấy, đọc, hoặc LÀM ĐƯỢC mỗi lượt, nên chỉ bộ 76 ca chạy hai chế độ mới nói được chúng làm Agent khá hơn hay tệ hơn. Bộ ấy tốn tiền mô hình nên §3.0 bắt hỏi người dùng trước.
A42: kiem_cap_goi_tra() chưa thành hàng rào | B42: Soát được mọi phiên đã lưu, nhưng chưa hook nào gọi nó tự động — bắt được chuyện cũ, chưa chặn được chuyện mới.
A43: Luật ERC quá áp chưa nổ trên dữ liệu thật | B43: Đường dẫn đã thông ở M3-07, nhưng ba kho có Fact điện áp thì không có mô hình mạch, và ngược lại. Phải chờ một dự án có cả hai.
A44: Cột “Mã nguồn” của ma trận truy vết trống ở mọi dự án | B44: Nó đọc hien_thuc_req — trường vừa mới tồn tại, chưa tệp nào trên đĩa từng khai. Nên “chưa hiện thực” ở đó nghĩa là “chưa ai KHAI”, không phải “chưa ai viết”.
A45: Lỗi _go_dau trong src/eide/tools/design.py | B45: Viết .replace('d','d') nên 'ổn định' và 'ON DINH' không khớp nhau. Hàm ấy đang dùng cho một phép kiểm an toàn (người có thật sự chọn không). Tìm thấy ở M2-03, CHƯA sửa vì ngoài phạm vi — cần bộ ca kiểm riêng.
A46: subagent req-critic (bước 4 của M2-03) | B46: Kế hoạch ghi “tuỳ chọn, gộp M2-13”. Chưa làm, đúng theo kế hoạch.
A47: Hai luật kiểm chân FPGA chưa có dữ liệu để nổ | B47: chan_lech_kit và io_type_lech_bank cần Fact chân kit. Không kho nào trong repo có Fact pin:tangnano20k.* hay khoá vccio — nên hôm nay chỉ 3 trong 5 luật của M3-18 kết luận được gì trên dữ liệu thật. Cùng hình dạng với luật ERC quá áp.
A48: Một bitstream cũ đã dựng với chân đồng hồ tự chọn | B48: blinky của du-lieu/riscv-tn20k-b — xem DEV-345 và README §8. Không sửa hiện vật cũ: đó là dữ liệu của những lượt đo đã chốt. Từ nay phép kiểm chặn trước nextpnr.
A49: Ba công cụ mới nhất chưa lượt Agent nào GỌI | B49: hdl.sensitivity · hdl.constraints_check · test.criteria. Mã của cả ba đã chạy trên hiện vật thật, nhưng đó là tôi gọi hàm, không phải tác tử gọi công cụ. README §8 đếm cả ba vào phần chưa dùng thật.
A50: Bộ kiểm C của ba dự án firmware thật đều KHÔNG đo được độ nhạy | B50: rtos-sinhvien: 0/12 tệp đo được (4 font khong_thay, control_rtos.c trùng ký hiệu, main.c không dịch trên máy chủ, logo_ptit.c mọi mutant hỏng biên dịch). stm32f469-freertos và thu-nghiem-g6: bộ kiểm ĐỎ SẴN. Đây là trạng thái của dữ liệu đo, không phải lỗi sản phẩm — nhưng nó nghĩa là chưa dự án firmware nào trong repo có một con số độ nhạy đáng tin. Xem DEV-348.
A51: POL-N6-sua-test chưa nổ trên một phiên thật nào | B51: Hook sua_test_sau_do cấp dữ kiện cho lời gọi SẮP xảy ra, nên không soát lại được phiên đã lưu — khác mọi phép đo trước của đợt này. Nó đã có 25 ca kiểm và phá lại 27/27, nhưng chưa lượt tác tử thật nào chạm vào nó. Cùng hình dạng với ba luật kiểm thiếu dữ liệu ở trên, chỉ khác lý do.
... A72: Bốn chỗ LỌT cùng một hình dạng: luật ĐÚNG, nằm ở chỗ ca kiểm không với tới — hai closure, một bảng phép không dựng nổi ca, và một tầng báo lại mà mọi ca cũ đều đi qua với stillborn == 0. | B72: M4-05 · DEV-348

Sheet Tiến độ 09-10-2026
A1: TIẾN ĐỘ ĐỢT TỐI ƯU TÁC TỬ — chốt ngày 09/10/2026
A2: Mỗi dòng 'Xong' đều có: mục DEV-LOG tra lại được · số ca kiểm trước→sau · một con số đo trên dữ liệu thật · phần còn nợ. Cột chi tiết nằm ở sheet “Danh mục tối ưu”, cột T–Y.
A4: Tổng quan | B4: Số việc | C4: Ghi chú
A5: Xong (đã gộp vào main, đã đẩy) | B5: 20 | C5: 20 việc đầu của Giai đoạn 1, theo đúng thứ tự # của kế hoạch
A6: Đang làm (chưa commit) | B6: 0 | C6: không việc nào đang dở
A7: Chưa làm | B7: 86 | C7: 86 việc còn lại trong 106
A8: TỔNG | B8: 106
A10: Phép đo của cả đợt | B10: Trước (06/10) | C10: Sau (08/10) | D10: Ghi chú
A11: Ca đơn vị Python (pytest -q) | B11: 1 610 | C11: 1 846 | D11: +236 ca so với 06/10; không ca cũ nào đỏ ở bất kỳ bước nào
A12: Ca đơn vị giao diện (swift test) | B12: 43 | C12: 43 | D12: không nhiệm vụ nào đụng ui/ — kiểu khối A2.2 dùng “table”, Swift đã dựng được
A13: kiem_tai_lieu.py | B13: 0 chỗ lệch | C13: 0 chỗ lệch | D13: 0 chỗ LỆCH CHẮC CHẮN cả hai lượt. Hôm nay nó bắt đúng chuyện cần bắt: hai công cụ mới làm README lệch số công cụ 127 → 129, và số 'cần đọc lại' nhảy 11 → 15 → về 11 sau khi sửa
A14: thu_sch.py (cờ schematic bật) | B14: 63/63 | C14: 63/63 | D14: chạy ở M3-03 và M3-04, không tụt
A15: Mục DEV-LOG mới | B15: — | C15: DEV-330 → DEV-349 | D15: 20 mục, mỗi việc một mục
A16: Cờ tính năng mới | B16: 1 (schematic) | C16: 8 | D16: 7 cờ mới, TẤT CẢ mặc định TẮT. Cờ thứ 7 là SIM_RUNNER_GIOI_HAN (M4-02) — nó giới hạn fs.write của sim-runner trong sim/; hàng rào chính của M4-02 (POL-N6-sua-test) thì KHÔNG sau cờ
A17: Mã lỗi mới | B17: — | C17: E4031 · E4032 · E6012 · E4033 · E4024 | D17: M4-05 không thêm mã nào. M4-02 cũng không (dùng lại E5006). E4033 (M3-18), E4024 (M4-01)
A19: # | B19: Mã | C19: Mảng | D19: Ưu tiên | E19: DEV-LOG | F19: Ca kiểm | G19: Cờ mặc định
A20: 1 | B20: M1-01 | C20: 1. Lõi tác tử | D20: P0 | E20: DEV-330 | F20: 105/309 phiên thật có lịch sử tự mâu thuẫn — 255 chỗ (156 kết quả thứ hai cùng id, 74 message chen giữa, 24 kết quả lạc lượt, 1 lời gọi không kết quả) | G20: không có cờ — sửa lỗi thuần
A21: 2 | B21: M1-02 | C21: 1. Lõi tác tử | D21: P0 | E21: DEV-331 | F21: lược đồ công cụ thật: 25 869 token/lời gọi (trần tool_schema=4000 chưa dòng mã nào đọc). Cờ bật: 4 475 token, giảm 82,7 %; 73 → 18 công cụ | G21: GON_CONG_CU — TẮT
A22: 3 | B22: M1-03 | C22: 1. Lõi tác tử | D22: P0 | E22: DEV-332 | F22: 1 822 lời gọi của tác tử con trong 26 phiên thật, 0 lần qua lớp luật. Toàn công cụ đọc trừ một build.compile — lỗ hổng chưa bị bước vào, không phải được canh | G22: không có cờ — sửa lỗi thuần
A23: 4 | B23: M2-01 | C23: 2. Phân tích & thiết kế phần mềm | D23: P0 | E23: DEV-333 | F23: kịch bản 3 REQ + 3 phương án + 3 tiêu chí + 3 tệp: sửa MỘT REQ làm 9 hiện vật STALE → còn 3. Phép đo đầu ra 6→2 vì bị hàng rào E4020 chặn, đã sửa kịch bản đo | G23: TRUY_VET — TẮT (phần nền chạy cả khi tắt)
A24: 5 | B24: M2-02 | C24: 2. Phân tích & thiết kế phần mềm | D24: P0 | E24: DEV-334 | F24: 63 kho thật: 5/37 REQ có ít nhất một phép đo; 27 chưa có phương án nào nhận; 0 REQ đi hết chuỗi. Cột 'Mã nguồn' trống ở MỌI dự án vì hien_thuc_req vừa mới tồn tại | G24: REQ_PHU — TẮT (khối A2.2 trên tab không phụ thuộc cờ)
A25: 6 | B25: M2-03 | C25: 2. Phân tích & thiết kế phần mềm | D25: P0 | E25: DEV-335 | F25: 37 REQ thật: 25 sạch (67 %), 11 thiếu tiêu chí đo được, 2 có từ mơ hồ. Lần đo đầu ra 3 từ mơ hồ, một là kêu oan ('ít nhất 2 lần' là mức đo được) — đã vá | G25: REQ_CHAT_LUONG — TẮT (module yeu_cau.py luôn có)
A26: 7 | B26: M2-06 | C26: 2. Phân tích & thiết kế phần mềm | D26: P0 | E26: DEV-336 | F26: sổ cái thật: 26 lần đánh dấu 'xong' ngay sau một lần ghi mã, 19 lần (73 %) không có phép kiểm nào đạt ở giữa. Phép đo đầu ở mức dự án ra 0 — đúng nhưng đo sai câu hỏi | G26: KE_HOACH_CONG_KIEM — TẮT
A27: 8 | B27: M2-08 | C27: 2. Phân tích & thiết kế phần mềm | D27: P0 | E27: DEV-337 | F27: 185 tệp .c thật: 1 758 → 1 786 hàm thấy được (+28 hàm trước đây VÔ HÌNH: 8 ngắt + 20 bị regex tham lam nuốt). 78 hàm nay gắn nhãn 'isr', 70 trong đó vốn đã có trong danh sách | G27: không có cờ — sửa lỗi thuần
A28: 9 | B28: M3-01 | C28: 3. Mạch, ERC, HDL/FPGA | D28: P0 | E28: DEV-338 | F28: 0 phát hiện trên 5 mô hình mạch thật — và lý do đáng hơn con số: 3 kho CÓ Fact v_max thì KHÔNG có mô hình mạch, 5 kho có mạch thì không có Fact ấy; thêm nữa Fact dùng chủ thể chip:X mà ERC không tra tiền tố đó | G28: không có cờ — sửa lỗi thuần
A29: 10 | B29: M3-03 | C29: 3. Mạch, ERC, HDL/FPGA | D29: P0 | E29: DEV-339 | F29: 8 phát hiện trên 5 mạch thật (6 nguon_khong_cap + 2 net_mot_chan), trong đó net clock I2C nối đúng một chân. SÁU trong tám là 'mô hình chưa khai' chứ không phải 'mạch sai'. robot-canbang: 107 Port lá, KHÔNG Port nào là power_out | G29: không có cờ — sửa lỗi thuần
A30: 11 | B30: M3-04 | C30: 3. Mạch, ERC, HDL/FPGA | D30: P0 | E30: DEV-340 | F30: 0 phát hiện trên 5 mạch thật — và đây là con số ĐÚNG (hai lỗi này catastrophic, không bo nào sống tới lúc lưu kho). Đã CẤY hai bộ cấp vào bản sao kho robot-canbang để chứng minh luật sống: nổ đúng 1 blocker trên net +5V thật | G30: không có cờ — sửa lỗi thuần
A31: 12 | B31: M3-07 | C31: 3. Mạch, ERC, HDL/FPGA | D31: P0 | E31: DEV-341 | F31: Fact tới được ERC: 5 → 17 (+12). Ba kho có Fact datasheet thì TOÀN BỘ mang chủ thể chip:, tức trước đó không một Fact nào tới được ERC. Độ phủ 5 mạch thật nay đọc được | G31: không có cờ — sửa lỗi thuần
... A34: 15 | B34: M3-13 | C34: 3. Mạch, ERC, HDL/FPGA | D34: P0 | E34: DEV-344 | F34: testbench Verilog THẬT của bài 3: tb_pcpi_dot4 1/1, tb_pcpi_mac 1/1, tb_pcpi_vmini không đo được (tb gọi bản bram HAI CỔNG đã bị bỏ 02/10) — mẫu số là TỆP, không phải phép phá | G34: không có cờ (công cụ mới core=False)
A35: 16 | B35: M3-18 | C35: 3. Mạch, ERC, HDL/FPGA | D35: P0 | E35: DEV-345 | F35: 6 cặp (mạng cổng, .cst) thật → 1 chỗ CHẶN: blinky của riscv-tn20k-b dựng bitstream 4,6 MB với chân đồng hồ do nextpnr tự chọn (rơi đúng chân 4 — bằng may). Cả 7 tệp .cst thật đọc hết, 0 lỗi cú pháp | G35: không có cờ (công cụ mới core=False)
A36: 17 | B36: M4-01 | C36: 4. Kiểm thử & chất lượng | D36: P0 | E36: DEV-346 | F36: 18 ca chạy trình biên dịch C thật: tệp test in số đo {"T1":300} với ngưỡng <=255 → EIDE phán 1 ca HỎNG. Chưa kho cũ nào có tiêu chí unit test để đo lại trên dữ liệu thật | G36: không có cờ (công cụ mới core=False)
A37: 18 | B37: M4-02 | C37: 4. Kiểm thử & chất lượng | D37: P0 | E37: DEV-347 | F37: 25 ca dựng đúng trạng thái thật (tệp test 3 ca, 1 ca đỏ, hiện vật dat=False) → fs.write còn 1 ca thì test.weakened=True. Và hàng rào cũ criteria.has_result chưa bao giờ nổ ngoài sim-01 | G37: SIM_RUNNER_GIOI_HAN — TẮT
A38: 19 | B38: M4-05 | C38: 4. Kiểm thử & chất lượng | D38: P1 | E38: DEV-348 | F38: du-lieu/rtos-sinhvien, chạy CẢ HAI hành vi: cũ so_thay=1, mới so_thay=0 — logo_ptit.c từ 'bộ kiểm ĐỎ' thành 'mọi đột biến đều làm hỏng biên dịch'. Một ô xanh giả, đã sửa | G38: không có cờ — sửa lỗi thuần
A39: 20 | B39: M4-19 | C39: 4. Kiểm thử & chất lượng | D39: P2 | E39: DEV-349 | F39: chạy TẠI CHỖ trên ba dự án firmware thật: kết luận giống hệt lượt đột biến tại chỗ của M4-05, và 50/50 tệp giữ nguyên cả sha256 lẫn mtime | G39: không có cờ — sửa lỗi thuần
A41: Việc còn MỞ (ngoài 86 việc chưa làm) | B41: Vì sao còn mở
A42: Bảy cờ mới đều còn TẮT | B42: GON_CONG_CU · TRUY_VET · REQ_PHU · REQ_CHAT_LUONG · KE_HOACH_CONG_KIEM · ERC_TU_DONG · SIM_RUNNER_GIOI_HAN. Cả bảy đổi thứ Agent nhìn thấy, đọc, hoặc LÀM ĐƯỢC mỗi lượt, nên chỉ bộ 76 ca chạy hai chế độ mới nói được chúng làm Agent khá hơn hay tệ hơn. Bộ ấy tốn tiền mô hình nên §3.0 bắt hỏi người dùng trước.
A43: kiem_cap_goi_tra() chưa thành hàng rào | B43: Soát được mọi phiên đã lưu, nhưng chưa hook nào gọi nó tự động — bắt được chuyện cũ, chưa chặn được chuyện mới.
A44: Luật ERC quá áp chưa nổ trên dữ liệu thật | B44: Đường dẫn đã thông ở M3-07, nhưng ba kho có Fact điện áp thì không có mô hình mạch, và ngược lại. Phải chờ một dự án có cả hai.
A45: Cột “Mã nguồn” của ma trận truy vết trống ở mọi dự án | B45: Nó đọc hien_thuc_req — trường vừa mới tồn tại, chưa tệp nào trên đĩa từng khai. Nên “chưa hiện thực” ở đó nghĩa là “chưa ai KHAI”, không phải “chưa ai viết”.
A46: Lỗi _go_dau trong src/eide/tools/design.py | B46: Viết .replace('d','d') nên 'ổn định' và 'ON DINH' không khớp nhau. Hàm ấy đang dùng cho một phép kiểm an toàn (người có thật sự chọn không). Tìm thấy ở M2-03, CHƯA sửa vì ngoài phạm vi — cần bộ ca kiểm riêng.
A47: subagent req-critic (bước 4 của M2-03) | B47: Kế hoạch ghi “tuỳ chọn, gộp M2-13”. Chưa làm, đúng theo kế hoạch.
A48: Hai luật kiểm chân FPGA chưa có dữ liệu để nổ | B48: chan_lech_kit và io_type_lech_bank cần Fact chân kit. Không kho nào trong repo có Fact pin:tangnano20k.* hay khoá vccio — nên hôm nay chỉ 3 trong 5 luật của M3-18 kết luận được gì trên dữ liệu thật. Cùng hình dạng với luật ERC quá áp.
A49: Một bitstream cũ đã dựng với chân đồng hồ tự chọn | B49: blinky của du-lieu/riscv-tn20k-b — xem DEV-345 và README §8. Không sửa hiện vật cũ: đó là dữ liệu của những lượt đo đã chốt. Từ nay phép kiểm chặn trước nextpnr.
A50: Ba công cụ mới nhất chưa lượt Agent nào GỌI | B50: hdl.sensitivity · hdl.constraints_check · test.criteria. Mã của cả ba đã chạy trên hiện vật thật, nhưng đó là tôi gọi hàm, không phải tác tử gọi công cụ. README §8 đếm cả ba vào phần chưa dùng thật.
A51: Bộ kiểm C của ba dự án firmware thật đều KHÔNG đo được độ nhạy | B51: rtos-sinhvien: 0/12 tệp đo được (4 font khong_thay, control_rtos.c trùng ký hiệu, main.c không dịch trên máy chủ, logo_ptit.c mọi mutant hỏng biên dịch). stm32f469-freertos và thu-nghiem-g6: bộ kiểm ĐỎ SẴN. Đây là trạng thái của dữ liệu đo, không phải lỗi sản phẩm — nhưng nó nghĩa là chưa dự án firmware nào trong repo có một con số độ nhạy đáng tin. Xem DEV-348.
A52: POL-N6-sua-test chưa nổ trên một phiên thật nào | B52: Hook sua_test_sau_do cấp dữ kiện cho lời gọi SẮP xảy ra, nên không soát lại được phiên đã lưu — khác mọi phép đo trước của đợt này. Nó đã có 25 ca kiểm và phá lại 27/27, nhưng chưa lượt tác tử thật nào chạm vào nó. Cùng hình dạng với ba luật kiểm thiếu dữ liệu ở trên, chỉ khác lý do.
... A75: Gắn cờ biên dịch cho cả LƯỢT MỐC là đổi chính cái mốc mà mọi so sánh dựa vào — mốc của cả ba dự án thật từ XANH thành ĐỎ. | B75: M4-19 · DEV-349

Sheet Tiến độ 09-10-2026 (chiều)
A1: TIẾN ĐỘ ĐỢT TỐI ƯU TÁC TỬ — chốt chiều 09/10/2026
A2: Mỗi dòng 'Xong' đều có: mục DEV-LOG tra lại được · số ca kiểm trước→sau · một con số đo trên dữ liệu thật · phần còn nợ. Cột chi tiết nằm ở sheet “Danh mục tối ưu”, cột T–Y.
A4: Tổng quan | B4: Số việc | C4: Ghi chú
A5: Xong (đã gộp vào main, đã đẩy) | B5: 21 | C5: 21 việc đầu của Giai đoạn 1, theo đúng thứ tự # của kế hoạch
A6: Đang làm (chưa commit) | B6: 0 | C6: không việc nào đang dở
A7: Chưa làm | B7: 85 | C7: 85 việc còn lại trong 106
A8: TỔNG | B8: 106
A10: Phép đo của cả đợt | B10: Trước (06/10) | C10: Sau (09/10) | D10: Ghi chú
A11: Ca đơn vị Python (pytest -q) | B11: 1 610 | C11: 1 862 | D11: +252 ca so với 06/10; không ca cũ nào đỏ ở bất kỳ bước nào
A12: Ca đơn vị giao diện (swift test) | B12: 43 | C12: 43 | D12: không nhiệm vụ nào đụng ui/ — kiểu khối A2.2 dùng “table”, Swift đã dựng được
A13: kiem_tai_lieu.py | B13: 0 chỗ lệch | C13: 0 chỗ lệch | D13: 0 chỗ LỆCH CHẮC CHẮN cả hai lượt. Hôm nay nó bắt đúng chuyện cần bắt: hai công cụ mới làm README lệch số công cụ 127 → 129, và số 'cần đọc lại' nhảy 11 → 15 → về 11 sau khi sửa
A14: thu_sch.py (cờ schematic bật) | B14: 63/63 | C14: 63/63 | D14: chạy ở M3-03 và M3-04, không tụt
A15: Mục DEV-LOG mới | B15: — | C15: DEV-330 → DEV-350 | D15: 21 mục, mỗi việc một mục
A16: Cờ tính năng mới | B16: 1 (schematic) | C16: 8 | D16: 7 cờ mới, TẤT CẢ mặc định TẮT. Cờ thứ 7 là SIM_RUNNER_GIOI_HAN (M4-02) — nó giới hạn fs.write của sim-runner trong sim/; hàng rào chính của M4-02 (POL-N6-sua-test) thì KHÔNG sau cờ
A17: Mã lỗi mới | B17: — | C17: E4031 · E4032 · E6012 · E4033 · E4024 | D17: M4-04, M4-05 và M4-19 không thêm mã nào; M4-02 dùng lại E5006. E4033 (M3-18), E4024 (M4-01). M4-01 còn DÙNG LẠI E4008/E4009/E4023 của sim.run — cùng một chuyện thì cùng một mã
A19: # | B19: Mã | C19: Mảng | D19: Ưu tiên | E19: DEV-LOG | F19: Ca kiểm | G19: Cờ mặc định
A20: 1 | B20: M1-01 | C20: 1. Lõi tác tử | D20: P0 | E20: DEV-330 | F20: 105/309 phiên thật có lịch sử tự mâu thuẫn — 255 chỗ (156 kết quả thứ hai cùng id, 74 message chen giữa, 24 kết quả lạc lượt, 1 lời gọi không kết quả) | G20: không có cờ — sửa lỗi thuần
A21: 2 | B21: M1-02 | C21: 1. Lõi tác tử | D21: P0 | E21: DEV-331 | F21: lược đồ công cụ thật: 25 869 token/lời gọi (trần tool_schema=4000 chưa dòng mã nào đọc). Cờ bật: 4 475 token, giảm 82,7 %; 73 → 18 công cụ | G21: GON_CONG_CU — TẮT
A22: 3 | B22: M1-03 | C22: 1. Lõi tác tử | D22: P0 | E22: DEV-332 | F22: 1 822 lời gọi của tác tử con trong 26 phiên thật, 0 lần qua lớp luật. Toàn công cụ đọc trừ một build.compile — lỗ hổng chưa bị bước vào, không phải được canh | G22: không có cờ — sửa lỗi thuần
A23: 4 | B23: M2-01 | C23: 2. Phân tích & thiết kế phần mềm | D23: P0 | E23: DEV-333 | F23: kịch bản 3 REQ + 3 phương án + 3 tiêu chí + 3 tệp: sửa MỘT REQ làm 9 hiện vật STALE → còn 3. Phép đo đầu ra 6→2 vì bị hàng rào E4020 chặn, đã sửa kịch bản đo | G23: TRUY_VET — TẮT (phần nền chạy cả khi tắt)
A24: 5 | B24: M2-02 | C24: 2. Phân tích & thiết kế phần mềm | D24: P0 | E24: DEV-334 | F24: 63 kho thật: 5/37 REQ có ít nhất một phép đo; 27 chưa có phương án nào nhận; 0 REQ đi hết chuỗi. Cột 'Mã nguồn' trống ở MỌI dự án vì hien_thuc_req vừa mới tồn tại | G24: REQ_PHU — TẮT (khối A2.2 trên tab không phụ thuộc cờ)
A25: 6 | B25: M2-03 | C25: 2. Phân tích & thiết kế phần mềm | D25: P0 | E25: DEV-335 | F25: 37 REQ thật: 25 sạch (67 %), 11 thiếu tiêu chí đo được, 2 có từ mơ hồ. Lần đo đầu ra 3 từ mơ hồ, một là kêu oan ('ít nhất 2 lần' là mức đo được) — đã vá | G25: REQ_CHAT_LUONG — TẮT (module yeu_cau.py luôn có)
A26: 7 | B26: M2-06 | C26: 2. Phân tích & thiết kế phần mềm | D26: P0 | E26: DEV-336 | F26: sổ cái thật: 26 lần đánh dấu 'xong' ngay sau một lần ghi mã, 19 lần (73 %) không có phép kiểm nào đạt ở giữa. Phép đo đầu ở mức dự án ra 0 — đúng nhưng đo sai câu hỏi | G26: KE_HOACH_CONG_KIEM — TẮT
A27: 8 | B27: M2-08 | C27: 2. Phân tích & thiết kế phần mềm | D27: P0 | E27: DEV-337 | F27: 185 tệp .c thật: 1 758 → 1 786 hàm thấy được (+28 hàm trước đây VÔ HÌNH: 8 ngắt + 20 bị regex tham lam nuốt). 78 hàm nay gắn nhãn 'isr', 70 trong đó vốn đã có trong danh sách | G27: không có cờ — sửa lỗi thuần
A28: 9 | B28: M3-01 | C28: 3. Mạch, ERC, HDL/FPGA | D28: P0 | E28: DEV-338 | F28: 0 phát hiện trên 5 mô hình mạch thật — và lý do đáng hơn con số: 3 kho CÓ Fact v_max thì KHÔNG có mô hình mạch, 5 kho có mạch thì không có Fact ấy; thêm nữa Fact dùng chủ thể chip:X mà ERC không tra tiền tố đó | G28: không có cờ — sửa lỗi thuần
A29: 10 | B29: M3-03 | C29: 3. Mạch, ERC, HDL/FPGA | D29: P0 | E29: DEV-339 | F29: 8 phát hiện trên 5 mạch thật (6 nguon_khong_cap + 2 net_mot_chan), trong đó net clock I2C nối đúng một chân. SÁU trong tám là 'mô hình chưa khai' chứ không phải 'mạch sai'. robot-canbang: 107 Port lá, KHÔNG Port nào là power_out | G29: không có cờ — sửa lỗi thuần
A30: 11 | B30: M3-04 | C30: 3. Mạch, ERC, HDL/FPGA | D30: P0 | E30: DEV-340 | F30: 0 phát hiện trên 5 mạch thật — và đây là con số ĐÚNG (hai lỗi này catastrophic, không bo nào sống tới lúc lưu kho). Đã CẤY hai bộ cấp vào bản sao kho robot-canbang để chứng minh luật sống: nổ đúng 1 blocker trên net +5V thật | G30: không có cờ — sửa lỗi thuần
A31: 12 | B31: M3-07 | C31: 3. Mạch, ERC, HDL/FPGA | D31: P0 | E31: DEV-341 | F31: Fact tới được ERC: 5 → 17 (+12). Ba kho có Fact datasheet thì TOÀN BỘ mang chủ thể chip:, tức trước đó không một Fact nào tới được ERC. Độ phủ 5 mạch thật nay đọc được | G31: không có cờ — sửa lỗi thuần
... A34: 15 | B34: M3-13 | C34: 3. Mạch, ERC, HDL/FPGA | D34: P0 | E34: DEV-344 | F34: testbench Verilog THẬT của bài 3: tb_pcpi_dot4 1/1, tb_pcpi_mac 1/1, tb_pcpi_vmini không đo được (tb gọi bản bram HAI CỔNG đã bị bỏ 02/10) — mẫu số là TỆP, không phải phép phá | G34: không có cờ (công cụ mới core=False)
A35: 16 | B35: M3-18 | C35: 3. Mạch, ERC, HDL/FPGA | D35: P0 | E35: DEV-345 | F35: 6 cặp (mạng cổng, .cst) thật → 1 chỗ CHẶN: blinky của riscv-tn20k-b dựng bitstream 4,6 MB với chân đồng hồ do nextpnr tự chọn (rơi đúng chân 4 — bằng may). Cả 7 tệp .cst thật đọc hết, 0 lỗi cú pháp | G35: không có cờ (công cụ mới core=False)
A36: 17 | B36: M4-01 | C36: 4. Kiểm thử & chất lượng | D36: P0 | E36: DEV-346 | F36: 18 ca chạy trình biên dịch C thật: tệp test in số đo {"T1":300} với ngưỡng <=255 → EIDE phán 1 ca HỎNG. Chưa kho cũ nào có tiêu chí unit test để đo lại trên dữ liệu thật | G36: không có cờ (công cụ mới core=False)
A37: 18 | B37: M4-02 | C37: 4. Kiểm thử & chất lượng | D37: P0 | E37: DEV-347 | F37: 25 ca dựng đúng trạng thái thật (tệp test 3 ca, 1 ca đỏ, hiện vật dat=False) → fs.write còn 1 ca thì test.weakened=True. Và hàng rào cũ criteria.has_result chưa bao giờ nổ ngoài sim-01 | G37: SIM_RUNNER_GIOI_HAN — TẮT
A38: 19 | B38: M4-05 | C38: 4. Kiểm thử & chất lượng | D38: P1 | E38: DEV-348 | F38: du-lieu/rtos-sinhvien, chạy CẢ HAI hành vi: cũ so_thay=1, mới so_thay=0 — logo_ptit.c từ 'bộ kiểm ĐỎ' thành 'mọi đột biến đều làm hỏng biên dịch'. Một ô xanh giả, đã sửa | G38: không có cờ — sửa lỗi thuần
A39: 20 | B39: M4-19 | C39: 4. Kiểm thử & chất lượng | D39: P2 | E39: DEV-349 | F39: chạy TẠI CHỖ trên ba dự án firmware thật: kết luận giống hệt lượt đột biến tại chỗ của M4-05, và 50/50 tệp giữ nguyên cả sha256 lẫn mtime | G39: không có cờ — sửa lỗi thuần
A40: 21 | B40: M4-04 | C40: 4. Kiểm thử & chất lượng | D40: P1 | E40: DEV-350 | F40: TÁI HIỆN được ca DANH-GIA §2.2 bằng máy trên control_rtos.c thật: bảng cũ 0 đột biến cho hằng hex, bảng mới dòng 147 → mutant SỐNG. Và chi_tiet trên 12 tệp thật: 110 s, điểm 0,0 | G40: không có cờ (tham số mới, mặc định giữ hành vi cũ)
A42: Việc còn MỞ (ngoài 85 việc chưa làm) | B42: Vì sao còn mở
A43: Bảy cờ mới đều còn TẮT | B43: GON_CONG_CU · TRUY_VET · REQ_PHU · REQ_CHAT_LUONG · KE_HOACH_CONG_KIEM · ERC_TU_DONG · SIM_RUNNER_GIOI_HAN. Cả bảy đổi thứ Agent nhìn thấy, đọc, hoặc LÀM ĐƯỢC mỗi lượt, nên chỉ bộ 76 ca chạy hai chế độ mới nói được chúng làm Agent khá hơn hay tệ hơn. Bộ ấy tốn tiền mô hình nên §3.0 bắt hỏi người dùng trước.
A44: kiem_cap_goi_tra() chưa thành hàng rào | B44: Soát được mọi phiên đã lưu, nhưng chưa hook nào gọi nó tự động — bắt được chuyện cũ, chưa chặn được chuyện mới.
A45: Luật ERC quá áp chưa nổ trên dữ liệu thật | B45: Đường dẫn đã thông ở M3-07, nhưng ba kho có Fact điện áp thì không có mô hình mạch, và ngược lại. Phải chờ một dự án có cả hai.
A46: Cột “Mã nguồn” của ma trận truy vết trống ở mọi dự án | B46: Nó đọc hien_thuc_req — trường vừa mới tồn tại, chưa tệp nào trên đĩa từng khai. Nên “chưa hiện thực” ở đó nghĩa là “chưa ai KHAI”, không phải “chưa ai viết”.
A47: Lỗi _go_dau trong src/eide/tools/design.py | B47: Viết .replace('d','d') nên 'ổn định' và 'ON DINH' không khớp nhau. Hàm ấy đang dùng cho một phép kiểm an toàn (người có thật sự chọn không). Tìm thấy ở M2-03, CHƯA sửa vì ngoài phạm vi — cần bộ ca kiểm riêng.
A48: subagent req-critic (bước 4 của M2-03) | B48: Kế hoạch ghi “tuỳ chọn, gộp M2-13”. Chưa làm, đúng theo kế hoạch.
A49: Hai luật kiểm chân FPGA chưa có dữ liệu để nổ | B49: chan_lech_kit và io_type_lech_bank cần Fact chân kit. Không kho nào trong repo có Fact pin:tangnano20k.* hay khoá vccio — nên hôm nay chỉ 3 trong 5 luật của M3-18 kết luận được gì trên dữ liệu thật. Cùng hình dạng với luật ERC quá áp.
A50: Một bitstream cũ đã dựng với chân đồng hồ tự chọn | B50: blinky của du-lieu/riscv-tn20k-b — xem DEV-345 và README §8. Không sửa hiện vật cũ: đó là dữ liệu của những lượt đo đã chốt. Từ nay phép kiểm chặn trước nextpnr.
A51: Ba công cụ mới nhất chưa lượt Agent nào GỌI | B51: hdl.sensitivity · hdl.constraints_check · test.criteria. Mã của cả ba đã chạy trên hiện vật thật, nhưng đó là tôi gọi hàm, không phải tác tử gọi công cụ. README §8 đếm cả ba vào phần chưa dùng thật.
A52: Bộ kiểm C của ba dự án firmware thật đều KHÔNG đo được độ nhạy | B52: rtos-sinhvien: 0/12 tệp đo được (4 font khong_thay, control_rtos.c trùng ký hiệu, main.c không dịch trên máy chủ, logo_ptit.c mọi mutant hỏng biên dịch). stm32f469-freertos và thu-nghiem-g6: bộ kiểm ĐỎ SẴN. Đây là trạng thái của dữ liệu đo, không phải lỗi sản phẩm — nhưng nó nghĩa là chưa dự án firmware nào trong repo có một con số độ nhạy đáng tin. Xem DEV-348.
A53: POL-N6-sua-test chưa nổ trên một phiên thật nào | B53: Hook sua_test_sau_do cấp dữ kiện cho lời gọi SẮP xảy ra, nên không soát lại được phiên đã lưu — khác mọi phép đo trước của đợt này. Nó đã có 25 ca kiểm và phá lại 27/27, nhưng chưa lượt tác tử thật nào chạm vào nó. Cùng hình dạng với ba luật kiểm thiếu dữ liệu ở trên, chỉ khác lý do.
... A78: Ca kiểm chi phí của tôi KHÔNG bắt được bản chậm, vì tệp dựng dùng hằng hex TRẦN — _bo_che trả về ngay khi không có chỗ giữ. Chính CHÚ THÍCH mỗi dòng của tệp thật mới làm mỗi lượt bỏ che thành một lượt regex thật. | B78: M4-04 · DEV-350

Sheet Tiến độ 09-10-2026 (toi)
A1: TIẾN ĐỘ ĐỢT TỐI ƯU TÁC TỬ — chốt tối 09/10/2026
A2: Mỗi dòng 'Xong' đều có: mục DEV-LOG tra lại được · số ca kiểm trước→sau · một con số đo trên dữ liệu thật · phần còn nợ. Cột chi tiết nằm ở sheet “Danh mục tối ưu”, cột T–Y.
A4: Tổng quan | B4: Số việc | C4: Ghi chú
A5: Xong (đã gộp vào main, đã đẩy) | B5: 22 | C5: 22 việc đầu của Giai đoạn 1 — việc #22 còn MỘT tiêu chí chưa đạt
A6: Đang làm (chưa commit) | B6: 0 | C6: không việc nào đang dở
A7: Chưa làm | B7: 84 | C7: 84 việc còn lại trong 106
A8: TỔNG | B8: 106
A10: Phép đo của cả đợt | B10: Trước (06/10) | C10: Sau (09/10) | D10: Ghi chú
A11: Ca đơn vị Python (pytest -q) | B11: 1 610 | C11: 1 878 | D11: +268 ca so với 06/10; không ca cũ nào đỏ ở bất kỳ bước nào
A12: Ca đơn vị giao diện (swift test) | B12: 43 | C12: 43 | D12: không nhiệm vụ nào đụng ui/ — kiểu khối A2.2 dùng “table”, Swift đã dựng được
A13: kiem_tai_lieu.py | B13: 0 chỗ lệch | C13: 0 chỗ lệch | D13: 0 chỗ LỆCH CHẮC CHẮN cả hai lượt. Hôm nay nó bắt đúng chuyện cần bắt: hai công cụ mới làm README lệch số công cụ 127 → 129, và số 'cần đọc lại' nhảy 11 → 15 → về 11 sau khi sửa
A14: thu_sch.py (cờ schematic bật) | B14: 63/63 | C14: 63/63 | D14: chạy ở M3-03 và M3-04, không tụt
A15: Mục DEV-LOG mới | B15: — | C15: DEV-330 → DEV-351 | D15: 22 mục, mỗi việc một mục
A16: Cờ tính năng mới | B16: 1 (schematic) | C16: 9 | D16: 8 cờ mới, TẤT CẢ mặc định TẮT. Cờ thứ 8 là TEST_HARDEN (M4-06) — Stop hook nhắc đo độ nhạy và công cụ test.harden. Phần ghi deps.upstream của M4-06 thì KHÔNG sau cờ
A17: Mã lỗi mới | B17: — | C17: E4031 · E4032 · E6012 · E4033 · E4024 | D17: M4-04, M4-05 và M4-19 không thêm mã nào; M4-02 dùng lại E5006. E4033 (M3-18), E4024 (M4-01). M4-01 còn DÙNG LẠI E4008/E4009/E4023 của sim.run — cùng một chuyện thì cùng một mã
A19: # | B19: Mã | C19: Mảng | D19: Ưu tiên | E19: DEV-LOG | F19: Ca kiểm | G19: Cờ mặc định
A20: 1 | B20: M1-01 | C20: 1. Lõi tác tử | D20: P0 | E20: DEV-330 | F20: 105/309 phiên thật có lịch sử tự mâu thuẫn — 255 chỗ (156 kết quả thứ hai cùng id, 74 message chen giữa, 24 kết quả lạc lượt, 1 lời gọi không kết quả) | G20: không có cờ — sửa lỗi thuần
A21: 2 | B21: M1-02 | C21: 1. Lõi tác tử | D21: P0 | E21: DEV-331 | F21: lược đồ công cụ thật: 25 869 token/lời gọi (trần tool_schema=4000 chưa dòng mã nào đọc). Cờ bật: 4 475 token, giảm 82,7 %; 73 → 18 công cụ | G21: GON_CONG_CU — TẮT
A22: 3 | B22: M1-03 | C22: 1. Lõi tác tử | D22: P0 | E22: DEV-332 | F22: 1 822 lời gọi của tác tử con trong 26 phiên thật, 0 lần qua lớp luật. Toàn công cụ đọc trừ một build.compile — lỗ hổng chưa bị bước vào, không phải được canh | G22: không có cờ — sửa lỗi thuần
A23: 4 | B23: M2-01 | C23: 2. Phân tích & thiết kế phần mềm | D23: P0 | E23: DEV-333 | F23: kịch bản 3 REQ + 3 phương án + 3 tiêu chí + 3 tệp: sửa MỘT REQ làm 9 hiện vật STALE → còn 3. Phép đo đầu ra 6→2 vì bị hàng rào E4020 chặn, đã sửa kịch bản đo | G23: TRUY_VET — TẮT (phần nền chạy cả khi tắt)
A24: 5 | B24: M2-02 | C24: 2. Phân tích & thiết kế phần mềm | D24: P0 | E24: DEV-334 | F24: 63 kho thật: 5/37 REQ có ít nhất một phép đo; 27 chưa có phương án nào nhận; 0 REQ đi hết chuỗi. Cột 'Mã nguồn' trống ở MỌI dự án vì hien_thuc_req vừa mới tồn tại | G24: REQ_PHU — TẮT (khối A2.2 trên tab không phụ thuộc cờ)
A25: 6 | B25: M2-03 | C25: 2. Phân tích & thiết kế phần mềm | D25: P0 | E25: DEV-335 | F25: 37 REQ thật: 25 sạch (67 %), 11 thiếu tiêu chí đo được, 2 có từ mơ hồ. Lần đo đầu ra 3 từ mơ hồ, một là kêu oan ('ít nhất 2 lần' là mức đo được) — đã vá | G25: REQ_CHAT_LUONG — TẮT (module yeu_cau.py luôn có)
A26: 7 | B26: M2-06 | C26: 2. Phân tích & thiết kế phần mềm | D26: P0 | E26: DEV-336 | F26: sổ cái thật: 26 lần đánh dấu 'xong' ngay sau một lần ghi mã, 19 lần (73 %) không có phép kiểm nào đạt ở giữa. Phép đo đầu ở mức dự án ra 0 — đúng nhưng đo sai câu hỏi | G26: KE_HOACH_CONG_KIEM — TẮT
A27: 8 | B27: M2-08 | C27: 2. Phân tích & thiết kế phần mềm | D27: P0 | E27: DEV-337 | F27: 185 tệp .c thật: 1 758 → 1 786 hàm thấy được (+28 hàm trước đây VÔ HÌNH: 8 ngắt + 20 bị regex tham lam nuốt). 78 hàm nay gắn nhãn 'isr', 70 trong đó vốn đã có trong danh sách | G27: không có cờ — sửa lỗi thuần
A28: 9 | B28: M3-01 | C28: 3. Mạch, ERC, HDL/FPGA | D28: P0 | E28: DEV-338 | F28: 0 phát hiện trên 5 mô hình mạch thật — và lý do đáng hơn con số: 3 kho CÓ Fact v_max thì KHÔNG có mô hình mạch, 5 kho có mạch thì không có Fact ấy; thêm nữa Fact dùng chủ thể chip:X mà ERC không tra tiền tố đó | G28: không có cờ — sửa lỗi thuần
A29: 10 | B29: M3-03 | C29: 3. Mạch, ERC, HDL/FPGA | D29: P0 | E29: DEV-339 | F29: 8 phát hiện trên 5 mạch thật (6 nguon_khong_cap + 2 net_mot_chan), trong đó net clock I2C nối đúng một chân. SÁU trong tám là 'mô hình chưa khai' chứ không phải 'mạch sai'. robot-canbang: 107 Port lá, KHÔNG Port nào là power_out | G29: không có cờ — sửa lỗi thuần
A30: 11 | B30: M3-04 | C30: 3. Mạch, ERC, HDL/FPGA | D30: P0 | E30: DEV-340 | F30: 0 phát hiện trên 5 mạch thật — và đây là con số ĐÚNG (hai lỗi này catastrophic, không bo nào sống tới lúc lưu kho). Đã CẤY hai bộ cấp vào bản sao kho robot-canbang để chứng minh luật sống: nổ đúng 1 blocker trên net +5V thật | G30: không có cờ — sửa lỗi thuần
A31: 12 | B31: M3-07 | C31: 3. Mạch, ERC, HDL/FPGA | D31: P0 | E31: DEV-341 | F31: Fact tới được ERC: 5 → 17 (+12). Ba kho có Fact datasheet thì TOÀN BỘ mang chủ thể chip:, tức trước đó không một Fact nào tới được ERC. Độ phủ 5 mạch thật nay đọc được | G31: không có cờ — sửa lỗi thuần
... A34: 15 | B34: M3-13 | C34: 3. Mạch, ERC, HDL/FPGA | D34: P0 | E34: DEV-344 | F34: testbench Verilog THẬT của bài 3: tb_pcpi_dot4 1/1, tb_pcpi_mac 1/1, tb_pcpi_vmini không đo được (tb gọi bản bram HAI CỔNG đã bị bỏ 02/10) — mẫu số là TỆP, không phải phép phá | G34: không có cờ (công cụ mới core=False)
A35: 16 | B35: M3-18 | C35: 3. Mạch, ERC, HDL/FPGA | D35: P0 | E35: DEV-345 | F35: 6 cặp (mạng cổng, .cst) thật → 1 chỗ CHẶN: blinky của riscv-tn20k-b dựng bitstream 4,6 MB với chân đồng hồ do nextpnr tự chọn (rơi đúng chân 4 — bằng may). Cả 7 tệp .cst thật đọc hết, 0 lỗi cú pháp | G35: không có cờ (công cụ mới core=False)
A36: 17 | B36: M4-01 | C36: 4. Kiểm thử & chất lượng | D36: P0 | E36: DEV-346 | F36: 18 ca chạy trình biên dịch C thật: tệp test in số đo {"T1":300} với ngưỡng <=255 → EIDE phán 1 ca HỎNG. Chưa kho cũ nào có tiêu chí unit test để đo lại trên dữ liệu thật | G36: không có cờ (công cụ mới core=False)
A37: 18 | B37: M4-02 | C37: 4. Kiểm thử & chất lượng | D37: P0 | E37: DEV-347 | F37: 25 ca dựng đúng trạng thái thật (tệp test 3 ca, 1 ca đỏ, hiện vật dat=False) → fs.write còn 1 ca thì test.weakened=True. Và hàng rào cũ criteria.has_result chưa bao giờ nổ ngoài sim-01 | G37: SIM_RUNNER_GIOI_HAN — TẮT
A38: 19 | B38: M4-05 | C38: 4. Kiểm thử & chất lượng | D38: P1 | E38: DEV-348 | F38: du-lieu/rtos-sinhvien, chạy CẢ HAI hành vi: cũ so_thay=1, mới so_thay=0 — logo_ptit.c từ 'bộ kiểm ĐỎ' thành 'mọi đột biến đều làm hỏng biên dịch'. Một ô xanh giả, đã sửa | G38: không có cờ — sửa lỗi thuần
A39: 20 | B39: M4-19 | C39: 4. Kiểm thử & chất lượng | D39: P2 | E39: DEV-349 | F39: chạy TẠI CHỖ trên ba dự án firmware thật: kết luận giống hệt lượt đột biến tại chỗ của M4-05, và 50/50 tệp giữ nguyên cả sha256 lẫn mtime | G39: không có cờ — sửa lỗi thuần
A40: 21 | B40: M4-04 | C40: 4. Kiểm thử & chất lượng | D40: P1 | E40: DEV-350 | F40: TÁI HIỆN được ca DANH-GIA §2.2 bằng máy trên control_rtos.c thật: bảng cũ 0 đột biến cho hằng hex, bảng mới dòng 147 → mutant SỐNG. Và chi_tiet trên 12 tệp thật: 110 s, điểm 0,0 | G40: không có cờ (tham số mới, mặc định giữ hành vi cũ)
A41: 22 | B41: M4-06 | C41: 4. Kiểm thử & chất lượng | D41: P0 | E41: DEV-351 | F41: đo TRƯỚC trên logo_ptit.c thật: điểm 0,0 · 30 mutant · 20 sống. Phần SAU chưa đo — cần lời gọi mô hình (§3.0 bắt hỏi trước), và dự án mẫu không có chỗ để đo | G41: TEST_HARDEN — TẮT
A43: Việc còn MỞ (ngoài 84 việc chưa làm) | B43: Vì sao còn mở
A44: Bảy cờ mới đều còn TẮT | B44: GON_CONG_CU · TRUY_VET · REQ_PHU · REQ_CHAT_LUONG · KE_HOACH_CONG_KIEM · ERC_TU_DONG · SIM_RUNNER_GIOI_HAN. Cả bảy đổi thứ Agent nhìn thấy, đọc, hoặc LÀM ĐƯỢC mỗi lượt, nên chỉ bộ 76 ca chạy hai chế độ mới nói được chúng làm Agent khá hơn hay tệ hơn. Bộ ấy tốn tiền mô hình nên §3.0 bắt hỏi người dùng trước.
A45: kiem_cap_goi_tra() chưa thành hàng rào | B45: Soát được mọi phiên đã lưu, nhưng chưa hook nào gọi nó tự động — bắt được chuyện cũ, chưa chặn được chuyện mới.
A46: Luật ERC quá áp chưa nổ trên dữ liệu thật | B46: Đường dẫn đã thông ở M3-07, nhưng ba kho có Fact điện áp thì không có mô hình mạch, và ngược lại. Phải chờ một dự án có cả hai.
A47: Cột “Mã nguồn” của ma trận truy vết trống ở mọi dự án | B47: Nó đọc hien_thuc_req — trường vừa mới tồn tại, chưa tệp nào trên đĩa từng khai. Nên “chưa hiện thực” ở đó nghĩa là “chưa ai KHAI”, không phải “chưa ai viết”.
A48: Lỗi _go_dau trong src/eide/tools/design.py | B48: Viết .replace('d','d') nên 'ổn định' và 'ON DINH' không khớp nhau. Hàm ấy đang dùng cho một phép kiểm an toàn (người có thật sự chọn không). Tìm thấy ở M2-03, CHƯA sửa vì ngoài phạm vi — cần bộ ca kiểm riêng.
A49: subagent req-critic (bước 4 của M2-03) | B49: Kế hoạch ghi “tuỳ chọn, gộp M2-13”. Chưa làm, đúng theo kế hoạch.
A50: Hai luật kiểm chân FPGA chưa có dữ liệu để nổ | B50: chan_lech_kit và io_type_lech_bank cần Fact chân kit. Không kho nào trong repo có Fact pin:tangnano20k.* hay khoá vccio — nên hôm nay chỉ 3 trong 5 luật của M3-18 kết luận được gì trên dữ liệu thật. Cùng hình dạng với luật ERC quá áp.
A51: Một bitstream cũ đã dựng với chân đồng hồ tự chọn | B51: blinky của du-lieu/riscv-tn20k-b — xem DEV-345 và README §8. Không sửa hiện vật cũ: đó là dữ liệu của những lượt đo đã chốt. Từ nay phép kiểm chặn trước nextpnr.
A52: Ba công cụ mới nhất chưa lượt Agent nào GỌI | B52: hdl.sensitivity · hdl.constraints_check · test.criteria. Mã của cả ba đã chạy trên hiện vật thật, nhưng đó là tôi gọi hàm, không phải tác tử gọi công cụ. README §8 đếm cả ba vào phần chưa dùng thật.
A53: Bộ kiểm C của ba dự án firmware thật đều KHÔNG đo được độ nhạy | B53: rtos-sinhvien: 0/12 tệp đo được (4 font khong_thay, control_rtos.c trùng ký hiệu, main.c không dịch trên máy chủ, logo_ptit.c mọi mutant hỏng biên dịch). stm32f469-freertos và thu-nghiem-g6: bộ kiểm ĐỎ SẴN. Đây là trạng thái của dữ liệu đo, không phải lỗi sản phẩm — nhưng nó nghĩa là chưa dự án firmware nào trong repo có một con số độ nhạy đáng tin. Xem DEV-348.
A54: POL-N6-sua-test chưa nổ trên một phiên thật nào | B54: Hook sua_test_sau_do cấp dữ kiện cho lời gọi SẮP xảy ra, nên không soát lại được phiên đã lưu — khác mọi phép đo trước của đợt này. Nó đã có 25 ca kiểm và phá lại 27/27, nhưng chưa lượt tác tử thật nào chạm vào nó. Cùng hình dạng với ba luật kiểm thiếu dữ liệu ở trên, chỉ khác lý do.
... A83: Tôi quên mở nhánh và commit thẳng lên main. Nội dung đúng, quy trình §3.1 thì không — đã dựng lại con trỏ toi-uu/M4-06 tại đúng commit. | B83: M4-06 · DEV-351

Sheet Tiến độ 09-10-2026 (khuya)
A1: TIẾN ĐỘ ĐỢT TỐI ƯU TÁC TỬ — chốt khuya 09/10/2026
A2: Mỗi dòng 'Xong' đều có: mục DEV-LOG tra lại được · số ca kiểm trước→sau · một con số đo trên dữ liệu thật · phần còn nợ. Cột chi tiết nằm ở sheet “Danh mục tối ưu”, cột T–Y.
A4: Tổng quan | B4: Số việc | C4: Ghi chú
A5: Xong (đã gộp vào main, đã đẩy) | B5: 23 | C5: 23 việc đầu của Giai đoạn 1 — việc #22 và #23 mỗi cái còn MỘT tiêu chí chưa đạt
A6: Đang làm (chưa commit) | B6: 0 | C6: không việc nào đang dở
A7: Chưa làm | B7: 83 | C7: 83 việc còn lại trong 106
A8: TỔNG | B8: 106
A10: Phép đo của cả đợt | B10: Trước (06/10) | C10: Sau (09/10 khuya) | D10: Ghi chú
A11: Ca đơn vị Python (pytest -q) | B11: 1 610 | C11: 1 896 | D11: +286 ca so với 06/10; không ca cũ nào đỏ ở bất kỳ bước nào
A12: Ca đơn vị giao diện (swift test) | B12: 43 | C12: 43 | D12: không nhiệm vụ nào đụng ui/ — kiểu khối A2.2 dùng “table”, Swift đã dựng được
A13: kiem_tai_lieu.py | B13: 0 chỗ lệch | C13: 0 chỗ lệch | D13: 0 chỗ LỆCH CHẮC CHẮN mọi lượt. M4-07 không thêm công cụ nào, nên số công cụ giữ 131 — nhưng nó SỬA chỗ đếm: kiem_tai_lieu bật mọi cờ theo Features.ten_co(), và danh sách ấy gõ tay nên cờ thứ 10 vô hình với nó
A14: thu_sch.py (cờ schematic bật) | B14: 63/63 | C14: 63/63 | D14: chạy ở M3-03 và M3-04, không tụt
A15: Mục DEV-LOG mới | B15: — | C15: DEV-330 → DEV-352 | D15: 23 mục, mỗi việc một mục
A16: Cờ tính năng mới | B16: 1 (schematic) | C16: 10 | D16: 9 cờ mới, TẤT CẢ mặc định TẮT. Cờ thứ 10 là VERIFIER_GOI_BANG_CHUNG (M4-07) — verifier nhận gói bằng chứng do MÃ dựng từ sổ cái thay cho đề bài tác tử chính tự viết. Phần sửa Features.ten_co() lấy tên cờ từ dataclass thì KHÔNG sau cờ
A17: Mã lỗi mới | B17: — | C17: E4031 · E4032 · E6012 · E4033 · E4024 | D17: M4-04, M4-05 và M4-19 không thêm mã nào; M4-02 dùng lại E5006. E4033 (M3-18), E4024 (M4-01). M4-01 còn DÙNG LẠI E4008/E4009/E4023 của sim.run — cùng một chuyện thì cùng một mã. M4-07 không thêm mã lỗi nào — nó không dựng thêm cổng chặn, nó đổi ĐẦU VÀO của một tác tử con
A19: # | B19: Mã | C19: Mảng | D19: Ưu tiên | E19: DEV-LOG | F19: Ca kiểm | G19: Cờ mặc định
A20: 1 | B20: M1-01 | C20: 1. Lõi tác tử | D20: P0 | E20: DEV-330 | F20: 105/309 phiên thật có lịch sử tự mâu thuẫn — 255 chỗ (156 kết quả thứ hai cùng id, 74 message chen giữa, 24 kết quả lạc lượt, 1 lời gọi không kết quả) | G20: không có cờ — sửa lỗi thuần
A21: 2 | B21: M1-02 | C21: 1. Lõi tác tử | D21: P0 | E21: DEV-331 | F21: lược đồ công cụ thật: 25 869 token/lời gọi (trần tool_schema=4000 chưa dòng mã nào đọc). Cờ bật: 4 475 token, giảm 82,7 %; 73 → 18 công cụ | G21: GON_CONG_CU — TẮT
A22: 3 | B22: M1-03 | C22: 1. Lõi tác tử | D22: P0 | E22: DEV-332 | F22: 1 822 lời gọi của tác tử con trong 26 phiên thật, 0 lần qua lớp luật. Toàn công cụ đọc trừ một build.compile — lỗ hổng chưa bị bước vào, không phải được canh | G22: không có cờ — sửa lỗi thuần
A23: 4 | B23: M2-01 | C23: 2. Phân tích & thiết kế phần mềm | D23: P0 | E23: DEV-333 | F23: kịch bản 3 REQ + 3 phương án + 3 tiêu chí + 3 tệp: sửa MỘT REQ làm 9 hiện vật STALE → còn 3. Phép đo đầu ra 6→2 vì bị hàng rào E4020 chặn, đã sửa kịch bản đo | G23: TRUY_VET — TẮT (phần nền chạy cả khi tắt)
A24: 5 | B24: M2-02 | C24: 2. Phân tích & thiết kế phần mềm | D24: P0 | E24: DEV-334 | F24: 63 kho thật: 5/37 REQ có ít nhất một phép đo; 27 chưa có phương án nào nhận; 0 REQ đi hết chuỗi. Cột 'Mã nguồn' trống ở MỌI dự án vì hien_thuc_req vừa mới tồn tại | G24: REQ_PHU — TẮT (khối A2.2 trên tab không phụ thuộc cờ)
A25: 6 | B25: M2-03 | C25: 2. Phân tích & thiết kế phần mềm | D25: P0 | E25: DEV-335 | F25: 37 REQ thật: 25 sạch (67 %), 11 thiếu tiêu chí đo được, 2 có từ mơ hồ. Lần đo đầu ra 3 từ mơ hồ, một là kêu oan ('ít nhất 2 lần' là mức đo được) — đã vá | G25: REQ_CHAT_LUONG — TẮT (module yeu_cau.py luôn có)
A26: 7 | B26: M2-06 | C26: 2. Phân tích & thiết kế phần mềm | D26: P0 | E26: DEV-336 | F26: sổ cái thật: 26 lần đánh dấu 'xong' ngay sau một lần ghi mã, 19 lần (73 %) không có phép kiểm nào đạt ở giữa. Phép đo đầu ở mức dự án ra 0 — đúng nhưng đo sai câu hỏi | G26: KE_HOACH_CONG_KIEM — TẮT
A27: 8 | B27: M2-08 | C27: 2. Phân tích & thiết kế phần mềm | D27: P0 | E27: DEV-337 | F27: 185 tệp .c thật: 1 758 → 1 786 hàm thấy được (+28 hàm trước đây VÔ HÌNH: 8 ngắt + 20 bị regex tham lam nuốt). 78 hàm nay gắn nhãn 'isr', 70 trong đó vốn đã có trong danh sách | G27: không có cờ — sửa lỗi thuần
A28: 9 | B28: M3-01 | C28: 3. Mạch, ERC, HDL/FPGA | D28: P0 | E28: DEV-338 | F28: 0 phát hiện trên 5 mô hình mạch thật — và lý do đáng hơn con số: 3 kho CÓ Fact v_max thì KHÔNG có mô hình mạch, 5 kho có mạch thì không có Fact ấy; thêm nữa Fact dùng chủ thể chip:X mà ERC không tra tiền tố đó | G28: không có cờ — sửa lỗi thuần
A29: 10 | B29: M3-03 | C29: 3. Mạch, ERC, HDL/FPGA | D29: P0 | E29: DEV-339 | F29: 8 phát hiện trên 5 mạch thật (6 nguon_khong_cap + 2 net_mot_chan), trong đó net clock I2C nối đúng một chân. SÁU trong tám là 'mô hình chưa khai' chứ không phải 'mạch sai'. robot-canbang: 107 Port lá, KHÔNG Port nào là power_out | G29: không có cờ — sửa lỗi thuần
A30: 11 | B30: M3-04 | C30: 3. Mạch, ERC, HDL/FPGA | D30: P0 | E30: DEV-340 | F30: 0 phát hiện trên 5 mạch thật — và đây là con số ĐÚNG (hai lỗi này catastrophic, không bo nào sống tới lúc lưu kho). Đã CẤY hai bộ cấp vào bản sao kho robot-canbang để chứng minh luật sống: nổ đúng 1 blocker trên net +5V thật | G30: không có cờ — sửa lỗi thuần
A31: 12 | B31: M3-07 | C31: 3. Mạch, ERC, HDL/FPGA | D31: P0 | E31: DEV-341 | F31: Fact tới được ERC: 5 → 17 (+12). Ba kho có Fact datasheet thì TOÀN BỘ mang chủ thể chip:, tức trước đó không một Fact nào tới được ERC. Độ phủ 5 mạch thật nay đọc được | G31: không có cờ — sửa lỗi thuần
... A34: 15 | B34: M3-13 | C34: 3. Mạch, ERC, HDL/FPGA | D34: P0 | E34: DEV-344 | F34: testbench Verilog THẬT của bài 3: tb_pcpi_dot4 1/1, tb_pcpi_mac 1/1, tb_pcpi_vmini không đo được (tb gọi bản bram HAI CỔNG đã bị bỏ 02/10) — mẫu số là TỆP, không phải phép phá | G34: không có cờ (công cụ mới core=False)
A35: 16 | B35: M3-18 | C35: 3. Mạch, ERC, HDL/FPGA | D35: P0 | E35: DEV-345 | F35: 6 cặp (mạng cổng, .cst) thật → 1 chỗ CHẶN: blinky của riscv-tn20k-b dựng bitstream 4,6 MB với chân đồng hồ do nextpnr tự chọn (rơi đúng chân 4 — bằng may). Cả 7 tệp .cst thật đọc hết, 0 lỗi cú pháp | G35: không có cờ (công cụ mới core=False)
A36: 17 | B36: M4-01 | C36: 4. Kiểm thử & chất lượng | D36: P0 | E36: DEV-346 | F36: 18 ca chạy trình biên dịch C thật: tệp test in số đo {"T1":300} với ngưỡng <=255 → EIDE phán 1 ca HỎNG. Chưa kho cũ nào có tiêu chí unit test để đo lại trên dữ liệu thật | G36: không có cờ (công cụ mới core=False)
A37: 18 | B37: M4-02 | C37: 4. Kiểm thử & chất lượng | D37: P0 | E37: DEV-347 | F37: 25 ca dựng đúng trạng thái thật (tệp test 3 ca, 1 ca đỏ, hiện vật dat=False) → fs.write còn 1 ca thì test.weakened=True. Và hàng rào cũ criteria.has_result chưa bao giờ nổ ngoài sim-01 | G37: SIM_RUNNER_GIOI_HAN — TẮT
A38: 19 | B38: M4-05 | C38: 4. Kiểm thử & chất lượng | D38: P1 | E38: DEV-348 | F38: du-lieu/rtos-sinhvien, chạy CẢ HAI hành vi: cũ so_thay=1, mới so_thay=0 — logo_ptit.c từ 'bộ kiểm ĐỎ' thành 'mọi đột biến đều làm hỏng biên dịch'. Một ô xanh giả, đã sửa | G38: không có cờ — sửa lỗi thuần
A39: 20 | B39: M4-19 | C39: 4. Kiểm thử & chất lượng | D39: P2 | E39: DEV-349 | F39: chạy TẠI CHỖ trên ba dự án firmware thật: kết luận giống hệt lượt đột biến tại chỗ của M4-05, và 50/50 tệp giữ nguyên cả sha256 lẫn mtime | G39: không có cờ — sửa lỗi thuần
A40: 21 | B40: M4-04 | C40: 4. Kiểm thử & chất lượng | D40: P1 | E40: DEV-350 | F40: TÁI HIỆN được ca DANH-GIA §2.2 bằng máy trên control_rtos.c thật: bảng cũ 0 đột biến cho hằng hex, bảng mới dòng 147 → mutant SỐNG. Và chi_tiet trên 12 tệp thật: 110 s, điểm 0,0 | G40: không có cờ (tham số mới, mặc định giữ hành vi cũ)
A41: 22 | B41: M4-06 | C41: 4. Kiểm thử & chất lượng | D41: P0 | E41: DEV-351 | F41: đo TRƯỚC trên logo_ptit.c thật: điểm 0,0 · 30 mutant · 20 sống. Phần SAU chưa đo — cần lời gọi mô hình (§3.0 bắt hỏi trước), và dự án mẫu không có chỗ để đo | G41: TEST_HARDEN — TẮT
A42: 23 | B42: M4-07 | C42: 4. Kiểm thử & chất lượng | D42: P0 | E42: DEV-352 | F42: sổ cái 42 dự án: 327 lời gọi task.run có việc, 323 là verifier · 209/323 đề bài dài hơn trần 300 ký tự · gói bằng chứng dựng được CÓ NỘI DUNG trên 29/42 dự án, 0 lần đổ · loc_claim bỏ 95/1 706 câu (năm dấu hiệu kế hoạch chỉ bỏ được 11) | G42: VERIFIER_GOI_BANG_CHUNG — TẮT
A43: Việc còn MỞ (ngoài 84 việc chưa làm) | B43: Vì sao còn mở
A44: Bảy cờ mới đều còn TẮT | B44: GON_CONG_CU · TRUY_VET · REQ_PHU · REQ_CHAT_LUONG · KE_HOACH_CONG_KIEM · ERC_TU_DONG · SIM_RUNNER_GIOI_HAN. Cả bảy đổi thứ Agent nhìn thấy, đọc, hoặc LÀM ĐƯỢC mỗi lượt, nên chỉ bộ 76 ca chạy hai chế độ mới nói được chúng làm Agent khá hơn hay tệ hơn. Bộ ấy tốn tiền mô hình nên §3.0 bắt hỏi người dùng trước.
A45: kiem_cap_goi_tra() chưa thành hàng rào | B45: Soát được mọi phiên đã lưu, nhưng chưa hook nào gọi nó tự động — bắt được chuyện cũ, chưa chặn được chuyện mới.
A46: Luật ERC quá áp chưa nổ trên dữ liệu thật | B46: Đường dẫn đã thông ở M3-07, nhưng ba kho có Fact điện áp thì không có mô hình mạch, và ngược lại. Phải chờ một dự án có cả hai.
A47: Cột “Mã nguồn” của ma trận truy vết trống ở mọi dự án | B47: Nó đọc hien_thuc_req — trường vừa mới tồn tại, chưa tệp nào trên đĩa từng khai. Nên “chưa hiện thực” ở đó nghĩa là “chưa ai KHAI”, không phải “chưa ai viết”.
A48: Lỗi _go_dau trong src/eide/tools/design.py | B48: Viết .replace('d','d') nên 'ổn định' và 'ON DINH' không khớp nhau. Hàm ấy đang dùng cho một phép kiểm an toàn (người có thật sự chọn không). Tìm thấy ở M2-03, CHƯA sửa vì ngoài phạm vi — cần bộ ca kiểm riêng.
A49: subagent req-critic (bước 4 của M2-03) | B49: Kế hoạch ghi “tuỳ chọn, gộp M2-13”. Chưa làm, đúng theo kế hoạch.
A50: Hai luật kiểm chân FPGA chưa có dữ liệu để nổ | B50: chan_lech_kit và io_type_lech_bank cần Fact chân kit. Không kho nào trong repo có Fact pin:tangnano20k.* hay khoá vccio — nên hôm nay chỉ 3 trong 5 luật của M3-18 kết luận được gì trên dữ liệu thật. Cùng hình dạng với luật ERC quá áp.
A51: Một bitstream cũ đã dựng với chân đồng hồ tự chọn | B51: blinky của du-lieu/riscv-tn20k-b — xem DEV-345 và README §8. Không sửa hiện vật cũ: đó là dữ liệu của những lượt đo đã chốt. Từ nay phép kiểm chặn trước nextpnr.
A52: Ba công cụ mới nhất chưa lượt Agent nào GỌI | B52: hdl.sensitivity · hdl.constraints_check · test.criteria. Mã của cả ba đã chạy trên hiện vật thật, nhưng đó là tôi gọi hàm, không phải tác tử gọi công cụ. README §8 đếm cả ba vào phần chưa dùng thật.
A53: Bộ kiểm C của ba dự án firmware thật đều KHÔNG đo được độ nhạy | B53: rtos-sinhvien: 0/12 tệp đo được (4 font khong_thay, control_rtos.c trùng ký hiệu, main.c không dịch trên máy chủ, logo_ptit.c mọi mutant hỏng biên dịch). stm32f469-freertos và thu-nghiem-g6: bộ kiểm ĐỎ SẴN. Đây là trạng thái của dữ liệu đo, không phải lỗi sản phẩm — nhưng nó nghĩa là chưa dự án firmware nào trong repo có một con số độ nhạy đáng tin. Xem DEV-348.
A54: POL-N6-sua-test chưa nổ trên một phiên thật nào | B54: Hook sua_test_sau_do cấp dữ kiện cho lời gọi SẮP xảy ra, nên không soát lại được phiên đã lưu — khác mọi phép đo trước của đợt này. Nó đã có 25 ca kiểm và phá lại 27/27, nhưng chưa lượt tác tử thật nào chạm vào nó. Cùng hình dạng với ba luật kiểm thiếu dữ liệu ở trên, chỉ khác lý do.
... A88: Tôi ghi con số ca kiểm (1 895) vào BỐN tệp tài liệu TRƯỚC khi bộ kiểm đầy đủ chạy xong — số thật là 1 896. Một con số suy ra bằng phép cộng trong đầu trông giống hệt một con số đo được. | B88: M4-07 · DEV-352

Sheet Danh mục tối ưu
A1: DANH MỤC ĐIỂM CẦN TỐI ƯU — TÁC TỬ (AGENT) EIDE v3
A2: Mỗi dòng là một phát hiện từ đọc mã thật (vị trí tệp:dòng tại ngày 06/10/2026). Cột Giai đoạn tự tính từ Ưu tiên + Công sức. Cột Trạng thái / Người phụ trách / Ghi chú để anh theo dõi.
A4: Mã | B4: Mảng | C4: Tính năng / khối | D4: Chủ đề xuyên suốt | E4: Vị trí mã | F4: Hiện trạng (mã đang làm gì) | G4: Vấn đề / khoảng trống | H4: Mẫu kiến trúc đối chiếu | I4: Đề xuất tối ưu | J4: Lợi ích kỳ vọng | K4: Ưu tiên | L4: Công sức | M4: Giai đoạn | N4: Rủi ro / đánh đổi | O4: Chỉ số đo hiệu quả | P4: Liên quan / trùng với | Q4: Trạng thái | R4: Người phụ trách | S4: Ghi chú | T4: Ngày xong | U4: Mục DEV-LOG | V4: Ca kiểm trước → sau | W4: Đo trên DỮ LIỆU THẬT | X4: Cờ mặc định | Y4: Còn nợ / lưu ý
A5: M1-01 | B5: 1. Lõi tác tử | C5: Toàn vẹn cặp function_call ↔ function_response | D5: T01 Giao thức & độ bền vòng lặp | E5: loop.py:695-699 (_tool_loop), loop.py:900-913 (_one_tool), loop.py:1375-1440 (_resolve_gate), llm/gemini.py:161 (_to_contents) | F5: Một phản hồi Gemini có thể chứa nhiều tool_calls. Vòng lặp chạy từng lời gọi một; nếu lời gọi thứ k bật thẻ cổng (awaiting_human) thì `return` ngay, các lời gọi k+1..n không có function_response nào. Trong _one_tool, khi kết quả `ok` mà rỗng, một message role=user (nhac_nho) được append TRƯỚC message tool của chính lời gọi đó, nên một lượt văn bản của người chen giữa function_call và function_response. Khi người duyệt cổng, _resolve_gate append thêm một reminder role=user rồi một function_response THỨ HAI cho cùng call id (lần đầu là lỗi E4003). Mỗi kết quả công cụ còn được bọc trong một Content(role=user) riêng, và from_function_response không truyền `id`. | G5: Gemini 3.x đòi số function_response bằng số function_call của lượt model, và các response phải đứng liền sau lượt đó. Lịch sử bị lệch như trên gây lỗi 400 lúc chập chờn hoặc làm mô hình hiểu sai. Ca 02/10 ghi trong mã (tác tử tưởng lời giao việc 'bị cắt mất') cùng họ với lỗi này. Thiếu id thì hai lời gọi song song cùng tên không ghép được với response của mình. Đây là lỗi nền: nó làm hỏng đúng những lượt dài, nhiều công cụ. | H5: ReAct (độ đúng của giao thức tool-calling), Human-in-the-loop (checkpoint chạy tiếp) | I5: Thêm bước chuẩn hoá `_chuan_hoa_lich_su(messages)` trong gemini._to_contents: (1) gộp mọi message role=tool liền sau một lượt model vào MỘT Content gồm nhiều Part.from_function_response(id=..., name=..., response=...); (2) dời mọi message user/_he_thong chen giữa xuống sau khối response. Trong _tool_loop, khi một lời gọi bật cổng, sinh response tổng hợp cho các lời gọi còn lại: {ok:false, code:'E4010', message_vi:'bị hoãn vì cổng G-x đang chờ duyệt'}. Trong _resolve_gate, thay vì thêm response thứ hai, ghi kết quả thật vào một message user (text) có tham chiếu call id, hoặc thay hẳn response E4003 trong transcript bằng kết quả thật (transcript.thay_toan_bo). Thêm một test bất biến: mọi lượt model có N call thì theo sau đúng N response cùng id. | J5: Hết lỗi 400 chập chờn ở lượt nhiều công cụ; không còn ca tác tử 'kể sai' vì lịch sử mâu thuẫn; tiền đề bắt buộc để chạy song song lời gọi tool. | K5: P0 | L5: M | M5: =IF(K5="P0",IF(OR(L5="L",L5="XL"),"GĐ2","GĐ1"),IF(K5="P1",IF(L5="S","GĐ2","GĐ3"),"GĐ4")) | N5: Đụng vào phát lại transcript cũ (phiên đã lưu) nên phải chuẩn hoá lúc đọc chứ không sửa tệp; cần ReplayGateway để hồi quy. | O5: Số lỗi 400 INVALID_ARGUMENT / 100 lượt; tỉ lệ lượt có lịch sử vi phạm bất biến (test tĩnh trên ledger); số ca 'tác tử hỏi lại đề bài' sau khi duyệt cổng. | Q5: Xong | R5: Agent (Claude Opus 5) | T5: 06/10/2026 | U5: DEV-330 | V5: 1610 → 1615 | W5: 105/309 phiên thật có lịch sử tự mâu thuẫn — 255 chỗ (156 kết quả thứ hai cùng id, 74 message chen giữa, 24 kết quả lạc lượt, 1 lời gọi không kết quả) | X5: không có cờ — sửa lỗi thuần | Y5: kiem_cap_goi_tra() mới là THƯỚC ĐO, chưa hook nào chạy nó tự động
A6: M1-02 | B6: 1. Lõi tác tử | C6: Lược đồ công cụ hiển thị mỗi lượt | D6: T02 Ngữ cảnh, lược đồ công cụ & token | E6: tools/registry.py:139-144 (visible/declarations), loop.py:667, config.py:137 (tool_schema=4000) | F6: Đo trực tiếp bằng build_registry(): có 118 công cụ, trong đó 73 là core=True luôn hiện. Khai báo JSON khoảng 77.600 ký tự (≈26k token) được gửi trong MỌI lần gọi LLM. Có những mô tả rất dài (target.flash 2.937 ký tự, store.procedure_set 2.505, tool.propose 2.309). ContextBudget.tool_schema=4000 được khai nhưng không chỗ nào dùng tới. registry._unlocked chỉ tăng mà không bao giờ giảm suốt phiên (tool.search, các hook và _mo_khoa_theo_ngu_canh đều chỉ add). | G6: Mức 26k token lược đồ gấp khoảng 6,5 lần ngân sách đã định. Một lượt 40 lời gọi tốn khoảng 1 triệu token đầu vào chỉ cho phần lược đồ. Quan trọng hơn, 73 công cụ cùng lúc làm giảm độ chính xác chọn công cụ: nhiều công cụ na ná nhau (store.* / ckm.* / fact.*), mô tả dài thì chìm, và thường có khoảng 31/120 công cụ không bao giờ nổ như chính mã đã đo. Đây là 'lỗi nằm ở mô tả tool' đúng như nguyên tắc của thang đối chiếu. | H6: Routing (chọn bộ công cụ theo loại việc), Agentic RAG cho công cụ (tool retrieval) | I6: (1) Cưỡng chế ngân sách: trong _assemble, tính approx_tokens(json(declarations)) và ghi vào asm.tokens['tool_schema']; vượt 4000–6000 thì cảnh báo trong ledger và hạ dần các nhóm ít dùng. (2) Rút core xuống khoảng 15–20 công cụ nền (fs.*, store.get/list, fact.query, ask_user, tool.search, plan.enter, memory.note, task.run). Phần còn lại chia theo `group` thành các 'bộ' (Tài liệu, Firmware/Build, CKM-mạch, Mô phỏng, Phiên bản) và mở theo tín hiệu xác định: thực thể trong mentioned_entities, inventory (có chip chưa, có mã chưa), bước kế hoạch đang làm (b.cong_cu) và S0 annotations. (3) Cắt mỗi mô tả còn ≤400 ký tự: một câu 'khi nào dùng' và một câu 'khi nào KHÔNG dùng'; phần dài chuyển vào hint_for_agent của lỗi. (4) Gỡ khoá theo LRU: công cụ đã mở mà không gọi trong K lượt thì ẩn lại. (5) Giữ thứ tự khai báo ổn định (sắp theo tên) để prefix cache không vỡ. | J6: Giảm khoảng 60–75 % token đầu vào mỗi lời gọi; chọn công cụ đúng hơn; độ trễ mỗi bước thấp hơn. | K6: P0 | L6: M | M6: =IF(K6="P0",IF(OR(L6="L",L6="XL"),"GĐ2","GĐ1"),IF(K6="P1",IF(L6="S","GĐ2","GĐ3"),"GĐ4")) | N6: Ẩn nhầm một công cụ cần thiết sẽ làm tăng số lần tool.search (đây đúng là hình dạng lỗi DEV-302/305). Cần bảng ánh xạ tín hiệu → bộ công cụ và đo trên 76 TC trước khi bật. | O6: Token lược đồ / lời gọi (mục tiêu ≤6k); tỉ lệ lời gọi sai công cụ (E5004/E5006/schema_violation); số tool.search / lượt; pass rate 76 TC. | P6: M1-18, M4-18 | Q6: Xong | R6: Agent (Claude Opus 5) | T6: 06/10/2026 | U6: DEV-331 | V6: 1615 → 1623 | W6: lược đồ công cụ thật: 25 869 token/lời gọi (trần tool_schema=4000 chưa dòng mã nào đọc). Cờ bật: 4 475 token, giảm 82,7 %; 73 → 18 công cụ | X6: GON_CONG_CU — TẮT | Y6: cần bộ 76 ca hai chế độ mới dám bật. Luật cắt mô tả 160 ký tự chỉ thu 0,46 % — trung vị một mô tả là 37 ký tự; phần dài nằm ở SỐ LƯỢNG trường, muốn ăn tiếp phải sửa lược đồ từng công cụ (nhiệm vụ khác)
A7: M1-03 | B7: 1. Lõi tác tử | C7: Tác tử con (subagent) đi vòng qua hook và policy | D7: T03 Tác tử con & điều phối song song | E7: subagent.py:292-316 (chay) — `r = registry.run(call.tool, call.args, ctx)` | F7: Subagent gọi thẳng registry.run, không qua pre_tool_use (check_sandbox, check_explain, constant_guard, ghi_de_ban_cua_nguoi, doi_tieu_chi), không qua policy.decide (cổng G-*), không qua khoá plan mode (_khoa_khi_soan_ke_hoach), và không qua post_tool_use (ghi sổ tool_result, gắn cờ 'log rỗng'). Subagent 'firmware' có fs.write, fs.edit và build.compile; 'sim-runner' có fs.write và sim.criteria. | G7: Kiến trúc tuyên bố 'không có đường nào đi vòng qua ba lớp xác định' (docstring loop.py), nhưng subagent chính là đường vòng đó. Tác tử chính có thể giao cho firmware ghi mã chứa hằng số không nguồn (constant_guard không chạy), đè tệp người vừa sửa, hoặc ghi trong lúc kế hoạch còn chưa duyệt. N1/N8/N9 thủng đúng ở nhánh ít ai soi tới. | H7: Supervisor–Workers (worker phải chịu cùng hàng rào), Human-in-the-loop | I7: Tách phần thân _one_tool thành một hàm thuần `thuc_thi_cong_cu(call, ctx, *, hooks, policy, registry, che_do)` trả về (ket_qua, the_cong|None), dùng chung cho Agent và subagent.chay. Trong subagent: policy 'ask' → không dựng thẻ mà trả lỗi E4011 'cần người duyệt — ghi vào chua_lam'. Đồng thời áp boc_ket_qua cho kết quả và cộng ctx.tool_calls_used. Thêm test: subagent firmware ghi hằng số không nguồn thì phải bị chặn giống tác tử chính. | J7: Đóng lỗ hổng an toàn và độ tin cậy; hành vi của tác tử chính và tác tử con nhất quán; ledger đầy đủ cho cả nhánh con. | K7: P0 | L7: M | M7: =IF(K7="P0",IF(OR(L7="L",L7="XL"),"GĐ2","GĐ1"),IF(K7="P1",IF(L7="S","GĐ2","GĐ3"),"GĐ4")) | N7: Subagent có thể kẹt nhiều hơn vì bị chặn. Cần hint rõ để nó nộp chua_lam thay vì thử lại. | O7: Số lời gọi ghi của subagent không có dòng hook/policy trong ledger (mục tiêu 0); số hằng số không nguồn lọt vào mã do subagent ghi. | P7: M2-14 | Q7: Xong | R7: Agent (Claude Opus 5) | T7: 06/10/2026 | U7: DEV-332 | V7: 1623 → 1628 | W7: 1 822 lời gọi của tác tử con trong 26 phiên thật, 0 lần qua lớp luật. Toàn công cụ đọc trừ một build.compile — lỗ hổng chưa bị bước vào, không phải được canh | X7: không có cờ — sửa lỗi thuần | Y7: —
A8: M1-04 | B8: 1. Lõi tác tử | C8: Song song hoá lời gọi công cụ chỉ-đọc | D8: T03 Tác tử con & điều phối song song | E8: loop.py:695-699 (for call in rsp.tool_calls), tools/registry.py::run | F8: Mọi lời gọi chạy TUẦN TỰ, kể cả khi mô hình đã phát song song nhiều lời gọi chỉ-đọc trong một phản hồi (fs.read nhiều tệp, fact.query nhiều thực thể). Mã đo được trên phiên STM32F469: 54 % lời gọi (580/1078) là fs.read/grep/glob. Không có khái niệm DAG hay Joiner. | G8: Độ trễ cộng dồn theo số lời gọi, trong khi đọc và tra cứu độc lập nhau hoàn toàn chạy song song được. Mô hình cũng không được khuyến khích gom lời gọi, vì hiến pháp không nói gì về việc phát nhiều lời gọi một lúc, nên tiêu nhiều vòng LLM cho việc chỉ cần một vòng. | H8: LLMCompiler (DAG + chạy song song + Joiner), Parallelization (sectioning) | I8: Làm sau khi đã sửa toàn vẹn cặp gọi–trả. Chia batch thành hai pha: (a) TUẦN TỰ chạy plan-lock + pre_tool_use + policy.decide cho từng call để giữ thứ tự cổng; (b) các call được allow, có risk=='R1', không writes_artefact và nằm trong _CONG_CU_DOC thì chạy bằng concurrent.futures.ThreadPoolExecutor(max_workers=4); call ghi chạy tuần tự sau đó theo thứ tự mô hình phát. Mỗi call vẫn tính 1 vào tool_calls_used. Thêm một câu vào hiến pháp §Cách làm việc: 'cần đọc nhiều thứ độc lập thì phát nhiều lời gọi trong MỘT lượt'. Cân nhắc thêm công cụ `fs.read_many(paths[])` có trần tổng ký tự. | J8: Giảm 30–50 % thời gian thực của lượt khám phá; giảm số vòng LLM / lượt; ít chạm trần 300 s hơn. | K8: P1 | L8: M | M8: =IF(K8="P0",IF(OR(L8="L",L8="XL"),"GĐ2","GĐ1"),IF(K8="P1",IF(L8="S","GĐ2","GĐ3"),"GĐ4")) | N8: Ctx (da_doc, emit, ledger) cần an toàn luồng: khoá ghi ledger và append messages theo đúng thứ tự call. Kết quả lớn đổ về cùng lúc có thể đẩy ngữ cảnh. | O8: Số lời gọi / vòng LLM; thời gian trung vị / lượt; tỉ lệ lượt chạm trần thời gian. | P8: M1-05 | Q8: Chưa làm
A9: M1-05 | B9: 1. Lõi tác tử | C9: Supervisor–Workers: subagent tuần tự, không ngân sách, không cắt kết quả | D9: T03 Tác tử con & điều phối song song | E9: subagent.py:269-323 (chay), tools/dieu_phoi.py::task_run | F9: task.run chạy một subagent đồng bộ, với ngữ cảnh sạch (tốt), công cụ bị lọc (tốt) và báo cáo 6 trường (tốt). Nhưng: vòng `for _ in range(dn.toi_da_goi)` đếm số VÒNG LLM chứ không đếm số lời gọi; khi hết vòng không có lượt 'buộc nộp báo cáo' nên dễ ra lỗi E5007. Kết quả công cụ đi nguyên văn vào `tin` (không qua boc_ket_qua trần 4.000 token). Lời gọi LLM của subagent không được _usage_add, không kiểm ctx.budget_left (giây và lời gọi) và không ghi ledger llm_call. Không có cách giao nhiều worker song song. | G9: Subagent dễ tràn ngữ cảnh khi đọc tệp lớn, tiêu token mà người dùng không thấy (chi phí lượt bị báo thấp), có thể vượt trần 300 s của lượt, và hay thất bại ở bước cuối vì không bị nhắc nộp. Việc lớn (rà nhiều mô-đun, nạp nhiều datasheet) không được chia cho nhiều worker chạy song song, nên mất lợi ích chính của mẫu Supervisor–Workers. | H9: Supervisor–Workers, Parallelization (sectioning), Hierarchical | I9: (1) Đổi vòng thành ngân sách theo lời gọi: `while bc.so_goi < dn.toi_da_goi`, kèm trần giây riêng (vd. 90 s) lấy từ ctx.budget_left. (2) Hết ngân sách thì thêm một lượt cuối với tools=[] và lời nhắc 'NỘP BÁO CÁO JSON ngay, phần chưa làm ghi vào chua_lam'. (3) Áp memory.boc_ket_qua cho mọi kết quả tool của subagent. (4) Gọi agent._usage_add và ledger 'llm_call' với trường subagent=ma. (5) Thêm `task.run_many(viec:[{subagent, viec}], toi_da=3)` chạy song song bằng ThreadPoolExecutor, trả về danh sách báo cáo tóm tắt (tom_tat + ket_luan + bang_chung), không trả nguyen_van. | J9: Tỉ lệ subagent nộp đúng lược đồ tăng; chi phí thật nhìn thấy được; việc lớn xong trong ít lượt hơn. | K9: P1 | L9: M | M9: =IF(K9="P0",IF(OR(L9="L",L9="XL"),"GĐ2","GĐ1"),IF(K9="P1",IF(L9="S","GĐ2","GĐ3"),"GĐ4")) | N9: Song song làm tăng đột biến lượng token và quota 429. Hai worker ghi cùng tệp thì cần soft-lock theo tệp (ctx.locks) hoặc chỉ cho worker chỉ-đọc chạy song song. | O9: Tỉ lệ E5007 / task.run; token subagent / lượt (phải xuất hiện trong cost); thời gian lượt khi dùng run_many so với tuần tự. | P9: M1-04 | Q9: Chưa làm | S9: Kéo lên giai đoạn sớm hơn vì là tiền đề (xem §5 kế hoạch)
A10: M1-06 | B10: 1. Lõi tác tử | C10: Độc lập của verifier | D10: T04 Kiểm chứng độc lập (verifier) | E10: subagent.py:46 (doc_duoc_viec), subagent.py:150; tools/dieu_phoi.py::task_run; hooks/standard.py:557 (kiem_viec_chua_ai_kiem) | F10: DinhNghia.doc_duoc_viec=False được khai cho verifier, nhưng không có dòng nào thi hành cờ này. Đường SubagentStop (firmware/sim tuyên đạt) dùng viec_cho_verifier, chỉ đưa báo cáo và bằng chứng, nên đúng thiết kế. Còn đường phổ biến nhất (hook Stop kiem_viec_chua_ai_kiem bảo tác tử chính gọi task.run(subagent='verifier', viec=...)) để tác tử chính TỰ VIẾT đề cho verifier bằng văn xuôi, có thể kèm kỳ vọng ('đã chạy đúng, kiểm giúp'). Verifier dùng cùng model và cùng temperature 0 với tác giả. | G10: Nguyên tắc 'verifier không thấy đề bài, chỉ thấy bằng chứng' bị phá ở chính đường mà hook đang đẩy tác tử đi. Cùng model và cùng nhiệt độ thì xác suất lặp lại đúng thiên kiến của tác giả rất cao, nên kiểm chứng dễ thành đóng dấu. | H10: Evaluator–Optimizer, Debate (phản biện), Reflexion | I10: (1) Khi subagent=='verifier', task.run KHÔNG nhận `viec` tự do. Đổi lược đồ thành `bang_chung: [{kind, ref, khang_dinh}]` (mỗi mục là một khẳng định gắn với một ref mở được). Mã dựng đề bằng viec_cho_verifier và lọc bỏ từ ngữ kết luận như 'đạt', 'thành công'. (2) Có thể tự sinh bang_chung từ ledger: các changeset của lượt (co_viec_chua_kiem đã có dau_vet). (3) Chạy verifier với nhiệt độ khác hoặc thinking_level cao, kèm system prompt 'giả định báo cáo sai, tìm phản chứng'. (4) Với khẳng định R3/R4 (nạp chip, tuyên đạt sim), chạy 2 verifier độc lập; bất đồng thì hạ kết luận và trình cả hai. | J10: Bắt được nhiều đạt giả hơn (đúng ca 'flash khớp từng byte nhưng vẫn chạy bản cũ' ghi trong hook). | K10: P1 | L10: S | M10: =IF(K10="P0",IF(OR(L10="L",L10="XL"),"GĐ2","GĐ1"),IF(K10="P1",IF(L10="S","GĐ2","GĐ3"),"GĐ4")) | N10: Thêm 1–2 lời gọi LLM ở cuối việc; verifier khắt khe quá sẽ sinh nhiều 'chua_du_du_kien'. | O10: Tỉ lệ verifier bác (khong_dat) trên bộ ca có cài lỗi cố ý; tỉ lệ đạt giả lọt qua trên 76 TC; độ trùng nhau giữa 2 verifier. | P10: M4-07, M4-08 | Q10: Chưa làm
A11: M1-07 | B11: 1. Lõi tác tử | C11: Báo cáo có lược đồ của subagent | D11: T03 Tác tử con & điều phối song song | E11: subagent.py::doc_bao_cao (tách dòng JSON cuối bằng startswith('{')) | F11: Subagent phải kết thúc bằng MỘT dòng JSON trong văn bản tự do. Mã lấy dòng cuối bắt đầu bằng '{' rồi json.loads. JSON xuống nhiều dòng, nằm trong ```json``` hay có chữ theo sau đều thành lỗi lược đồ (E5007). | G11: Hỏng định dạng làm mất trọn kết quả của cả một subagent: phần việc vẫn còn trong kho nhưng 'không có kết luận nào để dùng'. Gemini có cơ chế structured output và function calling bắt buộc, chính xác hơn nhiều so với tách văn bản. | H11: Prompt Chaining (cổng kiểm bằng code), Supervisor–Workers | I11: Đăng ký một 'công cụ nộp' ảo `bao_cao.nop` với parameters đúng 6 trường (ket_luan có enum, bang_chung có items object) và thêm vào `khai` của mọi subagent. Subagent kết thúc bằng cách gọi nó, chay() bắt lời gọi đó làm báo cáo. Dự phòng: ở lượt buộc nộp, đặt response_mime_type='application/json' + response_schema trong GenerateContentConfig (thêm tham số `response_schema` vào LLMGateway.stream). Giữ doc_bao_cao làm đường lùi, nhưng tách JSON bằng parser cân ngoặc chứ không theo dòng. | J11: Tỉ lệ báo cáo hợp lệ gần 100 %; bỏ được một lớp hỏng ngẫu nhiên. | K11: P1 | L11: S | M11: =IF(K11="P0",IF(OR(L11="L",L11="XL"),"GĐ2","GĐ1"),IF(K11="P1",IF(L11="S","GĐ2","GĐ3"),"GĐ4")) | N11: Cần kiểm Gemini 3.8-flash có cho dùng response_schema cùng tools trong một lời gọi hay không; nếu không thì tách hai lời gọi. | O11: Tỉ lệ E5007 do lỗi lược đồ / tổng task.run. | Q11: Chưa làm
A12: M1-08 | B12: 1. Lõi tác tử | C12: Routing theo loại việc khi chỉ có MỘT model | D12: T05 Lập kế hoạch & thực thi theo bước | E12: config.py:40 (ALLOWED_MODELS={'gemini-3.8-flash'}), config.py:191-205 (ModelConfig), llm/gemini.py:67-75 (GenerateContentConfig) | F12: Chủ sản phẩm chốt chỉ dùng gemini-3.8-flash cho main, subagent và summarize; assert_allowed cưỡng chế. GenerateContentConfig không đặt thinking_config (thinking_level / thinking_budget), không đặt tool_config (mode AUTO/ANY/NONE). Mọi lời gọi (đọc tệp, lập kế hoạch, kiểm chứng, tóm tắt nén) dùng cùng một cấu hình suy nghĩ. | G12: Không đổi được model, nhưng 'model nhỏ hay model mạnh' vẫn mô phỏng được bằng mức suy nghĩ. Hiện mọi bước cùng một chế độ: bước đọc/tra đơn giản trả tiền suy nghĩ thừa (thoughts_tokens đã được đo nhưng không ai điều khiển), còn bước lập kế hoạch, verifier, design-review và plan.exit lại không được đẩy suy nghĩ sâu hơn. | H12: Routing (phân loại → cấu hình chuyên biệt), Plan-and-Execute | I12: Thêm `muc_nghi` vào LLMGateway.stream (giá trị thap|vua|cao) → types.ThinkingConfig(thinking_level=...) hoặc thinking_budget, tuỳ API của 3.8-flash. Bộ định tuyến XÁC ĐỊNH (0 token) trong _tool_loop: (a) đang plan mode, vòng đầu sau câu người mới, verifier, design-review, compaction C2/C3 → cao; (b) vòng ngay sau một batch chỉ-đọc thành công → thap; (c) sau lỗi E-* lặp lại → cao. Dùng tool_config mode=NONE cho lượt 'buộc trả lời' (hết ngân sách, hook Stop said_something) để mô hình không gọi tool nữa. Ghi muc_nghi vào ledger llm_call. | J12: Giảm thoughts_tokens ở bước dễ, tăng chất lượng ở bước then chốt; không vi phạm ràng buộc một model. | K12: P1 | L12: S | M12: =IF(K12="P0",IF(OR(L12="L",L12="XL"),"GĐ2","GĐ1"),IF(K12="P1",IF(L12="S","GĐ2","GĐ3"),"GĐ4")) | N12: Tham số thinking của 3.8-flash cần kiểm tài liệu thật; định tuyến sai có thể làm bước khó bị nghĩ nông. | O12: thoughts_tokens / lượt; pass@1 các ca lập kế hoạch và kiểm chứng; số vòng LLM / lượt. | Q12: Chưa làm
A13: M1-09 | B13: 1. Lõi tác tử | C13: Temperature 0 với dòng Gemini 3 | D13: T01 Giao thức & độ bền vòng lặp | E13: config.py:198 (temperature=0.0), llm/gemini.py:70, llm/gateway.py docstring §F3 | F13: Mọi lời gọi dùng temperature 0 và seed=7 để đạt 'tất định'. Chính mã ghi nhận nhiều ca quay vòng: ledger.query 21 lần liên tiếp, fs.read 28 lần, 14 lời gọi chỉ-đọc rải nhiều công cụ. Vì vậy mới phải có _nhac_neu_dang_quay_vong. | G13: Theo khuyến nghị công khai của Google cho các model Gemini 3, nên giữ temperature mặc định 1.0; hạ thấp hơn có thể gây lặp hoặc giảm chất lượng, nhất là khi model có suy nghĩ. Cần xác minh lại cho riêng 3.8-flash. Hành vi quay vòng đã đo được khớp với triệu chứng này. Còn 'tất định' thì đằng nào cũng không có thật (docstring gemini.py tự thừa nhận phải chạy mỗi ca 5 lần). | H13: ReAct (chất lượng vòng lặp), nguyên tắc 'có eval trước khi leo thang' | I13: Chạy A/B trên 76 TC × 5 lần: temperature 0 / 0.7 / 1.0 (bỏ seed hoặc giữ seed), đo pass rate, số lần hook quay vòng nổ và số lời gọi / lượt. Nếu 1.0 tốt hơn thì đặt mặc định 1.0 cho tác tử chính và subagent, giữ 0 cho các tác vụ trích xuất thuần (fact.extract, bộ nén C2) qua tham số `temperature=` của stream (đã có sẵn). Cập nhật docstring §F3: tất định được bảo đảm bằng lớp mã (S0, policy, hook), không bằng nhiệt độ. | J13: Kỳ vọng ít quay vòng hơn, ít chạm trần 40 lời gọi hơn, câu trả lời tốt hơn. | K13: P1 | L13: S | M13: =IF(K13="P0",IF(OR(L13="L",L13="XL"),"GĐ2","GĐ1"),IF(K13="P1",IF(L13="S","GĐ2","GĐ3"),"GĐ4")) | N13: Kết quả biến động hơn giữa các lần chạy, bộ đo phải dựa trên tỉ lệ thống kê chứ không trông vào khớp từng chữ. | O13: Số lần _nhac_neu_dang_quay_vong nổ / 100 lượt; tỉ lệ lượt hết ngân sách; pass rate trung bình qua 5 lần chạy. | Q13: Chưa làm
A14: M1-10 | B14: 1. Lõi tác tử | C14: Xử lý finish_reason và retry khi đang stream | D14: T01 Giao thức & độ bền vòng lặp | E14: llm/gemini.py:81-92 (vòng retry), :113-114, :130 (on_text); loop.py:663-690 | F14: finish_reason được ghi vào Response nhưng vòng lặp không đọc. MAX_TOKENS (max_output_tokens=8192; tuỳ API, phần suy nghĩ có thể cũng tính vào trần này), MALFORMED_FUNCTION_CALL, SAFETY hay RECITATION đều bị coi như 'trả lời xong'. Retry bọc toàn bộ _one_call: nếu luồng đã stream một phần chữ (on_text đã emit ra Console) rồi mới hỏng, lần thử lại stream LẠI từ đầu, nên người dùng thấy chữ lặp. Lùi mũ tới 8 s × 3 lần mà không kiểm ctx.budget_left; không có timeout cho từng lời gọi. | G14: Câu trả lời bị cắt ngang vì MAX_TOKENS bị hiểu là kết thúc lượt, và mã đang viết dở thì mất. Lời gọi hàm hỏng định dạng làm lượt dừng im lặng (đúng loại 'lượt im lặng' mà _cau_im_lang phải chữa cháy). Chữ lặp làm giảm tin cậy giao diện. | H14: ReAct (độ bền vòng lặp) | I14: Trong _tool_loop, sau stream: finish=='MAX_TOKENS' và không có tool_calls → append reminder 'câu trả lời bị cắt, viết tiếp từ chỗ dừng hoặc ghi phần dài ra tệp bằng fs.write' rồi lặp (tối đa 1 lần). 'MALFORMED_FUNCTION_CALL' → reminder nêu lại lược đồ công cụ vừa gọi hỏng rồi lặp. SAFETY → nói thật với người dùng. Trong gemini.stream: nếu đã emit chữ thì không retry tự động mà trả EideError có cờ partial=True để vòng lặp quyết định, hoặc gửi console_stream(reset=True) trước khi thử lại. Cấp `deadline` từ ctx.budget_left vào stream và đặt http timeout cho client. | J14: Bớt lượt bị cắt ngang hoặc im lặng; giao diện không lặp chữ; không vượt trần thời gian vì retry. | K14: P1 | L14: S | M14: =IF(K14="P0",IF(OR(L14="L",L14="XL"),"GĐ2","GĐ1"),IF(K14="P1",IF(L14="S","GĐ2","GĐ3"),"GĐ4")) | N14: Thêm nhánh logic; cần ScriptedGateway giả lập từng finish_reason để test. | O14: Phân bố finish_reason trong ledger llm_call (cần ghi thêm trường này); số lượt kết thúc với MAX_TOKENS; số sự cố chữ lặp. | Q14: Chưa làm
A15: M1-11 | B15: 1. Lõi tác tử | C15: Ngân sách token mỗi lượt và cửa sổ làm việc | D15: T02 Ngữ cảnh, lược đồ công cụ & token | E15: config.py:50-60 (Budget), config.py:200 (context_window=1_000_000), config.py:155-160 (nguong_c1..c4), loop.py:1502-1504 (_context_pressure) | F15: Ngân sách lượt chỉ có max_tool_calls=40 và max_seconds=300, không có trần token. Nén C1 bắt đầu ở 60 % của 1 triệu token (600k), C2 ở 700k. Áp lực ngữ cảnh được ước bằng len(str(m))//3, đếm cả base64 của thought_signature trong `parts` và cả `envelope` nằm trong message. | G15: Một lượt có thể tiêu hàng triệu token mà không trần nào chặn. Ở cửa sổ vài trăm nghìn token, chất lượng truy hồi và bám chỉ dẫn của model đã giảm rõ ('context rot') từ rất lâu trước khi chạm 60 %, nên nén đến quá muộn với chất lượng nhưng quá sớm với ước lượng (đếm cả chữ ký base64). Usage thật (rsp.usage.input_tokens) đã có nhưng không được dùng để đo áp lực. | H15: Memory-augmented/MemGPT (quản lý cửa sổ), nguyên tắc 'mọi vòng lặp có trần token' | I15: (1) Thêm Budget.max_tokens_luot (vd. 600k đầu vào cộng dồn) kiểm trong _tool_loop bằng ctx.usage_luot.input_tokens, hết thì dừng như hết lời gọi. (2) Thêm ModelConfig.cua_so_lam_viec (vd. 200k) làm mẫu số cho muc_nen thay cho 1M. (3) _context_pressure lấy usage.input_tokens của phản hồi gần nhất, cộng phần message mới thêm ước theo chữ, bỏ trường parts/envelope khi ước. | J15: Chi phí lượt có trần dự đoán được; nén sớm giữ chất lượng bám ngữ cảnh; ước lượng khớp thực tế. | K15: P1 | L15: S | M15: =IF(K15="P0",IF(OR(L15="L",L15="XL"),"GĐ2","GĐ1"),IF(K15="P1",IF(L15="S","GĐ2","GĐ3"),"GĐ4")) | N15: Nén sớm hơn thì C2 (có LLM) chạy nhiều hơn; cần đo tỉ lệ nén C2 thất bại. | O15: Token đầu vào / lượt (p50/p95); sai số giữa ước lượng và usage thật; pass rate theo độ dài phiên. | Q15: Chưa làm
A16: M1-12 | B16: 1. Lõi tác tử | C16: Prompt caching và khối nhắc lặp trong transcript | D16: T02 Ngữ cảnh, lược đồ công cụ & token | E16: loop.py:1497-1500 (_user_block), context/assemble.py:240-280, llm/gemini.py (không dùng CachedContent), memory/compact.py::c1 | F16: Hiến pháp nằm trong system_instruction (ổn định, tốt). Toàn bộ khối <system-reminder> (eide_md ≤3k, inventory, facts, human_edits, pending, skills-hint) được NỐI CỨNG vào message user của mỗi lượt và lưu vĩnh viễn trong transcript. C1 chỉ stub kết quả công cụ, không động tới các reminder cũ. Chỉ có implicit caching, không dùng explicit cache (client.caches). Danh sách tool đổi mỗi khi một công cụ được mở khoá, làm vỡ prefix. | G16: Sau N lượt có N bản inventory/facts/pending cũ cùng nằm trong ngữ cảnh. Chúng mâu thuẫn với bản mới ('0 yêu cầu' ở lượt 3 với '5 yêu cầu' ở lượt 9), trái với §3 'inventory là sự thật', và tốn token. Prefix cache vỡ mỗi lần tool list đổi, nên tỉ lệ cached_tokens thấp hơn mức có thể đạt. | H16: Memory-augmented/MemGPT, Agentic RAG (ngữ cảnh đúng lúc) | I16: (1) Lưu reminder ở trường riêng `_reminder` của message user. Khi dựng contents cho LLM thì chỉ ghép reminder của message user MỚI NHẤT, còn các message cũ chỉ gửi `text` gốc. (2) Thêm bước C0 trong compact: xoá reminder cũ khỏi transcript. (3) Cố định thứ tự tool (sắp theo tên); bộ core ổn định đặt trước, công cụ mở khoá đặt sau. (4) Khi phần tĩnh (constitution + tool core) ≥ ngưỡng cache tối thiểu của API thì dùng client.caches.create với TTL khoảng 30 phút, truyền cached_content vào config. (5) Theo dõi tỉ lệ cached/input (Usage.cached_tokens đã có). | J16: Giảm mạnh token lặp; hết mâu thuẫn inventory; tỉ lệ cache cao hơn nên rẻ và nhanh hơn. | K16: P1 | L16: M | M16: =IF(K16="P0",IF(OR(L16="L",L16="XL"),"GĐ2","GĐ1"),IF(K16="P1",IF(L16="S","GĐ2","GĐ3"),"GĐ4")) | N16: Explicit cache có phí lưu trữ và cần làm mới khi constitution hay tool đổi; phải giữ được phát lại transcript phiên cũ. | O16: cached_tokens / input_tokens; token trung bình / lời gọi theo số lượt của phiên; số ca tác tử dẫn inventory cũ. | P16: M5-13 | Q16: Chưa làm
A17: M1-13 | B17: 1. Lõi tác tử | C17: Plan-and-Execute: thiếu Replanner và bước thực thi có cấu trúc | D17: T05 Lập kế hoạch & thực thi theo bước | E17: ke_hoach.py (KeHoach, Buoc, doi_chieu), tools/ke_hoach.py (plan.enter/exit/step_done/merge/cancel), hooks/standard.py:497 (doi_chieu_ke_hoach) | F17: Plan mode tốt ở phần LẬP: khoá công cụ ghi, kiem_ke_hoach kiểm tên công cụ có thật và mỗi bước có hien_vat, thieu_phan_tich đòi bước kiến trúc và code.analyze, la_viec_lon tính bằng mã, G-SCOPE cho người duyệt, step_done đòi hiện vật mở ra được. Nhưng không có `plan.revise`: muốn sửa thì phải cancel rồi enter lại, và kế hoạch cũ bị cất. Buoc không có trường phụ thuộc và không có tiêu chí xong kiểm được bằng máy. doi_chieu chỉ so TÊN công cụ. Không có executor theo bước: tác tử chính tự nhảy giữa các bước trong một vòng ReAct chung với ngân sách 40 lời gọi cho cả lượt. | G17: Replan đắt (phải duyệt lại từ đầu) nên tác tử có xu hướng đi chệch trong im lặng thay vì sửa kế hoạch. Không có tiêu chí xong thì step_done chỉ kiểm 'có tệp' chứ không kiểm 'tệp đạt'. Không có phụ thuộc thì không biết bước nào làm song song được hay bước nào bị chặn khi một bước trước hỏng. | H17: Plan-and-Execute (Planner/Executor/Replanner), ReWOO, LLMCompiler | I17: (1) Thêm vào Buoc: `phu_thuoc: list[int]` và `tieu_chi_xong: str` (một lệnh hoặc truy vấn kiểm được, vd. 'build.compile ok', 'test.run pass', 'store.get REQ-3 tồn tại'). step_done tự chạy phép kiểm này khi có thể. (2) Công cụ `plan.revise(thay_doi, vi_sao)`: giữ các bước đã xong, sửa hoặc chèn bước chưa làm. Nếu thay đổi không làm kế hoạch lớn hơn (la_viec_lon không đổi) và không thêm cổng thì không cần duyệt lại, chỉ hiện diff trong <pending>. (3) Replanner tự động: bước thất bại 2 lần (cùng mã lỗi) hoặc doi_chieu phát hiện ≥3 công cụ ngoài kế hoạch → hook Stop chèn 'gọi plan.revise' thay cho lời nhắc chung chung. (4) Executor theo bước: lượt 'làm tiếp' chỉ đưa vào <pending> bước kế tiếp đang mở cùng ngân sách con (vd. 15 lời gọi / bước). | J17: Bớt đi chệch im lặng; bước 'xong' có ý nghĩa kiểm chứng; việc lớn đi qua nhiều lượt ổn định hơn. | K17: P1 | L17: L | M17: =IF(K17="P0",IF(OR(L17="L",L17="XL"),"GĐ2","GĐ1"),IF(K17="P1",IF(L17="S","GĐ2","GĐ3"),"GĐ4")) | N17: Kế hoạch phức tạp hơn thì mô hình soạn sai nhiều hơn; plan.revise không duyệt có thể bị lạm dụng để lách G-SCOPE (giữ quy tắc: thêm cổng hoặc R3 thì phải duyệt). | O17: Tỉ lệ kế hoạch hoàn thành không bị cancel; số bước step_done bị E6004; số lần lệch kế hoạch / kế hoạch; số lượt / kế hoạch. | P17: M2-06, M2-07 | Q17: Chưa làm
A18: M1-14 | B18: 1. Lõi tác tử | C18: Reflexion: biến thất bại thành bài học lâu dài | D18: T06 Reflexion – bài học dài hạn | E18: loop.py:642-660 (hết ngân sách), loop.py::_nhac_neu_dang_quay_vong, tools/writing.py:229 (memory.note, mục cố định Mục tiêu/Chip/Quyết định/Giả định/Quy ước/Đừng), hooks/standard.py (Stop) | F18: Thất bại được ghi ledger (incident, budget_exhausted, verifier bác, quay vòng, E-code lặp) và được nói ra cho người dùng, nhưng KHÔNG được chưng cất thành bài học. EIDE.md không có mục 'Bài học'; memory.note chỉ chạy khi mô hình tự nhớ ra mà gọi. Các 'bài học đo được' hiện chỉ nằm trong chú thích mã do người viết, chứ tác tử không tự học. | G18: Cùng một lỗi lặp lại qua phiên (vd. cày fs.read thay vì dùng addr2line, quên plan.step_done, tìm tệp sắp tự viết). Tác tử không có cơ chế mang kinh nghiệm thất bại sang lần sau, nên mỗi phiên bắt đầu từ con số 0 về hành vi. | H18: Reflexion, Memory-augmented/MemGPT | I18: (1) Thêm mục 'Bài học' vào EideMd, tác tử được ghi, có trần khoảng 15 dòng theo kiểu FIFO hoặc theo điểm dùng. (2) Hook cuối lượt `chung_cat_bai_hoc`: khi lượt có incident thuộc {budget_exhausted, quay vòng nổ, verifier khong_dat, E-code giống nhau ≥3 lần}, gọi 1 lần LLM (model summarize, thinking thấp, temperature 0) với đầu vào là chuỗi công cụ, lỗi và kết quả cuối, đầu ra theo lược đồ {tinh_huong, sai_o_dau, lan_sau_lam_gi, tu_khoa}. Hoặc dùng mẫu xác định cho các ca đã biết. (3) Truy hồi: assemble thêm khối <bai_hoc> ≤300 token, chọn theo tu_khoa khớp câu người dùng hoặc thực thể. (4) Người xem và xoá được trên khối A14.6; dòng nào được dùng mà lượt đó thành công thì tăng điểm. | J18: Giảm lỗi lặp giữa các phiên; tác tử thông minh dần theo dự án. | K18: P1 | L18: M | M18: =IF(K18="P0",IF(OR(L18="L",L18="XL"),"GĐ2","GĐ1"),IF(K18="P1",IF(L18="S","GĐ2","GĐ3"),"GĐ4")) | N18: Bài học sai hoặc quá khái quát sẽ thành thiên kiến lâu dài, nên cần trần dòng, nguồn [run-xx] và quyền xoá của người. Mỗi lần thất bại tốn thêm 1 lời gọi LLM. | O18: Tỉ lệ tái phát cùng loại incident giữa các phiên; số lần quay vòng / 100 lượt trước và sau; tỉ lệ bài học bị người xoá. | P18: M3-21, M5-14 | Q18: Chưa làm
A19: M1-15 | B19: 1. Lõi tác tử | C19: Tự động hoá kiểm chứng cuối việc bằng mã | D19: T04 Kiểm chứng độc lập (verifier) | E19: hooks/standard.py:557-612 (kiem_viec_chua_ai_kiem), loop.py:536-543 (chỉ 1 vòng thêm), loop.py:890-894 (ghi_chua_kiem) | F19: Khi có việc đã ghi mà chưa kiểm, hook Stop mở khoá task.run và CHÈN LỜI NHẮC bảo tác tử gọi verifier, chỉ được 1 vòng thêm. Các hook Stop khác (giả định, human_edits, said_something, hỏi xong thì làm tiếp) có thể nổ cùng lúc và bị nối thành một khối injection dài. Nếu mô hình lờ đi thì việc kết thúc mà không ai kiểm. | G19: Chính mã đã nhận định 'SubagentStop gọi verifier bằng MÃ vì lúc mô hình tự tin nhất là lúc nó ít gọi nhất', nhưng ở đường phổ biến nhất lại quay về trông vào mô hình. Nhiều lời nhắc gộp trong 1 vòng duy nhất cạnh tranh nhau, nên mô hình dễ chỉ làm cái đầu tiên. | H19: Evaluator–Optimizer, Prompt Chaining (cổng kiểm bằng code) | I19: Ở hook Stop, khi điều kiện chua_kiem đúng và không có kế hoạch dở: vòng lặp TỰ chạy SA.chay(ma='verifier', viec=viec_cho_verifier(bằng chứng dựng từ dau_vet và changeset của lượt)) bằng mã. Kết quả được append như một message tool giả (role=user, có cấu trúc) rồi mới cho tác tử 1 vòng để trình bày, kèm luật 'verifier bác thì phải nói ra'. Ưu tiên các injection của Stop theo bậc (human_edits > verifier > giả định > hỏi-xong), mỗi vòng thêm chỉ đưa 1–2 cái quan trọng nhất. | J19: Kiểm chứng chạy 100 % ở cuối mỗi đợt việc, không phụ thuộc mô hình có nghe lời hay không. | K19: P1 | L19: S | M19: =IF(K19="P0",IF(OR(L19="L",L19="XL"),"GĐ2","GĐ1"),IF(K19="P1",IF(L19="S","GĐ2","GĐ3"),"GĐ4")) | N19: Thêm 1 subagent (≤10 lời gọi) cuối mỗi đợt việc; cần gộp với trần thời gian của lượt. | O19: Tỉ lệ đợt việc có ghi mà có verifier chạy (mục tiêu ~100 %); tỉ lệ verifier bác; số vòng thêm bị bỏ phí. | P19: M4-10 | Q19: Chưa làm
A20: M1-16 | B20: 1. Lõi tác tử | C20: Phản biện cho quyết định thiết kế | D20: T07 Phản biện thiết kế (Debate/ToT) | E20: ke_hoach.py::thieu_phan_tich (đòi store.option_create/option_choose/adr_create), subagent.py SUBAGENT['design-review'] | F20: Kế hoạch viết mã mới phải có bước chọn kiến trúc (option/ADR), đây là điểm mạnh. Nhưng việc so phương án và chọn do CÙNG một tác tử, trong cùng một vòng, không có rubric chấm và không có vai phản biện. design-review chỉ chạy khi tác tử chính tự giao, và chỉ soi bản đồ mạch. | G20: Quyết định kiến trúc là điểm ảnh hưởng lớn nhất mà lại ít kiểm nhất: một góc nhìn, không phản chứng, không tiêu chí đo. Đúng loại quyết định mà mẫu Debate và Evaluator–Optimizer sinh ra để xử lý. | H20: Debate (nhiều vai phản biện + trọng tài), Evaluator–Optimizer (rubric, có trần vòng), ToT (sinh nhiều hướng rồi chấm) | I20: Thêm subagent 'phan-bien' (chỉ công cụ đọc, prompt 'tìm lý do phương án được chọn sẽ hỏng: tài nguyên chip, thời gian thực, khả năng test, rủi ro người'). Khi gọi store.option_choose hoặc store.adr_create, hook post_tool_use tự chạy phan-bien với rubric cố định (5 tiêu chí, mỗi tiêu chí 0–2, bắt buộc dẫn Fact). Điểm < ngưỡng hoặc có phản chứng dẫn Fact VÀNG/BẠC → trả về tác tử tối đa 1 vòng sửa, rồi đưa cả hai quan điểm vào thẻ G-DESIGN cho người làm trọng tài. Trần: 1 vòng phản biện, 1 vòng sửa. | J20: Quyết định kiến trúc có lý lẽ hai chiều và bằng chứng; người duyệt thấy được đánh đổi. | K20: P2 | L20: M | M20: =IF(K20="P0",IF(OR(L20="L",L20="XL"),"GĐ2","GĐ1"),IF(K20="P1",IF(L20="S","GĐ2","GĐ3"),"GĐ4")) | N20: Tăng token và độ trễ ở các bước kiến trúc (ít xảy ra nên chấp nhận được); phản biện cùng model có thể yếu, nên dùng thinking cao. | O20: Tỉ lệ ADR bị người sửa hoặc bác sau duyệt; số lần phải đổi kiến trúc giữa chừng kế hoạch. | P20: M2-04, M2-13 | Q20: Chưa làm
A21: M1-17 | B21: 1. Lõi tác tử | C21: Phát hiện quay vòng | D21: T01 Giao thức & độ bền vòng lặp | E21: loop.py:548-618 (_nhac_neu_dang_quay_vong, NGUONG_QUAY_VONG=6, NGUONG_TONG_DOC=10) | F21: Đếm theo tên công cụ (≥6) và theo tổng lời gọi chỉ-đọc (≥10), chỉ khi lượt chưa ghi gì. Mỗi loại nhắc 1 lần, gợi ý 4 lối ra (có tool.propose). Không phát hiện lời gọi TRÙNG Y HỆT (cùng tool và args), không đếm lỗi lặp cùng mã E-*, không leo thang sau lần nhắc đầu. | G21: Mô hình lờ lời nhắc thì vẫn cày tới hết 40 lời gọi. Lời gọi trùng y hệt (đọc lại cùng tệp, cùng ledger.query) tốn cả một lượt vòng mà kết quả không đổi. Lỗi cùng mã lặp lại (mô hình 'gọi lại y hệt', trái với hiến pháp) không bị bắt. Một lượt đã ghi một tệp rồi quay vòng thì miễn nhiễm hoàn toàn. | H21: ReAct (kiểm soát vòng lặp), Plan-and-Execute (leo thang sang replan) | I21: (1) Giữ ctx.da_goi_hash = Counter(hash(tool, json.dumps(args, sort_keys=True))). Lần trùng thứ 2 với công cụ chỉ-đọc thì không chạy lại mà trả stub 'kết quả y hệt lời gọi #k (đã có trong ngữ cảnh)'. (2) Đếm (tool, error.code) ≥2 → nhắc riêng kèm hint_for_agent của lỗi. (3) Leo thang: sau lần nhắc thứ nhất mà còn thêm ≥5 lời gọi chỉ-đọc thì gọi LLM vòng kế với tool_config mode=NONE, buộc trả lời hoặc gọi plan.enter/ask_user. (4) Tính lại điều kiện 'đã ghi' theo cửa sổ trượt 10 lời gọi gần nhất thay vì cả lượt. | J21: Cắt phần đuôi lãng phí của lượt quay vòng; ít lượt hết ngân sách hơn. | K21: P1 | L21: S | M21: =IF(K21="P0",IF(OR(L21="L",L21="XL"),"GĐ2","GĐ1"),IF(K21="P1",IF(L21="S","GĐ2","GĐ3"),"GĐ4")) | N21: Đọc lại sau khi tệp đã đổi thì không phải trùng: phải đưa mtime hoặc hash nội dung vào khoá (C1 đã có _khoa_doc để tham khảo). | O21: Số lời gọi trùng y hệt / lượt; tỉ lệ lượt hết 40 lời gọi; số lời gọi sau lần nhắc quay vòng đầu tiên. | Q21: Chưa làm
A22: M1-18 | B22: 1. Lõi tác tử | C22: tool.search và cơ chế nạp trễ | D22: T02 Ngữ cảnh, lược đồ công cụ & token | E22: tools/registry.py:146-170 (search), tools/builtin.py:482-500 (tool.search) | F22: Chấm điểm theo chuỗi con hoặc fnmatch trên tên, summary_vi và keywords, chưa chuẩn hoá dấu tiếng Việt (trong khi hooks/s0.py đã có normalize_vi). Mở khoá tới 8 công cụ khớp; kết quả chỉ có name/summary/risk/requires, KHÔNG có lược đồ tham số. Công cụ chỉ gọi được ở vòng LLM SAU. Có lời nhắc tool.propose khi không khớp (tốt). | G22: Câu truy vấn không dấu hoặc khác chữ thì trượt. Mỗi lần tìm tốn trọn một vòng LLM trước khi gọi được công cụ. Mở 8 công cụ một lúc làm phình lược đồ vĩnh viễn (xem mục lược đồ). Tìm mờ trả về công cụ không liên quan. | H22: Agentic RAG (viết lại truy vấn, chấm độ liên quan) áp cho công cụ | I22: (1) Chuẩn hoá normalize_vi cho cả truy vấn lẫn chỉ mục; chấm BM25 trên tên + summary + keywords + returns_vi. (2) Chỉ mở khoá các công cụ đạt ngưỡng điểm, tối đa 3; kèm `ly_do_khop` để mô hình biết vì sao. (3) Mở khoá chủ động không cần vòng tìm: trong _assemble, nếu câu người dùng khớp mạnh keywords của một công cụ core=False thì mở luôn (đây là cách đã làm tay cho skill.load và plan.*). (4) Ghi ledger 'tool_search' gồm truy vấn, danh sách trả về và công cụ được gọi sau đó, để đo precision. | J22: Bớt vòng LLM lãng phí; công cụ đúng hiện ra đúng lúc; giảm số công cụ 'chưa nổ lần nào'. | K22: P2 | L22: S | M22: =IF(K22="P0",IF(OR(L22="L",L22="XL"),"GĐ2","GĐ1"),IF(K22="P1",IF(L22="S","GĐ2","GĐ3"),"GĐ4")) | N22: Mở khoá chủ động sai sẽ phình lược đồ; cần trần và cơ chế LRU đi kèm. | O22: Precision@3 của tool.search (công cụ trả về có được gọi ngay sau đó không); số tool.search / lượt; số công cụ chưa nổ lần nào. | P22: M1-02 | Q22: Chưa làm
A23: M1-19 | B23: 1. Lõi tác tử | C23: Kiểm tham số công cụ | D23: T01 Giao thức & độ bền vòng lặp | E23: tools/registry.py:219-232 (_validate_args), tools/registry.py::run (E5999) | F23: Chỉ kiểm thiếu trường required và thừa trường lạ. Không kiểm kiểu (integer/string/array), không kiểm enum, không kiểm lược đồ lồng nhau (explain, items của buoc). Sai kiểu thì nổ trong thân công cụ thành E5999 'lỗi bên trong công cụ, không phải lỗi tham số của bạn'. | G23: Thông điệp E5999 nói sai nguyên nhân: lỗi do tham số mà lại bảo 'không phải lỗi tham số', nên mô hình không biết sửa gì và thường đổi hướng hoặc bỏ cuộc thay vì sửa một ký tự. Gemini cũng đã bị sanitize_schema bỏ bớt ràng buộc nên hay gửi sai kiểu hơn. | H23: Prompt Chaining (cổng kiểm bằng code), nguyên tắc 'lỗi thường nằm ở mô tả và lược đồ tool' | I23: Viết bộ kiểm JSON Schema tối giản (type, enum, items, properties lồng, minimum/maximum, có ép kiểu an toàn kiểu '3'→3), hoặc dùng jsonschema nếu chấp nhận phụ thuộc. Trả schema_violation có đường dẫn trường (vd. 'buoc[2].cong_cu: thiếu') và giá trị mong đợi. Ở nhánh Exception chung, nếu là TypeError hoặc KeyError phát sinh khi gọi fn thì phân loại lại thành lỗi tham số. | J23: Mô hình tự sửa lời gọi sai ngay ở vòng sau; giảm E5999 giả. | K23: P2 | L23: S | M23: =IF(K23="P0",IF(OR(L23="L",L23="XL"),"GĐ2","GĐ1"),IF(K23="P1",IF(L23="S","GĐ2","GĐ3"),"GĐ4")) | N23: Kiểm chặt quá sẽ bác những lời gọi trước đây vẫn chạy được nhờ công cụ tự xử lý; cần chạy qua bộ test công cụ. | O23: Số E5999 / 1000 lời gọi; tỉ lệ lời gọi sửa thành công ở vòng kế sau schema_violation. | Q23: Chưa làm
A24: M1-20 | B24: 1. Lõi tác tử | C24: Đo lường và eval quỹ đạo | D24: T15 Đo lường & bộ đánh giá (eval) | E24: loop.py:672-676 (ledger llm_call), loop.py::_report, tools/chay_usecase.py, tools/bo_usecase.py, tools/theo_doi.py | F24: Ledger đã ghi đủ: llm_call (model, usage in/out/cached/thoughts, danh sách tool, elapsed), tool_use, tool_result, hook, gate, incident, turn.end. Có harness 76 TC chạy qua app thật, có ReplayGateway và theo_doi.py tổng kết 'cơ chế nào đã nổ'. Nhưng phép chấm 76 TC chỉ là 'có dấu hiệu của thứ đề bài chờ', không chấm quỹ đạo. Không có bảng chỉ số chuẩn mỗi phiên (lời gọi/lượt, cache ratio, quay vòng, tỉ lệ cổng, tỉ lệ verifier bác). Subagent không ghi llm_call; finish_reason không được ghi. | G24: Mọi đề xuất tối ưu ở trên (temperature, lược đồ, song song, thinking) đều cần một thước đo ổn định trước khi bật. Hiện mỗi thay đổi phải đọc tay chuỗi công cụ, và hồi quy chất lượng (khác với hồi quy pass/fail) không được bắt. | H24: Nguyên tắc 'có bộ đánh giá (eval) trước khi leo thang', Evaluator–Optimizer (giám khảo theo rubric) | I24: (1) Module `eide/do_luong.py`: từ ledger tính chỉ số theo lượt và theo phiên (n_llm, n_tool, tỉ lệ chỉ-đọc, cached/input, thoughts/out, số nhắc quay vòng, số lượt hết ngân sách, số cổng mở/duyệt/bác, tỉ lệ verifier dat/khong_dat, phân bố finish_reason), xuất JSON cho CI. (2) Ghi thêm finish_reason, muc_nghi và subagent vào llm_call. (3) Eval quỹ đạo: với mỗi TC, khai 'công cụ bắt buộc phải gọi / cấm gọi / hiện vật phải tồn tại' (kiểm bằng mã), cộng một LLM-giám khảo theo rubric 4 tiêu chí (đúng việc, có nguồn, nói giả định, không đạt giả) chạy offline. (4) Cổng CI: so với mốc cơ sở, chặn merge khi pass rate giảm >3 điểm hoặc token/lượt tăng >15 %. | J24: Mọi tối ưu có số đo trước và sau; bắt hồi quy hành vi sớm. | K24: P1 | L24: M | M24: =IF(K24="P0",IF(OR(L24="L",L24="XL"),"GĐ2","GĐ1"),IF(K24="P1",IF(L24="S","GĐ2","GĐ3"),"GĐ4")) | N24: LLM-giám khảo có thiên lệch, cần hiệu chỉnh trên một mẫu người chấm; chạy app thật 76 TC × 5 lần tốn chi phí. | O24: Có hay không bảng chỉ số tự động mỗi lần chạy; tương quan giữa điểm giám khảo và điểm người chấm; số hồi quy bị CI chặn. | P24: M4-20, M4-21 | Q24: Chưa làm | S24: Kéo lên giai đoạn sớm hơn vì là tiền đề (xem §5 kế hoạch)
A25: M1-21 | B25: 1. Lõi tác tử | C25: CodeAct cho việc phân tích tạm thời | D25: T09 Phân tích mã tĩnh & CodeAct | E25: nang_luc.py + tools/nang_luc.py (tool.propose / tool.reload), loop.py::_nhac_neu_dang_quay_vong (lựa chọn 4) | F25: Tác tử có thể tự viết công cụ Python LÂU DÀI qua tool.propose: duyệt bằng thẻ hiện mã nguồn, phải có test xanh, là changeset và nằm ở .eide/cong-cu. Đây là điểm mạnh lớn. Không có đường viết một đoạn mã dùng MỘT LẦN để trả lời nhanh một câu hỏi phân tích (đếm, lọc, đối chiếu nhiều tệp, tính toán), nên tác tử hoặc cày fs.read/grep (54 % lời gọi) hoặc phải đi cả quy trình đề xuất công cụ. | G25: Câu hỏi kiểu 'hàm nào gọi X qua con trỏ', 'tổng kích thước section', 'đối chiếu pinout giữa 3 tệp' cần hàng chục lời gọi JSON, trong khi một đoạn Python 10 dòng giải xong. tool.propose quá nặng cho việc dùng một lần. | H25: CodeAct | I25: Thêm công cụ `py.phan_tich(ma, dau_vao_tep[])` mức R1: chạy trong tiến trình con có giới hạn (thư mục dự án mount chỉ-đọc, không mạng, timeout 10 s, trần RAM, trần 4k ký tự stdout), chỉ cho thư viện chuẩn và các tiện ích đọc ELF/map có sẵn. Không ghi được tệp; mã và kết quả vào ledger. Nếu cùng một đoạn mã được dùng lại ≥3 lần thì hook gợi ý nâng cấp thành tool.propose (kèm chính số đo đó làm vi_sao). | J25: Giảm mạnh số lời gọi đọc / lượt ở các câu hỏi phân tích; cầu nối tự nhiên sang tool.propose. | K25: P2 | L25: L | M25: =IF(K25="P0",IF(OR(L25="L",L25="XL"),"GĐ2","GĐ1"),IF(K25="P1",IF(L25="S","GĐ2","GĐ3"),"GĐ4")) | N25: Sandbox trên macOS khó làm kín (cần sandbox-exec hoặc container); rủi ro an toàn nếu rò quyền ghi hoặc mạng nên phải qua policy và cổng nếu cần. Kết quả mã sai mà trông tin cậy. | O25: Số lời gọi / lượt ở nhóm câu hỏi phân tích; tỉ lệ py.phan_tich lỗi; số đoạn được nâng thành công cụ. | P25: M2-17, M3-08 | Q25: Chưa làm
A26: M1-22 | B26: 1. Lõi tác tử | C26: Độ bền lớp cấp quyền khi điều kiện lỗi | D26: T01 Giao thức & độ bền vòng lặp | E26: policy/engine.py::_eval (raise ValueError), loop.py:850-852 (perm = self.policy.decide trong _one_tool), loop.py::turn (try/finally không có except) | F26: _eval ném ValueError khi một biểu thức `when` hoặc `auto_if` trong policy.yaml không tính được. Ý định đúng: không âm thầm cho qua. Nhưng _one_tool và turn không bắt ngoại lệ này, nên nó làm sập cả lượt (chỉ có finally ghi turn.end), mô hình không nhận được lỗi có hướng dẫn, và các lời gọi còn lại trong batch không có response. | G26: Một dòng luật viết sai (hoặc một hook đưa xuống facts kiểu lạ) biến thành sự cố toàn lượt thay vì một lời từ chối an toàn. Trái với tinh thần 'lỗi quay về mô hình như dữ liệu'. | H26: Human-in-the-loop (thất bại an toàn), Prompt Chaining (cổng kiểm) | I26: Bọc policy.decide trong _one_tool bằng try/except ValueError → coi là Decision('deny') với mã E4012 'luật cấp quyền lỗi, đã chặn an toàn', ghi incident kèm biểu thức, và báo người dùng bằng notice. Thêm test tĩnh lúc khởi động: thử _eval mọi biểu thức trong policy.yaml với một env mẫu để bắt lỗi cú pháp ngay khi nạp. | J26: Không còn sập lượt vì cấu hình; lỗi luật lộ ra ngay lúc khởi động. | K26: P2 | L26: S | M26: =IF(K26="P0",IF(OR(L26="L",L26="XL"),"GĐ2","GĐ1"),IF(K26="P1",IF(L26="S","GĐ2","GĐ3"),"GĐ4")) | N26: Thấp. | O26: Số lượt kết thúc bằng exception chưa bắt; số lỗi policy phát hiện lúc khởi động. | Q26: Chưa làm
A27: M2-01 | B27: 2. Phân tích & thiết kế phần mềm | C27: Truy vết yêu cầu (traceability) REQ → thiết kế → mã → test | D27: T08 Yêu cầu & truy vết | E27: src/eide/deps.py::ha_nguon_cua (dòng 52–79); src/eide/history.py::ghi_kho (dòng 109–140); src/eide/store/db.py:411 | F27: deps.py có hai đường lan STALE: 'theo khai báo' (đọc deps.upstream của hiện vật) và 'theo loại' (bảng HA_NGUON: req → option, adr, block_diagram, code, criteria…). Kho có cột deps, nhưng history.ghi_kho không nhận và không truyền tham số deps. Grep toàn bộ src/eide chỉ thấy db.py ghi deps, nên deps.upstream luôn rỗng. | G27: Đường 'khai báo' không bao giờ chạy, nên chỉ còn lan theo loại. Sửa một REQ bất kỳ thì MỌI tệp code, mọi criteria, mọi option đều bị đánh STALE. Báo động giả hàng loạt dạy người dùng bỏ qua băng cảnh báo, đúng điều human_edit.py tự cảnh báo. Không trả lời được câu 'REQ FR-03 do tệp nào hiện thực, test nào kiểm', nên không có ma trận truy vết thật. | H27: Blackboard (kho hiện vật là bảng trạng thái chung), Memory-augmented | I27: Thêm tham số deps: dict|None vào History.ghi_kho rồi truyền xuống store.apply. Thêm trường 'hien_thuc_req: [FR-..]' (tuỳ chọn) vào fs.write/fs.edit, store.option_create (đã có dap_ung_req), ckm.module_set (đã có dap_ung_req), sim.criteria (đã có do_req ở từng assert) và test.run. Ánh xạ các trường này thành deps.upstream. Trong ha_nguon_cua: khi hiện vật có upstream khai báo thì KHÔNG lan theo loại cho nó (khai báo thắng mặc định). Viết hàm mới deps.ma_tran_truy_vet(store) → bảng REQ × {option, adr, code, criteria/assert, sim_result/test}, kèm bốn cột 'chưa thiết kế / chưa hiện thực / chưa kiểm / kiểm trượt'. | J27: STALE chỉ sáng đúng chỗ bị ảnh hưởng. Có ma trận truy vết để đưa vào tài liệu đề án và để tác tử tự hỏi 'REQ nào chưa có test'. | K27: P0 | L27: M | M27: =IF(K27="P0",IF(OR(L27="L",L27="XL"),"GĐ2","GĐ1"),IF(K27="P1",IF(L27="S","GĐ2","GĐ3"),"GĐ4")) | N27: Tác tử có thể khai thiếu hien_thuc_req. Cần cảnh báo mềm khi fs.write một tệp mã mà không gắn REQ nào, đồng thời giữ đường lan theo loại làm dự phòng cho hiện vật không khai. | O27: Số hiện vật bị STALE mỗi lần sửa REQ (kỳ vọng giảm >70%); tỉ lệ REQ có đủ chuỗi REQ→code→test; tỉ lệ STALE được người 'chấp nhận không sửa' (đo báo động giả) | P27: M4-11 | Q27: Xong | R27: Agent (Claude Opus 5) | T27: 06/10/2026 | U27: DEV-333 | V27: 1628 → 1637 | W27: kịch bản 3 REQ + 3 phương án + 3 tiêu chí + 3 tệp: sửa MỘT REQ làm 9 hiện vật STALE → còn 3. Phép đo đầu ra 6→2 vì bị hàng rào E4020 chặn, đã sửa kịch bản đo | X27: TRUY_VET — TẮT (phần nền chạy cả khi tắt) | Y27: ma_tran_truy_vet() chưa lên tab (làm ở M2-02)
A28: M2-02 | B28: 2. Phân tích & thiết kế phần mềm | C28: Ma trận truy vết hiển thị và cổng 'phủ yêu cầu' trước khi báo xong | D28: T08 Yêu cầu & truy vết | E28: src/eide/surfaces.py::requirements (dòng 129–200); src/eide/hooks/standard.py::kiem_viec_chua_ai_kiem (dòng 557–612) | F28: Tab A2 có bảng REQ (A2.1), bảng phương án (A2.3, có cột 'Đáp ứng REQ/KHÔNG đáp ứng') và bảng ADR. Bảng tiêu chí mô phỏng hiện cột 'Đo yêu cầu nào' và ghi '— chưa gắn REQ —' khi thiếu. Stop hook buộc gọi verifier, nhưng verifier 'cố ý KHÔNG biết đề bài': nó chỉ đối chiếu bằng chứng với lời khai. | G28: Không có chỗ nào gộp lại thành câu 'trong 12 REQ có 3 REQ chưa có assert/test nào đo'. Verifier không xét phủ yêu cầu, nên tác tử có thể báo 'xong' khi một REQ chưa ai đụng tới. Kiểm thử phản ứng theo việc vừa làm, không chủ động theo đặc tả. | H28: Evaluator–Optimizer, Prompt Chaining (cổng kiểm bằng mã), Human-in-the-loop | I28: Thêm khối A2.5 'Ma trận truy vết' vào surfaces.requirements, dựng từ deps.ma_tran_truy_vet. Thêm Stop hook mới 'req_chua_phu': nếu có REQ loai FR/NFR mà không có assert do_req hoặc test trỏ tới, thì chèn system-reminder liệt kê các REQ đó và đòi một trong hai việc: viết sim.criteria/test, hoặc tuyên bố rõ là ngoài phạm vi lượt này. Hook chỉ chạy khi kế hoạch hiện tại đã hoàn thành (giống cách kiem_viec_chua_ai_kiem hoãn khi plan chưa xong), để không tốn lượt. | J28: Kiểm thử thành chủ động: tác tử biết thiếu test ở đâu trước khi người dùng phát hiện. | K28: P0 | L28: S | M28: =IF(K28="P0",IF(OR(L28="L",L28="XL"),"GĐ2","GĐ1"),IF(K28="P1",IF(L28="S","GĐ2","GĐ3"),"GĐ4")) | N28: Thêm một vòng Stop, tốn khoảng 1 lượt. Cần trần: hook chỉ nổ một lần mỗi lượt. | O28: Tỉ lệ REQ có ≥1 assert/test (coverage yêu cầu); số REQ 'mồ côi' khi kết thúc kế hoạch; số lỗi do người dùng tìm ra sau khi tác tử báo xong | Q28: Xong | R28: Agent (Claude Opus 5) | T28: 07/10/2026 | U28: DEV-334 | V28: 1637 → 1646 | W28: 63 kho thật: 5/37 REQ có ít nhất một phép đo; 27 chưa có phương án nào nhận; 0 REQ đi hết chuỗi. Cột 'Mã nguồn' trống ở MỌI dự án vì hien_thuc_req vừa mới tồn tại | X28: REQ_PHU — TẮT (khối A2.2 trên tab không phụ thuộc cờ) | Y28: khối là A2.2 chứ KHÔNG phải A2.5 như kế hoạch ghi — A2.5 đã là khối Kế hoạch chia việc
A29: M2-03 | B29: 2. Phân tích & thiết kế phần mềm | C29: Kiểm chất lượng yêu cầu (mơ hồ, mâu thuẫn, thiếu tiêu chí chấp nhận) | D29: T08 Yêu cầu & truy vết | E29: src/eide/tools/writing.py::store_req_create (dòng 165–197) | F29: store.req_create bắt buộc source_quote (N7), còn criteria là tuỳ chọn (mặc định ''). Hàm không kiểm gì khác: không kiểm tiêu chí có đo được không (đơn vị, ngưỡng), không dò từ mơ hồ ('nhanh', 'ổn định', 'thông minh'), không so với REQ đã có để phát hiện trùng hay mâu thuẫn. Grep 'mơ hồ|mâu thuẫn|EARS|INVEST' trong src/eide không thấy bộ kiểm yêu cầu nào. Các ca TC004 (mơ hồ) và TC005 (mâu thuẫn hoặc bất khả thi) trong tools/bo_usecase.py hoàn toàn dựa vào lời nhắc mô hình. | G29: REQ không có tiêu chí đo được thì không sinh được assert, và chuỗi truy vết đứt ngay từ gốc. Mâu thuẫn giữa hai REQ (ví dụ 'pin 1 tuần' và 'gửi Wi-Fi mỗi giây') chỉ được phát hiện nếu mô hình tình cờ nhớ ra. | H29: Evaluator–Optimizer (rubric chất lượng yêu cầu), Prompt Chaining (cổng bằng mã) | I29: Tạo src/eide/yeu_cau.py gồm: (1) kiem_tieu_chi(criteria) bằng regex tìm số + đơn vị + phép so, không có thì trả cảnh báo 'tiêu chí chưa đo được'; (2) TU_MO_HO = {nhanh, ổn định, thông minh, dễ dùng, tốt, nhiều…} để dò trong text; (3) trung_lap(store, text) dùng độ tương tự token để phát hiện REQ trùng ý và gợi ý req_update; (4) với NFR có số, so cùng 'đại lượng' (ví dụ dòng, công suất) giữa các REQ và Fact để nêu cặp có thể mâu thuẫn. store.req_create trả kèm 'canh_bao_chat_luong' (không chặn). Thêm lệnh gom 'req.review' gọi subagent mới 'req-critic' (chỉ đọc, ≤8 lời gọi) chấm theo rubric kiểu INVEST/ISO 29148 (rõ ràng, đo được, khả thi, nhất quán, đầy đủ) và trả danh sách câu hỏi làm rõ để đưa vào ask_user. | J29: Bắt lỗi yêu cầu ở đầu chuỗi, nơi sửa rẻ nhất. TC004/TC005 chuyển từ phụ thuộc lời nhắc sang có bằng chứng bằng mã. | K29: P0 | L29: M | M29: =IF(K29="P0",IF(OR(L29="L",L29="XL"),"GĐ2","GĐ1"),IF(K29="P1",IF(L29="S","GĐ2","GĐ3"),"GĐ4")) | N29: Heuristic dò từ mơ hồ dễ kêu thừa. Chỉ nên cảnh báo, không chặn. req-critic tốn thêm token mỗi đợt đặc tả. | O29: Tỉ lệ REQ có tiêu chí đo được; số câu hỏi làm rõ sinh ra trên mỗi đặc tả; điểm pass TC004/TC005 theo người chấm (không chỉ dấu hiệu bề mặt) | Q29: Xong | R29: Agent (Claude Opus 5) | T29: 07/10/2026 | U29: DEV-335 | V29: 1646 → 1657 | W29: 37 REQ thật: 25 sạch (67 %), 11 thiếu tiêu chí đo được, 2 có từ mơ hồ. Lần đo đầu ra 3 từ mơ hồ, một là kêu oan ('ít nhất 2 lần' là mức đo được) — đã vá | X29: REQ_CHAT_LUONG — TẮT (module yeu_cau.py luôn có) | Y29: subagent req-critic CHƯA làm (chờ khung subagent M2-13). Và tìm thấy lỗi _go_dau trong src/eide/tools/design.py viết .replace('d','d') nên 'ổn định' ≠ 'ON DINH' — CHƯA sửa, ngoài phạm vi
A30: M2-04 | B30: 2. Phân tích & thiết kế phần mềm | C30: So sánh phương án kiến trúc có chấm điểm (ToT/Debate) | D30: T07 Phản biện thiết kế (Debate/ToT) | E30: src/eide/tools/design.py::option_create, option_choose; src/eide/surfaces.py:170–185 (bảng A2.3) | F30: store.option_create ghi từng phương án gồm ten, kien_truc, chi_phi_uoc, do_kho (thấp/trung bình/cao), rui_ro, dap_ung_req, khong_dap_ung. Docstring của design.py tự trích §E2: 'bảng so sánh cạnh nhau có CỘT ĐIỂM theo ràng buộc'. Lược đồ không có trường điểm hay trọng số, bảng A2.3 không có cột điểm. option_choose không kiểm có ≥2 phương án. Không có bước nào sinh nhiều phương án độc lập rồi chấm. | G30: Các phương án do cùng một mạch suy nghĩ sinh ra, thường có một phương án 'đúng' và vài phương án làm nền. Không có rubric nên không so được định lượng. Yêu cầu §E2 chưa được hiện thực. | H30: Tree of Thoughts (sinh nhiều hướng, chấm, chọn), Debate (phản biện chéo + trọng tài), Evaluator–Optimizer | I30: (1) Thêm vào option_create trường 'diem: {REQ/ràng buộc → 0..5, ly_do}' và thêm artefact 'rubric' (tieu_chi, trong_so, nguon = REQ/NFR). (2) Thêm công cụ mới 'design.explore' (core=False, R1) chạy N=3 subagent 'architect' với seed hoặc vai khác nhau (an toàn thời gian thực, chi phí thấp, dễ bảo trì), mỗi subagent đề xuất 1 phương án trong ngữ cảnh riêng. Sau đó 1 subagent 'design-critic' chấm từng phương án theo rubric và nêu điểm yếu chí mạng. Kết quả ghi thành option_*, kèm điểm trọng số tính bằng mã. (3) option_choose cảnh báo khi chỉ có 1 phương án hoặc khi chọn phương án không phải điểm cao nhất mà chưa có lý do trong he_qua. (4) Bảng A2.3 thêm cột 'Điểm (trọng số)'. Trần: N≤3, mỗi subagent ≤10 lời gọi. | J30: Quyết định kiến trúc có căn cứ định lượng, đúng tinh thần 'mọi thứ phải có sở cứ'. Giảm thiên lệch một phương án. | K30: P1 | L30: M | M30: =IF(K30="P0",IF(OR(L30="L",L30="XL"),"GĐ2","GĐ1"),IF(K30="P1",IF(L30="S","GĐ2","GĐ3"),"GĐ4")) | N30: Token nhân khoảng 3–4 lần ở bước thiết kế; độ trễ tăng. Chỉ bật cho việc 'tạo mới' (thieu_phan_tich đã phân biệt) hoặc khi người dùng yêu cầu. | O30: Số phương án trung bình mỗi quyết định; độ chênh điểm giữa phương án chọn và phương án nhì; tỉ lệ ADR bị đổi lại sau đó (đảo quyết định) | P30: M1-16 | Q30: Chưa làm
A31: M2-05 | B31: 2. Phân tích & thiết kế phần mềm | C31: Kiểm tham chiếu REQ trong phương án | D31: T08 Yêu cầu & truy vết | E31: src/eide/tools/design.py::option_create; đối chiếu src/eide/tools/ckm.py:286 | F31: ckm.module_set kiểm từng mã trong dap_ung_req có tồn tại trong kho (req_la) và báo lại. store.option_create nhận dap_ung_req/khong_dap_ung mà không kiểm REQ có thật không, cũng không kiểm hợp của hai danh sách có phủ hết REQ hiện có. | G31: Tác tử có thể ghi REQ không tồn tại, hoặc bỏ sót REQ: phương án không nói gì về FR-05, nên người duyệt không biết nó có đáp ứng hay không. Bảng so sánh có lỗ mà trông như đủ. | H31: Prompt Chaining (cổng kiểm bằng mã) | I31: Trong option_create: tính req_la = REQ khai mà không có trong kho, và chua_xet = {REQ trong kho} − dap_ung − khong_dap_ung. Có req_la thì trả lỗi E5005 kèm gợi ý. Có chua_xet thì trả note_vi liệt kê 'phương án chưa nói gì về: …'. Bảng A2.3 tô các ô 'chưa xét'. | J31: Mọi phương án được xét đầy đủ trên tập REQ; bảng so sánh trung thực. | K31: P1 | L31: S | M31: =IF(K31="P0",IF(OR(L31="L",L31="XL"),"GĐ2","GĐ1"),IF(K31="P1",IF(L31="S","GĐ2","GĐ3"),"GĐ4")) | N31: Rất thấp. | O31: Số REQ 'chưa xét' trung bình mỗi phương án; số lỗi tham chiếu REQ lạ | Q31: Chưa làm
A32: M2-06 | B32: 2. Phân tích & thiết kế phần mềm | C32: Kế hoạch sinh mã dạng Prompt Chaining có cổng kiểm từng bước | D32: T05 Lập kế hoạch & thực thi theo bước | E32: src/eide/ke_hoach.py::Buoc, kiem_ke_hoach, thieu_phan_tich; src/eide/tools/ke_hoach.py:246–270 | F32: Đây là điểm mạnh. Plan mode khoá công cụ ghi; plan.exit kiểm hình thức (2–20 bước, công cụ có thật, mỗi bước có hiện vật) và chặn kế hoạch viết mã mới khi thiếu bước chọn kiến trúc (option/adr) và thiếu bước nói cấu trúc mã. Kế hoạch sửa mã bị chặn nếu thiếu code.analyze. plan.step_done đòi hiện vật thật (E6004). Tuy vậy, Buoc chỉ có viec/cong_cu/hien_vat/cong/chi_phi: không có trường 'kiểm bằng gì' và không có trường 'REQ nào'. Phép kiểm 'cấu trúc mã' chỉ là tìm từ khoá (_TU_CAU_TRUC: 'module', 'api', 'thư mục'…). | G32: Mỗi bước đã có hiện vật nhưng không có cổng chất lượng: viết xong firmware/x.c rồi sang bước sau mà không bắt build/test. Tác tử có thể lách phép kiểm cấu trúc chỉ bằng cách viết chữ 'module' vào ghi_chu. Không truy được bước nào hiện thực REQ nào. | H32: Prompt Chaining, Plan-and-Execute | I32: Thêm vào Buoc hai trường: 'kiem: str' (một tên công cụ kiểm: build.compile | test.run | sim.run | hdl.lint | code.analyze) và 'req: list[str]'. kiem_ke_hoach đòi mọi bước có _la_ma(b) phải có kiem. plan.step_done với bước có kiem thì đối chiếu sổ cái: phải có lời gọi công cụ kiem ok=True SAU lần ghi hiện vật của bước đó, nếu không thì từ chối (mã lỗi mới E6006). Thay phép tìm từ khoá cấu trúc bằng yêu cầu một hiện vật 'code_structure' (danh sách tệp + trách nhiệm + giao diện) được ghi trước bước sinh mã đầu tiên. | J32: Lỗi được chặn ngay tại bước sinh ra nó, không dồn tới cuối kế hoạch. | K32: P0 | L32: M | M32: =IF(K32="P0",IF(OR(L32="L",L32="XL"),"GĐ2","GĐ1"),IF(K32="P1",IF(L32="S","GĐ2","GĐ3"),"GĐ4")) | N32: Mỗi bước thêm một lời gọi build/test. Với AVR/ARM biên dịch nhanh nên chấp nhận được; cho phép kiem='khong' kèm lý do cho bước thuần tài liệu. | O32: Số lỗi biên dịch/test phát hiện ở bước cuối so với tại bước; số lượt sửa lại; pass@1 build sau mỗi bước | P32: M1-13 | Q32: Xong | R32: Agent (Claude Opus 5) | T32: 07/10/2026 | U32: DEV-336 | V32: 1657 → 1671 | W32: sổ cái thật: 26 lần đánh dấu 'xong' ngay sau một lần ghi mã, 19 lần (73 %) không có phép kiểm nào đạt ở giữa. Phép đo đầu ở mức dự án ra 0 — đúng nhưng đo sai câu hỏi | X32: KE_HOACH_CONG_KIEM — TẮT | Y32: mã lỗi E6012 (bảng TC của kế hoạch ghi nhầm E6010)
A33: M2-07 | B33: 2. Phân tích & thiết kế phần mềm | C33: Replanner khi bước thất bại | D33: T05 Lập kế hoạch & thực thi theo bước | E33: src/eide/ke_hoach.py::doi_chieu (dòng 285–301); hooks/standard.py::doi_chieu_ke_hoach | F33: doi_chieu chỉ báo 'ngoai_ke_hoach' và 'chua_lam', và docstring nói rõ không phía nào bị coi là lỗi. Không có trạng thái bước 'that_bai'; Buoc chỉ có cờ xong: bool. Không có đường sửa kế hoạch có kiểm soát giữa chừng ngoài plan.enter mới (cất kế hoạch cũ). | G33: Khi một bước vỡ (ví dụ thiết kế ISR không đạt thời gian), tác tử hoặc tự ứng biến ngoài kế hoạch, hoặc bỏ cả kế hoạch. Phần đã làm và lý do đổi hướng không được ghi thành tri thức. | H33: Plan-and-Execute (Replanner), Reflexion | I33: Thêm trạng thái bước {cho, xong, that_bai, bo} kèm 'ly_do'. Thêm công cụ 'plan.revise(tu_buoc, buoc_moi[], ly_do)': chỉ sửa phần CHƯA làm, giữ nguyên bước đã xong, qua lại cổng G-SCOPE khi số bước thay đổi >30% hoặc thêm công cụ có gate. Khi một bước that_bai thì tự ghi memory.note mục 'Bài học' (Reflexion) để lần lập kế hoạch sau đọc lại. | J33: Kế hoạch dài sống sót qua thất bại cục bộ; người dùng thấy rõ vì sao đổi hướng. | K33: P2 | L33: M | M33: =IF(K33="P0",IF(OR(L33="L",L33="XL"),"GĐ2","GĐ1"),IF(K33="P1",IF(L33="S","GĐ2","GĐ3"),"GĐ4")) | N33: Thêm một công cụ và một nhánh duyệt; cần trần số lần revise (ví dụ 3) để tránh lập kế hoạch vô tận. | O33: Tỉ lệ kế hoạch hoàn thành; số lần plan.enter lại do bỏ kế hoạch; số bước 'ngoai_ke_hoach' trung bình | P33: M1-13 | Q33: Chưa làm
A34: M2-08 | B34: 2. Phân tích & thiết kế phần mềm | C34: Phân tích mã tĩnh: nhận diện hàm (ISR, static, macro) | D34: T09 Phân tích mã tĩnh & CodeAct | E34: src/eide/phan_tich_ma.py::_HAM (dòng 33–41), _ky_hieu | F34: Regex C là '^[A-Za-z_][\w \*]*\s+\**(\w+)\s*\([^;]*\)\s*\{': bắt buộc có kiểu trả về trước tên hàm. Header được tách theo prototype. | G34: Regex này không bắt được ISR viết bằng macro AVR 'ISR(TIMER1_COMPA_vect) {', vì trước 'ISR' không có kiểu. Nó cũng không bắt được 'void __attribute__((interrupt)) X(void)' và handler Cortex-M khai báo trong bảng vector. Đây đúng là những hàm nguy hiểm nhất khi sửa firmware: tài liệu yêu cầu robot cấm số thực và phép chia trong ngắt 50 kHz. Hàm khai qua macro, con trỏ hàm và typedef cũng vô hình. | H34: CodeAct (phân tích bằng công cụ thật thay vì regex) | I34: Thêm mẫu riêng: r'^\s*ISR\s*\(\s*(\w+)' và r'__attribute__\s*\(\(\s*(interrupt|signal)'. Đọc bảng vector trong startup_*.s và *_IRQHandler để gắn nhãn 'isr'. Đổi TepMa.ky_hieu thành danh sách {ten, loai: ham|isr|static|macro, dong}. Về lâu dài dùng tree-sitter-c hoặc libclang (nếu có trên máy) để có AST, giữ regex làm dự phòng. | J34: Tài liệu phân tích liệt kê đủ ISR, nên code-analyst soi được đúng chỗ đắt nhất. | K34: P0 | L34: S | M34: =IF(K34="P0",IF(OR(L34="L",L34="XL"),"GĐ2","GĐ1"),IF(K34="P1",IF(L34="S","GĐ2","GĐ3"),"GĐ4")) | N34: tree-sitter là phụ thuộc mới; regex bổ sung thì gần như không rủi ro. | O34: Tỉ lệ ISR được nhận diện trên bộ dự án mẫu (robot AVR, STM32F469); số ký hiệu bỏ sót so với ctags | Q34: Xong | R34: Agent (Claude Opus 5) | T34: 07/10/2026 | U34: DEV-337 | V34: 1671 → 1679 | W34: 185 tệp .c thật: 1 758 → 1 786 hàm thấy được (+28 hàm trước đây VÔ HÌNH: 8 ngắt + 20 bị regex tham lam nuốt). 78 hàm nay gắn nhãn 'isr', 70 trong đó vốn đã có trong danh sách | X34: không có cờ — sửa lỗi thuần | Y34: —
A35: M2-09 | B35: 2. Phân tích & thiết kế phần mềm | C35: Phân tích tĩnh chiều sâu: call graph, độ phức tạp, ngăn xếp, ngữ cảnh ISR | D35: T09 Phân tích mã tĩnh & CodeAct | E35: src/eide/phan_tich_ma.py (cả tệp, 144 dòng); docstring 'Không phân tích ngữ nghĩa, không dựng đồ thị gọi hàm đúng nghĩa' | F35: code.analyze chỉ dò 'tên ký hiệu xuất hiện ở tệp nào' (quét văn bản, mức tệp), sau đó giao cho subagent code-analyst (≤14 lời gọi đọc) nhận định về chỗ gọi gián tiếp. Không có đồ thị gọi hàm mức hàm, không đo độ phức tạp vòng (cyclomatic), không ước lượng ngăn xếp, không biết hàm nào chạy trong ngữ cảnh ngắt, không phát hiện biến chung ISR/main thiếu volatile hoặc thiếu đoạn cấm ngắt. Build có -Wall -Wextra (toolchain.py:434, 732), nhưng không có -fstack-usage, -fanalyzer hay cppcheck. | G35: Với firmware, các lỗi đắt nhất là tràn ngăn xếp, race condition giữa ISR và main, và ISR quá dài. Phép quét văn bản không thấy được những lỗi này, còn code-analyst chỉ đọc bằng mắt với 14 lời gọi. | H35: CodeAct, Evaluator–Optimizer | I35: Tạo src/eide/build/phan_tich_tinh.py và công cụ 'code.static' (R1, core=False): (1) biên dịch thêm cờ -fstack-usage -fcallgraph-info=su (GCC ≥10), đọc .su/.ci để có call graph và ngăn xếp tối đa theo chuỗi gọi từ main và từ mỗi ISR, so với RAM trong hộ chiếu chip; (2) chạy cppcheck --enable=warning,performance,portability --addon=misra nếu có cài (đi qua tool.install); (3) đo độ phức tạp vòng bằng lizard (pip) hoặc đếm nhánh trên AST; (4) luật riêng cho ISR: trong tập hàm reachable từ ISR, cấm float/double, '/', '%', gọi hàm chặn (_delay_ms, printf), và báo biến toàn cục được ghi ở cả ISR lẫn main mà không có volatile. Kết quả ghi thành artefact 'findings' có path tệp:dòng. code.analyze đính kèm tóm tắt này vào phần DỮ KIỆN. | J35: Bắt được lớp lỗi firmware mà test trên máy chủ không bắt được; code-analyst có dữ kiện thật để nhận định. | K35: P1 | L35: L | M35: =IF(K35="P0",IF(OR(L35="L",L35="XL"),"GĐ2","GĐ1"),IF(K35="P1",IF(L35="S","GĐ2","GĐ3"),"GĐ4")) | N35: Phụ thuộc phiên bản GCC và cppcheck; addon MISRA cần tệp luật có bản quyền, nên chỉ chạy kiểm tra cú pháp. Cần trần thời gian chạy. | O35: Số phát hiện thật/giả trên bộ mã robot; ngăn xếp ước lượng so với đo thật (stack painting); tỉ lệ lỗi race được bắt trước khi nạp | P35: M4-13 | Q35: Chưa làm | S35: Kéo lên giai đoạn sớm hơn vì là tiền đề (xem §5 kế hoạch)
A36: M2-10 | B36: 2. Phân tích & thiết kế phần mềm | C36: Biến 'điều cấm' trong đặc tả thành luật máy kiểm | D36: T08 Yêu cầu & truy vết | E36: tools/sinh_yeu_cau_robot.py:353–390 ('1.4. Bốn điều cấm') | F36: Tài liệu yêu cầu robot (sinh bằng python-docx) nêu bốn điều cấm cụ thể: không dùng số thực hoặc phép chia trong ngắt 50 kHz; không dùng hàm chờ chặn trong vòng lặp chính; không điều khiển WS2812; không tắt động cơ bằng chân EN. Các điều cấm này chỉ tồn tại dưới dạng văn xuôi trong tệp .docx. | G36: Đây chính là các yêu cầu ràng buộc (constraint REQ) kiểm được bằng máy, nhưng không có artefact REQ nào và không có luật nào kiểm mã sinh ra có vi phạm hay không. Tác tử sinh mã có thể vi phạm mà không ai báo. | H36: Prompt Chaining (cổng bằng mã), Evaluator–Optimizer | I36: Thêm loại REQ 'CR' (ràng buộc) với trường 'luat_may': {pham_vi: 'isr:TIMER0_COMPA'|'main_loop'|'*', cam_ky_hieu: ['_delay_ms', 'float', '/'], cam_ghi_chan: ['PD5']}. Viết src/eide/rules/req_rules.py để kiểm trên kết quả code.static (call graph + AST). Gắn vào post_tool_use của fs.write/fs.edit với tệp .c: vi phạm thì trả note_vi kèm mã REQ. Bộ sinh tài liệu đọc REQ từ kho thay vì gõ cứng. | J36: Đặc tả và mã được giữ khớp nhau tự động; vi phạm bị bắt ngay khi ghi. | K36: P1 | L36: M | M36: =IF(K36="P0",IF(OR(L36="L",L36="XL"),"GĐ2","GĐ1"),IF(K36="P1",IF(L36="S","GĐ2","GĐ3"),"GĐ4")) | N36: Luật quá đơn giản (cấm '/') sẽ kêu thừa khi chia cho hằng lũy thừa 2. Cần danh sách ngoại lệ. | O36: Số vi phạm ràng buộc phát hiện lúc ghi so với lúc chạy trên bo; tỉ lệ kêu thừa | Q36: Chưa làm
A37: M2-11 | B37: 2. Phân tích & thiết kế phần mềm | C37: Hiệu năng và phạm vi quét của code.analyze | D37: T02 Ngữ cảnh, lược đồ công cụ & token | E37: src/eide/phan_tich_ma.py::quet (dòng 82–106), BO_QUA (dòng 45) | F37: Hàm quét ngược chạy goc.rglob('*') trên toàn cây, với mỗi tệp chạy re.search cho TỪNG ký hiệu (độ phức tạp O(tệp × ký hiệu)), không có trần số tệp hay thời gian. BO_QUA chỉ gồm .eide, .git, node_modules, __pycache__, vendor, build, .venv. Tệp .h cũng được tính là 'ai đang dùng'. | G37: Dự án STM32 có thư mục Drivers/ và Middlewares/ (HAL, FreeRTOS) với hàng nghìn tệp. Một lần quét có thể mất hàng chục giây, và danh sách 'chỗ phải xem lại' bị ngập bởi prototype trong header và tệp thư viện. Kết quả công cụ quá dài, đúng lỗi phổ biến mà thang đối chiếu nêu. | H37: (nguyên tắc chung: kết quả công cụ gọn) | I37: Thêm 'Drivers', 'Middlewares', 'CMSIS', 'third_party', 'lib' vào BO_QUA (đọc thêm từ cấu hình dự án). Gộp mọi ký hiệu thành một regex alternation \b(a|b|c)\b và quét mỗi tệp một lần. Thêm trần TRAN_TEP_QUET=2000 và trần thời gian 10 s, quá trần thì ghi rõ 'đã dừng ở N tệp'. Tách cột 'định nghĩa/khai báo (.h)' khỏi 'nơi gọi (.c)'. | J37: code.analyze nhanh hơn và có nhiều tín hiệu thật hơn nhiễu. | K37: P1 | L37: S | M37: =IF(K37="P0",IF(OR(L37="L",L37="XL"),"GĐ2","GĐ1"),IF(K37="P1",IF(L37="S","GĐ2","GĐ3"),"GĐ4")) | N37: Loại trừ thư mục vendor có thể bỏ sót trường hợp người dùng sửa HAL. Cho phép ghi đè bằng tham số. | O37: Thời gian code.analyze trên dự án F469; số mục 'chỗ phải xem lại' trên mỗi thay đổi | Q37: Chưa làm
A38: M2-12 | B38: 2. Phân tích & thiết kế phần mềm | C38: Sơ đồ kiến trúc phần mềm trên tab Thiết kế | D38: T09 Phân tích mã tĩnh & CodeAct | E38: src/eide/kien_truc.py::so_do_mo_dun, muc_kien_truc (dòng 67–225) | F38: Đây là điểm mạnh: sơ đồ chỉ vẽ khi có cạnh #include/import thật, khớp theo TÊN tệp, nhóm theo thư mục, giới hạn TRAN_TEP=40, và nói rõ lý do khi không vẽ được. Nguồn tệp là store.list('code'), tức chỉ những tệp có hiện vật code trong kho. | G38: Khớp theo tên tệp sẽ nối sai khi hai thư mục cùng có config.h. Chỉ có góc nhìn 'tệp include tệp', không có góc nhìn thành phần, giao diện hay luồng dữ liệu, không có sơ đồ trạng thái hay tuần tự cho firmware. Không đối chiếu được 'kiến trúc đã chốt trong ADR' với 'cấu trúc phụ thuộc thực tế' để phát hiện vi phạm phân tầng (ví dụ tầng app include thẳng thanh ghi). | H38: Evaluator–Optimizer (kiểm kiến trúc khớp thiết kế) | I38: (1) Ưu tiên khớp đường dẫn tương đối theo thư mục của tệp nguồn và các thư mục -I lấy từ cấu hình build, sau đó mới khớp theo tên. (2) Thêm trường 'tang' (phân tầng: app/service/driver/hal) vào hiện vật code_structure (xem đề xuất Prompt Chaining) và hàm kiem_phan_tang(): cạnh đi ngược tầng thì là phát hiện. (3) Cho tác tử ghi khai báo C4 nhẹ (container/component → tệp) để khối A5.6 vẽ thêm mức Component. | J38: Phát hiện được trôi kiến trúc (architecture drift) giữa ADR và mã thật. | K38: P2 | L38: M | M38: =IF(K38="P0",IF(OR(L38="L",L38="XL"),"GĐ2","GĐ1"),IF(K38="P1",IF(L38="S","GĐ2","GĐ3"),"GĐ4")) | N38: Độ phức tạp hiển thị tăng; giữ trần 40 nút. | O38: Số cạnh nối sai (so với include thật); số vi phạm phân tầng phát hiện | Q38: Chưa làm
A39: M2-13 | B39: 2. Phân tích & thiết kế phần mềm | C39: Rà soát thiết kế phần mềm (design-review cho kiến trúc, không chỉ mạch) | D39: T07 Phản biện thiết kế (Debate/ToT) | E39: src/eide/subagent.py:82–91 ('design-review'); src/eide/skills/design-review-checklist.md | F39: Subagent design-review và skill checklist chỉ dành cho mạch: net hở, chân, pull-up, ngân sách dòng, mức logic, địa chỉ I2C. Công cụ của nó gồm ckm.graph, board.check, eda.*. Không có subagent hay checklist nào để rà kiến trúc phần mềm, ADR hay cấu trúc mã. | G39: Thiết kế phần mềm được chốt qua G-DESIGN mà không có góc nhìn phản biện độc lập nào. Người duyệt chỉ thấy lập luận của chính tác tử đề xuất. | H39: Debate (phản biện + trọng tài), Evaluator–Optimizer | I39: Thêm subagent 'sw-design-review' (chỉ đọc: store.get/list, fs.read, code.static, build.map) và skill 'sw-design-review-checklist.md': phân tầng và hướng phụ thuộc; ngân sách thời gian từng tầng (ISR / vòng điều khiển / nền); tài nguyên chia sẻ và chiến lược khoá; trạng thái lỗi và đường phục hồi; ngân sách Flash/RAM; khả năng kiểm thử (phần logic tách khỏi thanh ghi); REQ nào không phương án nào đáp ứng. Gọi nó tự động trước option_choose (pre_tool_use) khi việc là 'tạo mới', và đưa phát hiện vào thẻ G-DESIGN để người duyệt thấy cả hai phía. | J39: Quyết định kiến trúc được phản biện trước khi khoá, nên giảm việc đổi kiến trúc giữa chừng. | K39: P1 | L39: S | M39: =IF(K39="P0",IF(OR(L39="L",L39="XL"),"GĐ2","GĐ1"),IF(K39="P1",IF(L39="S","GĐ2","GĐ3"),"GĐ4")) | N39: Thêm khoảng 8–10 lời gọi cho mỗi lần chốt; có thể kêu thừa nếu checklist quá chung. | O39: Số phát hiện có giá trị trong mỗi lần rà; tỉ lệ ADR bị đảo sau khi đã chốt | P39: M1-16 | Q39: Chưa làm
A40: M2-14 | B40: 2. Phân tích & thiết kế phần mềm | C40: Subagent firmware: tiêu chí 'xong' chỉ là biên dịch được | D40: T03 Tác tử con & điều phối song song | E40: src/eide/subagent.py:92–102 ('firmware') | F40: System prompt ghi: 'Biên dịch xong mới được nói là xong; ket_luan: dat chỉ khi build.compile trả về có tệp ảnh'. Danh sách công cụ không có test.run, test.sensitivity, sim.run hay code.analyze. | G40: Định nghĩa xong là 'biên dịch được' nằm ngay trong subagent sinh mã. Worker không tự chạy test và không đo độ nhạy test được, nên lỗi logic chỉ lộ ra khi verifier chạy hoặc khi chạy trên bo. | H40: Supervisor–Workers, Evaluator–Optimizer (vòng sinh–chấm–sửa có trần) | I40: Thêm test.run, test.sensitivity và code.analyze vào cong_cu của 'firmware'. Sửa prompt: 'dat' chỉ khi (a) build.compile có ảnh, (b) test.run không có ca hỏng nếu có test/, (c) không còn cảnh báo -Wall mới so với trước. Vòng tự sửa tối đa 3 lần (đếm bằng mã trong subagent.chay), quá trần thì trả 'chua_dat' kèm lỗi cuối. | J40: Worker trả về mã đã qua kiểm thử đơn vị, nên giảm số lượt verifier bác. | K40: P1 | L40: S | M40: =IF(K40="P0",IF(OR(L40="L",L40="XL"),"GĐ2","GĐ1"),IF(K40="P1",IF(L40="S","GĐ2","GĐ3"),"GĐ4")) | N40: Subagent tốn thêm 2–4 lời gọi; cần nâng toi_da_goi tương ứng (xem VIEC-CHO-LAM mục 6 về hạn quá chặt). | O40: Tỉ lệ verifier trả khong_dat sau firmware; số ca test hỏng phát hiện sau khi worker báo xong | P40: M1-03, M4-02 | Q40: Chưa làm
A41: M2-15 | B41: 2. Phân tích & thiết kế phần mềm | C41: Tài liệu dự án người dùng đồng bộ với mã (doc-code sync) | D41: T08 Yêu cầu & truy vết | E41: tests/test_tai_lieu_khop_ma.py; tools/kiem_tai_lieu.py; tools/sinh_yeu_cau_robot.py | F41: Đây là điểm mạnh cho chính EIDE: kiem_tai_lieu.py đối chiếu tên công cụ, đường dẫn, mã lỗi và con số giữa docs/md và mã EIDE, và chạy trong hồi quy. Nhưng tài liệu của DỰ ÁN NGƯỜI DÙNG, ví dụ YEU-CAU-PHAT-TRIEN-PHAN-MEM-ROBOT-TU-CAN-BANG.docx, được sinh bằng một script 1206 dòng gõ cứng nội dung ('Mọi con số lấy thẳng từ mã' nhưng thực tế là chép tay: TWBR=12, bảng thanh ghi, 'mười tệp'…). Không có công cụ nào cho tác tử kiểm tài liệu .md/.docx của dự án có còn khớp mã hay Fact không. | G41: Sửa mã firmware (đổi chân, đổi hằng số PID) thì tài liệu yêu cầu và thiết kế lệch đi trong im lặng. STALE chỉ áp cho hiện vật trong kho, không áp cho tệp tài liệu tác tử tự viết. | H41: Evaluator–Optimizer, Blackboard | I41: Tổng quát hoá kiem_tai_lieu.py thành công cụ tác tử 'doc.check_sync(nguon.md)': trích từ tài liệu các cặp (ký hiệu/thanh ghi/hằng số = giá trị) và đường dẫn tệp, rồi đối chiếu với mã (grep #define, phép gán thanh ghi) và Fact trong kho, báo từng chỗ lệch kèm tệp:dòng. Khi fs.write một .md có trích tệp mã, ghi deps.upstream trỏ tới các tệp code đó, để sửa mã thì tài liệu bị STALE (cần đề xuất truy vết P0). Bộ sinh docx nên đọc REQ/Fact/criteria từ kho rồi render qua doc.render thay vì gõ cứng. | J41: Tài liệu luận văn/đề án luôn khớp mã đang chạy, đúng yêu cầu 'mọi thứ phải có sở cứ'. | K41: P1 | L41: M | M41: =IF(K41="P0",IF(OR(L41="L",L41="XL"),"GĐ2","GĐ1"),IF(K41="P1",IF(L41="S","GĐ2","GĐ3"),"GĐ4")) | N41: Trích cặp (tên = giá trị) từ văn xuôi tiếng Việt dễ sót; nên bắt đầu với bảng Markdown và khối code. | O41: Số chỗ lệch tài liệu–mã phát hiện; thời gian từ khi sửa mã tới khi tài liệu được cập nhật | Q41: Chưa làm
A42: M2-16 | B42: 2. Phân tích & thiết kế phần mềm | C42: Kiểu sơ đồ thiết kế: stateDiagram, classDiagram | D42: T09 Phân tích mã tĩnh & CodeAct | E42: src/eide/so_do.py::doc (dòng 102–108); skills/trinh-bay-bang-hinh.md ('Hai kiểu vẽ được, và chỉ hai') | F42: Bộ vẽ PNG chỉ đọc sequenceDiagram và graph/flowchart; kiểu khác trả None và in mã kèm câu nói rõ là chưa vẽ được. Skill dặn tác tử diễn đạt lại bằng hai kiểu trên. | G42: Thiết kế firmware dựa nặng vào máy trạng thái (tài liệu robot có '2.3. Tám trạng thái', '2.4. Khi nào đổi trạng thái'). Diễn đạt bằng flowchart làm mất ngữ nghĩa sự kiện/điều kiện chuyển và không kiểm được tính đầy đủ (trạng thái không có lối ra, sự kiện không xử lý). | H42: (công cụ trình bày; hỗ trợ Evaluator kiểm thiết kế) | I42: Thêm _trang_thai(nguon) cho 'stateDiagram-v2' (s1 --> s2 : sự kiện [điều kiện]), tái dùng bộ xếp chỗ xep_cho của _luong. Thêm hàm kiem_may_trang_thai(): báo trạng thái không tới được từ [*], trạng thái cụt, và cặp (trạng thái, sự kiện) không có chuyển tiếp nếu người dùng khai danh sách sự kiện. Đồng bộ phần đọc trong Views/SoDo.swift theo cùng bộ kiểm dùng chung. | J42: Thiết kế hành vi firmware được vẽ đúng loại và kiểm được bằng máy. | K42: P3 | L42: M | M42: =IF(K42="P0",IF(OR(L42="L",L42="XL"),"GĐ2","GĐ1"),IF(K42="P1",IF(L42="S","GĐ2","GĐ3"),"GĐ4")) | N42: Phải sửa hai bộ đọc (Python + Swift), như docstring đã nêu. | O42: Số sơ đồ trạng thái vẽ thành công; số lỗi máy trạng thái phát hiện | Q42: Chưa làm
A43: M2-17 | B43: 2. Phân tích & thiết kế phần mềm | C43: CodeAct: phân tích dữ liệu và mã bằng code chạy trong sandbox | D43: T09 Phân tích mã tĩnh & CodeAct | E43: Danh sách công cụ đăng ký (tools/*.py): không có công cụ chạy Python/shell tuỳ ý; tool.propose là đường duy nhất để tác tử tự viết mã công cụ | F43: Phân tích log mô phỏng, CSV đo đạc, map file hay call graph đều phải đi qua công cụ dựng sẵn (build.map, sim.run, test.run) hoặc qua tool.propose (viết công cụ mới, có bộ kiểm và người duyệt). Plan mode đo được 54% lời gọi là fs.read/fs.grep/fs.glob. | G43: Những câu hỏi phân tích dùng một lần ('ISR nào gọi hàm có chia', 'vẽ phân bố sai số góc từ log 10.000 dòng') không đáng để viết một công cụ mới, nhưng làm bằng chuỗi fs.grep tuần tự thì tốn hàng chục lời gọi và ngân sách 40 lời gọi/lượt. | H43: CodeAct | I43: Thêm công cụ 'analysis.py' (R1, core=False, CHỈ ĐỌC): chạy một đoạn Python ≤200 dòng trong tiến trình con với python -I, cwd tạm, chỉ mount dự án ở chế độ đọc (hoặc sao chép có giới hạn), không mạng, timeout 30 s, giới hạn bộ nhớ, stdout cắt 4 KB kèm cờ da_cat. Cho sẵn các helper: doc_ma(path), ky_hieu(), call_graph() (từ code.static), doc_csv(). Kết quả ghi artefact 'analysis' (KHONG_STALE). Cấm ghi tệp; muốn ghi thì vẫn phải đi qua fs.write để giữ changeset và hoàn tác. | J43: Gộp 10–20 lời gọi đọc thành 1; phân tích dữ liệu đo và log chính xác hơn so với mô hình tự 'đọc' bằng mắt. | K43: P2 | L43: M | M43: =IF(K43="P0",IF(OR(L43="L",L43="XL"),"GĐ2","GĐ1"),IF(K43="P1",IF(L43="S","GĐ2","GĐ3"),"GĐ4")) | N43: Bảo mật sandbox trên macOS (không có seccomp); phải giữ nguyên tắc chỉ đọc và chặn mạng; mã sinh ra có thể sai. Kết quả phải được trình bày là DỮ KIỆN do mã chạy, tách khỏi nhận định. | O43: Số lời gọi trên mỗi câu hỏi phân tích; tỉ lệ lượt chạm trần 40 lời gọi; độ chính xác câu trả lời phân tích log | P43: M1-21 | Q43: Chưa làm
A44: M2-18 | B44: 2. Phân tích & thiết kế phần mềm | C44: Bộ đánh giá (eval) cho mảng phân tích–thiết kế | D44: T15 Đo lường & bộ đánh giá (eval) | E44: tools/bo_usecase.py (dòng 1–25: 'Phép chấm này đo… bề mặt') | F44: Bộ 76 ca chấm bằng dau_hieu (cụm từ phải có), cam (cụm từ không được có) và cong_cu (công cụ phải được gọi). Docstring tự thừa nhận: 'Ô xanh ở đây nghĩa là có dấu hiệu… không phải đã làm đúng'. | G44: Không có eval định lượng cho chất lượng đặc tả và thiết kế: REQ có tiêu chí đo được không, phương án có phủ REQ không, ADR có lý do loại phương án khác không, kế hoạch có cổng kiểm không. Vì thế các cải tiến ở trên không đo được trước và sau. | H44: Evaluator–Optimizer (eval trước khi leo thang) | I44: Thêm tools/cham_thiet_ke.py chấm trên KHO hiện vật sau mỗi phiên usecase, không chấm trên lời đáp: % REQ có criteria đo được; % REQ được ≥1 option xét; số option mỗi ADR; % ADR có he_qua; % bước sinh mã có kiem; độ phủ ma trận truy vết; số STALE mỗi lần sửa REQ. Kèm một rubric LLM-as-judge (mô hình khác hoặc nhiệt độ 0) cho TC001–TC007, có bộ mẫu đã gán nhãn bởi người để hiệu chỉnh. | J44: Có thước đo khách quan để chứng minh cải tiến trong đề án và tránh báo xanh giả. | K44: P1 | L44: M | M44: =IF(K44="P0",IF(OR(L44="L",L44="XL"),"GĐ2","GĐ1"),IF(K44="P1",IF(L44="S","GĐ2","GĐ3"),"GĐ4")) | N44: LLM-as-judge có thiên lệch; cần đối chiếu với nhãn người trên ít nhất 20 ca. | O44: Các chỉ số kho nêu trên theo từng phiên bản; độ tương quan giữa điểm judge và điểm người | P44: M5-21 | Q44: Chưa làm
A45: M2-19 | B45: 2. Phân tích & thiết kế phần mềm | C45: Chống giả mạo xuất xứ quyết định (điểm mạnh cần giữ, có thể mở rộng) | D45: T08 Yêu cầu & truy vết | E45: src/eide/tools/design.py::_kiem_nguoi_that_su_chon (E5006–E5009); src/eide/surfaces.py::_ai_quyet | F45: Đây là điểm mạnh. Khi quyet_boi='nguoi', hàm kiểm ba điều: câu trích có trong sổ cái human_act; câu có dấu hiệu chọn (chọn, dùng, lấy, đồng ý…); câu nhắc tới mã hoặc tên phương án (bỏ qua từ chung). Tab A2.4 phân biệt 'Anh quyết' / 'qua G-DESIGN' / 'Tác tử tự quyết'. store.req_create thì chỉ BẮT BUỘC có source_quote, không kiểm câu trích có trong sổ cái. | G45: REQ là gốc của mọi chuỗi truy vết nhưng có mức bảo vệ xuất xứ thấp hơn ADR: tác tử có thể đặt một câu bịa hoặc diễn giải lại vào source_quote. Lỗi xuất xứ 'nguồn có thật nhưng không nói điều được gán' (ca TC004) cũng xảy ra được với REQ. | H45: Human-in-the-loop, Agentic RAG (kiểm bám nguồn) | I45: Tái dùng phần kiểm số 1 của _kiem_nguoi_that_su_chon (khớp câu trích với human_act trong sổ cái sau khi bỏ dấu) cho store.req_create và store.req_update: không khớp thì trả lỗi kiểu E5007 với gợi ý ask_user. Thêm kiểm 'bám nguồn' nhẹ: các danh từ hoặc con số trong text phải xuất hiện trong source_quote hoặc trong Fact; nếu không thì gắn confidence DONG và hiện trên A2.1. | J45: Gốc truy vết đáng tin; giảm REQ do tác tử tự 'sáng tác'. | K45: P2 | L45: S | M45: =IF(K45="P0",IF(OR(L45="L",L45="XL"),"GĐ2","GĐ1"),IF(K45="P1",IF(L45="S","GĐ2","GĐ3"),"GĐ4")) | N45: Người dùng nói bằng giọng nói hoặc qua tệp đính kèm thì câu trích có thể không khớp nguyên văn; cần cho phép trích từ tài liệu đã nạp (doc ref). | O45: Tỉ lệ REQ có source_quote khớp sổ cái; số REQ bị từ chối vì trích không khớp | Q45: Chưa làm
A46: M3-01 | B46: 3. Mạch, ERC, HDL/FPGA | C46: ERC theo cây — bộ luật | D46: T10 ERC & thiết kế mạch | E46: src/eide/knowledge/erc.py:136 (erc) + knowledge/compare.py:211 (qua_ap) | F46: erc() chỉ chạy đúng 4 luật bằng mã: ngan_sach_dong, muc_logic_tren_net, trung_dia_chi_bus, pull_up_bus. KHOA (erc.py:40) có khai khoá 'v_max' (vdd.max/vin.max) nhưng không luật nào đọc nó. compare.py đã có hàm qua_ap(), nhưng hàm này chỉ chạy khi tác tử (agent) tự gọi fact.compare cho từng cặp số, không nằm trong board.check. | G46: Lỗi đắt nhất trong mạch nhúng là cấp 5 V vào chân chỉ chịu 3,3 V (hỏng vĩnh viễn), và ERC tự động không bắt được lỗi này. Tác tử phải tự nhớ ra việc gọi fact.compare. board.check báo 'đạt' cho một mạch có thể đốt chip. | H46: Prompt Chaining (cổng kiểm bằng code), Evaluator–Optimizer | I46: Thêm luật thứ 5 qua_ap_tren_net(cay, tf, phang) vào erc(): với mỗi net điện, lấy điện áp cao nhất mà net có thể mang (Fact voh hoặc điện áp rail của net nguồn, gắn qua canonical 'v_rail' của net loại power), rồi so với v_max hoặc vddio.max của từng chân nhận, dùng lại CP.qua_ap. Thêm khoá 'vddio.max' và 'v_tolerant' (chân chịu 5 V, kiểu FT của STM32) vào KHOA. Thiếu một vế thì trả 'chua_du_du_kien'. | J46: Bắt lớp lỗi phá huỷ phần cứng ngay ở mức sơ đồ, trước khi hàn hay nạp. | K46: P0 | L46: S | M46: =IF(K46="P0",IF(OR(L46="L",L46="XL"),"GĐ2","GĐ1"),IF(K46="P1",IF(L46="S","GĐ2","GĐ3"),"GĐ4")) | N46: Báo nhầm khi chân có diode kẹp hoặc chịu được 5 V mà chưa có Fact. Cần khoá v_tolerant để người xác nhận ngoại lệ. | O46: Tỉ lệ bắt lỗi trên bộ ca cài sẵn lỗi 5V→3V3 (mục tiêu 100%); số lỗi lọt xuống mạch thật | Q46: Xong | R46: Agent (Claude Opus 5) | T46: 07/10/2026 | U46: DEV-338 | V46: 1679 → 1686 | W46: 0 phát hiện trên 5 mô hình mạch thật — và lý do đáng hơn con số: 3 kho CÓ Fact v_max thì KHÔNG có mô hình mạch, 5 kho có mạch thì không có Fact ấy; thêm nữa Fact dùng chủ thể chip:X mà ERC không tra tiền tố đó | X46: không có cờ — sửa lỗi thuần | Y46: đã gỡ ở M3-07 (nối chủ thể chip:X)
A47: M3-02 | B47: 3. Mạch, ERC, HDL/FPGA | C47: ERC — mức logic | D47: T10 ERC & thiết kế mạch | E47: src/eide/knowledge/erc.py:343 (muc_logic_tren_net), compare.py:192 (muc_logic), knowledge/docs.py:344 (_MAU_THONG_SO) | F47: Luật mức logic chỉ so VOH(phát) ≥ VIH(thu). docs.py đã trích được vil.max và vol.max, nhưng KHOA của ERC không có hai khoá này. Giá trị lấy bằng regex số kèm đơn vị trên cùng một dòng. | G47: Thiếu nửa còn lại của phép kiểm: VOL ≤ VIL, tức mức thấp có bị đọc thành mức cao không, và lề nhiễu (noise margin). Datasheet CMOS thường ghi VIH = 0,7×VDD, tức một tỉ lệ chứ không phải một số volt. Regex hoặc bỏ qua giá trị đó, hoặc đọc '0,7' thành 0,7 V, cho kết luận 'đạt' sai. | H47: Prompt Chaining (cổng mã), Agentic RAG (kiểm bám nguồn) | I47: Thêm 'vol' và 'vil' vào KHOA, và cho muc_logic_tren_net kiểm cả hai chiều cùng lề nhiễu NM_H = VOH − VIH, NM_L = VIL − VOL (cảnh báo khi lề < 0,2 V). Trong docs.py, nhận dạng giá trị dạng tỉ lệ (r'0[.,]\d+\s*[x×*]\s*V(DD|CC)') thành Fact {value_ratio, ref: vdd}. Sau đó ERC nhân với điện áp rail thực của chân đó trên cây. | J47: Kiểm đủ tương thích mức logic khi nối hai miền điện áp, ví dụ ESP32 3V3 với module 5V, và bớt 'đạt' giả do đọc sai VIH dạng tỉ lệ. | K47: P1 | L47: S | M47: =IF(K47="P0",IF(OR(L47="L",L47="XL"),"GĐ2","GĐ1"),IF(K47="P1",IF(L47="S","GĐ2","GĐ3"),"GĐ4")) | N47: Fact dạng tỉ lệ cần biết rail của chân. Thiếu rail thì phải trả 'chưa đủ dữ kiện'. | O47: Số cặp phát–thu được kết luận (không còn 'chưa đủ dữ kiện'); số Fact VIH dạng tỉ lệ đọc đúng trên 10 datasheet mẫu | P47: M5-06 | Q47: Chưa làm
A48: M3-03 | B48: 3. Mạch, ERC, HDL/FPGA | C48: ERC theo kiểu chân (ma trận điện) | D48: T10 ERC & thiết kế mạch | E48: src/eide/sch/kyhieu.py:27 (KIEU_CHAN), tools/sch.py:11 (không có KiCad), knowledge/ckm.py:563 (net_mot_chan) | F48: Kiểu chân (input/output/bidirectional/power_in/power_out/passive) được suy từ hướng Port và ghi vào .kicad_sym. Mã ghi rõ phần kiểm theo kiểu chân là việc của 'ERC KiCad', nhưng máy không cài KiCad và tài liệu SCH-44 cũng không cho cài. Không có ma trận kiểm kiểu chân nội bộ nào. 'Net một chân' chỉ là một dòng thông tin trong ckm.build, không phải phát hiện ERC. | G48: Các lỗi kinh điển không được bắt: hai output nối chung một net (chập), power_in không có power_out nào cấp, input treo không ai lái, net một chân. SCH-44 đặt mục tiêu 'ERC nội bộ + KiCad ERC 0 lỗi', nhưng nửa KiCad không bao giờ chạy, nên con số 0 lỗi là không đo. | H48: Evaluator–Optimizer, Prompt Chaining | I48: Viết knowledge/erc_kieu_chan.py với MA_TRAN_ERC 7×7 theo đúng bảng mặc định của KiCad (lỗi/cảnh báo/đạt). Duyệt flatten(cay) cùng kiểu chân từ symbol_map:mach (ưu tiên kiểu chân người đã xác nhận qua sch.symbol_confirm). Sinh PhatHien có path cho: output–output, power_out–power_out, power_in không có nguồn cấp (chấp nhận cờ PWR_FLAG khai trong canonical), input không có bên lái, net một chân. Gọi trong erc(). | J48: Thay chỗ ERC KiCad còn thiếu mà không phải cài KiCad; bắt chập đầu ra và chân nguồn không được cấp. | K48: P0 | L48: M | M48: =IF(K48="P0",IF(OR(L48="L",L48="XL"),"GĐ2","GĐ1"),IF(K48="P1",IF(L48="S","GĐ2","GĐ3"),"GĐ4")) | N48: Kiểu chân suy sai, nhất là passive, sẽ sinh báo nhầm. Nên hạ mức xuống cảnh báo khi ký hiệu chưa được người xác nhận. | O48: Tỉ lệ bắt lỗi trên bộ ca cài sẵn lỗi kiểu chân; tỉ lệ báo nhầm trên 3 mạch mẫu của SCH-44 §D | Q48: Xong | R48: Agent (Claude Opus 5) | T48: 07/10/2026 | U48: DEV-339 | V48: 1686 → 1695 | W48: 8 phát hiện trên 5 mạch thật (6 nguon_khong_cap + 2 net_mot_chan), trong đó net clock I2C nối đúng một chân. SÁU trong tám là 'mô hình chưa khai' chứ không phải 'mạch sai'. robot-canbang: 107 Port lá, KHÔNG Port nào là power_out | X48: không có cờ — sửa lỗi thuần | Y48: hai phép phá chỉ ra THIẾT KẾ sai của tôi (miễn net đất quá rộng; nhánh iout_max chưa ca nào chạm) — đã sửa cả hai
A49: M3-04 | B49: 3. Mạch, ERC, HDL/FPGA | C49: ERC — toàn vẹn net nguồn / ngắn mạch | D49: T10 ERC & thiết kế mạch | E49: src/eide/knowledge/erc.py:_hai_ve_dong, _la_dat, _nhom_nguon | F49: _hai_ve_dong chỉ giữ MỘT khối cấp, cái có Fact iout_max tin nhất, và lặng lẽ bỏ qua các khối cấp khác trên cùng net. _la_dat bỏ hẳn net đất khỏi phép kiểm. Không có kiểm tra rail nào bị nối thẳng vào GND. | G49: Hai LDO, hoặc USB 5V và pin, cùng xuất lên một net là lỗi tranh chấp nguồn hay dòng ngược, nhưng ERC lại chọn một cái rồi tính ngân sách như bình thường. Một net vừa mang tên +3V3 vừa có chân GND (do gán nhầm) bị _la_dat coi là đất nên bị bỏ qua, tức là ngắn mạch nguồn không bị phát hiện. | H49: Evaluator–Optimizer (cổng mã) | I49: Trong _hai_ve_dong, gom TẤT CẢ ứng viên cấp. Có từ 2 trở lên mà không khai diode OR hay ideal-diode (canonical 'or_ing') thì sinh 'tranh_chap_nguon' mức blocker. Thêm luật 'chap_nguon': một net điện mà các net phạm vi của nó vừa có loai power/rail vừa có loai gnd, hoặc chứa chân tên VCC/VDD lẫn GND/VSS của cùng một linh kiện, thì báo blocker kèm path cả hai đầu. | J49: Bắt ngắn mạch nguồn và tranh chấp nguồn, hai lỗi làm cháy bo ngay lần cấp điện đầu tiên. | K49: P0 | L49: S | M49: =IF(K49="P0",IF(OR(L49="L",L49="XL"),"GĐ2","GĐ1"),IF(K49="P1",IF(L49="S","GĐ2","GĐ3"),"GĐ4")) | N49: Thấp; cần một ngoại lệ có khai báo cho mạch power-path. | O49: Ca kiểm ngắn mạch/tranh chấp được bắt; báo nhầm trên mạch mẫu = 0 | Q49: Xong | R49: Agent (Claude Opus 5) | T49: 07/10/2026 | U49: DEV-340 | V49: 1695 → 1703 | W49: 0 phát hiện trên 5 mạch thật — và đây là con số ĐÚNG (hai lỗi này catastrophic, không bo nào sống tới lúc lưu kho). Đã CẤY hai bộ cấp vào bản sao kho robot-canbang để chứng minh luật sống: nổ đúng 1 blocker trên net +5V thật | X49: không có cờ — sửa lỗi thuần | Y49: —
A50: M3-05 | B50: 3. Mạch, ERC, HDL/FPGA | C50: ERC — luật miền thiếu (decoupling, boot/reset, LED, nhiệt) | D50: T10 ERC & thiết kế mạch | E50: src/eide/knowledge/erc.py:136; skills/design-review-checklist.md | F50: Không có luật nào về tụ decoupling trên chân power_in, về chân BOOT0/NRST/EN/strapping (chỉ có ở danh sách kiểm tra khi dò bo, build/mach_that.py:103), về điện trở hạn dòng LED, hay về công suất toả nhiệt của LDO. Skill design-review-checklist chỉ lặp lại đúng 6 mục mà ERC đã kiểm. | G50: Đây đúng là những lỗi bo mạch hay gặp trong thực tế: thiếu tụ 100 nF gây treo hoặc reset ngẫu nhiên, BOOT0 thả nổi làm chip vào bootloader, LED nối thẳng vào GPIO, LDO tuyến tính 12→3V3 cháy vì nhiệt. Tác tử không có cổng mã nào cho chúng, nên chỉ còn trông vào việc mô hình tự nhớ. | H50: Evaluator–Optimizer, Prompt Chaining | I50: Thêm bộ luật mềm, mức major hoặc minor, mỗi luật một hàm: (a) decoupling: mỗi linh kiện có chân power_in phải có ít nhất một tụ (ref C*) nối giữa net đó và GND trong cùng khối; (b) boot_reset: chân có Fact role∈{boot,reset,strap} (thêm khoá vào docs.py) phải có điện trở kéo về mức xác định hoặc nút bấm; (c) led_han_dong: LED (ref D*/LED*) phải có R nối tiếp, tính I=(V−Vf)/R bằng mã và so với Fact if.max của LED và ioh.max của GPIO; (d) nhiet_ldo: P=(Vin−Vout)·ΣI, so với Fact pd.max hoặc θJA. Đồng bộ skill checklist với danh sách luật thật. | J50: Phủ thêm nhóm lỗi hay gặp nhất của bo tự làm; kết quả rà soát có căn cứ là mã chứ không phải trí nhớ của mô hình. | K50: P1 | L50: M | M50: =IF(K50="P0",IF(OR(L50="L",L50="XL"),"GĐ2","GĐ1"),IF(K50="P1",IF(L50="S","GĐ2","GĐ3"),"GĐ4")) | N50: Dễ báo nhầm, ví dụ tụ dùng chung cho cụm chân. Nên để mức cảnh báo và có cơ chế người chấp nhận (stale.accept tương tự). | O50: Số lỗi miền bắt được trên bộ 10 mạch lỗi cài sẵn; tỉ lệ người chấp nhận phát hiện, đo độ nhiễu | Q50: Chưa làm
A51: M3-06 | B51: 3. Mạch, ERC, HDL/FPGA | C51: ERC — pull-up I2C | D51: T10 ERC & thiết kế mạch | E51: src/eide/knowledge/erc.py:454 (pull_up_bus), compare.py:264 (pull_up) | F51: pull_up_bus đếm mọi linh kiện có ref bắt đầu bằng 'R' nối vào net SDA/SCL rồi coi đó là pull-up. compare.pull_up chỉ cảnh báo khi R > 2×khuyến nghị. | G51: Điện trở nối tiếp, ví dụ 33 Ω chống dội, bị tính thành pull-up, nên vừa che việc thiếu pull-up thật vừa sinh cảnh báo 'hai cụm' sai. Luật không kiểm đầu kia của điện trở có lên rail nguồn không. Không kiểm R quá nhỏ: tại 3,3 V, R < Vdd/3 mA ≈ 1,1 kΩ thì vượt IOL 3 mA của I2C. Cũng không tính rise time theo điện dung bus. | H51: Evaluator–Optimizer (cổng mã) | I51: Chỉ coi là pull-up khi chân còn lại của R nằm trên một net loai power. Dùng chân này để biết rail và Vdd. Tính Rmin=(Vdd−VOL)/IOL và Rmax=tr/(0,8473·Cb) bằng mã (Cb lấy từ Fact hoặc mặc định có ghi nguồn 'giả định 100 pF' → tầng ĐỒNG). Kiểm cả SDA lẫn SCL theo cặp. Pull-up song song thì tính R tương đương thay vì chỉ đếm. | J51: Bớt báo nhầm, và bắt thêm lỗi pull-up quá mạnh hoặc quá yếu, loại lỗi 'chạy lúc được lúc không'. | K51: P1 | L51: S | M51: =IF(K51="P0",IF(OR(L51="L",L51="XL"),"GĐ2","GĐ1"),IF(K51="P1",IF(L51="S","GĐ2","GĐ3"),"GĐ4")) | N51: Giả định Cb phải được nói ra (N4) và đánh tầng ĐỒNG. | O51: Báo nhầm pull-up trên mạch có R nối tiếp = 0; ca R quá nhỏ được bắt | Q51: Chưa làm
A52: M3-07 | B52: 3. Mạch, ERC, HDL/FPGA | C52: Nối Fact trích từ datasheet ↔ khoá ERC | D52: T10 ERC & thiết kế mạch | E52: src/eide/knowledge/erc.py:40 (KHOA) vs knowledge/docs.py:357 ('icc.typ'), tools/sch.py:216 | F52: Trích theo dòng sinh khoá 'icc.typ' cho ICC, nhưng bí danh i_max trong ERC chỉ nhận icc.max/idd.max/i.max. Không có mẫu trích nào cho iout_max (dòng ra LDO) hay addr (địa chỉ I2C), nên hai vế này chỉ có được khi người tự khai. sch.netlist chỉ trả về các phát hiện 'khong_dat' và ẩn hết 'chua_du_du_kien'. | G52: Trên dự án thật, ngan_sach_dong và trung_dia_chi gần như luôn ra 'chưa đủ dữ kiện', còn sch.netlist báo 'ERC 0 lỗi chặn'. Đó là một ô xanh giả, vì phần lớn luật chưa hề được đánh giá. Tác tử không biết mình cần nạp Fact gì. | H52: Agentic RAG (định tuyến/viết lại truy vấn), Prompt Chaining | I52: (1) Thêm mẫu cho iout/output current/IOUT(max), I2C address/slave address (đọc dạng nhị phân 1001000 và hex), cùng ánh xạ cột Max của bảng ICC thành icc.max. (2) Cho i_max nhận thêm icc.typ nhưng đánh dấu 'dùng typ thay max' trong bằng chứng. (3) Mọi kết quả ERC (board.check, sch.netlist) trả thêm 'do_phu' = {luat: dat/khong_dat/chua_du} cùng danh sách Fact còn thiếu theo dạng lệnh gợi ý: doc.load hoặc fact.extract cho chip X, khoá Y. | J52: ERC thực sự đánh giá được thay vì luôn im lặng; tác tử có đường đi cụ thể để lấp dữ kiện còn thiếu. | K52: P0 | L52: S | M52: =IF(K52="P0",IF(OR(L52="L",L52="XL"),"GĐ2","GĐ1"),IF(K52="P1",IF(L52="S","GĐ2","GĐ3"),"GĐ4")) | N52: Thêm mẫu regex có thể bắt nhầm, cần PHAM_VI_HOP_LY cho khoá mới. | O52: Tỉ lệ phát hiện 'chua_du_du_kien' / tổng trên 3 mạch mẫu (mục tiêu < 30%) | P52: M5-05 | Q52: Xong | R52: Agent (Claude Opus 5) | T52: 07/10/2026 | U52: DEV-341 | V52: 1703 → 1713 | W52: Fact tới được ERC: 5 → 17 (+12). Ba kho có Fact datasheet thì TOÀN BỘ mang chủ thể chip:, tức trước đó không một Fact nào tới được ERC. Độ phủ 5 mạch thật nay đọc được | X52: không có cờ — sửa lỗi thuần | Y52: hai tập dữ liệu vẫn chưa giao nhau, nên luật quá áp M3-01 vẫn chưa nổ trên dữ liệu thật — nhưng đường dẫn đã thông
A53: M3-08 | B53: 3. Mạch, ERC, HDL/FPGA | C53: Tính toán kỹ thuật bằng mã (CodeAct) | D53: T09 Phân tích mã tĩnh & CodeAct | E53: src/eide/knowledge/khoi_thu_vien.py:56–81 (CONG_THUC) | F53: Có một danh sách công thức ĐÓNG, rất tốt: không eval, mỗi giá trị trả về GiaTriDanXuat kèm công thức và nguồn tham số. Nhưng danh sách chỉ có 3 công thức (chia_ap_r2, tu_loc, pull_up) và chỉ chạy được trong khoi.place. Trong 100+ công cụ không có công cụ tính toán hay chạy mã nào. | G53: Ngoài 3 công thức đó, mọi phép tính như R hạn dòng LED, chia áp ADC, công suất P=I²R, nhiệt LDO, RC/tần số timer, tụ tải thạch anh, baud error hay ngân sách dòng pin đều do LLM tự nhẩm trong lời văn. Kết quả không truy vết được và hay sai đơn vị. | H53: CodeAct | I53: Thêm công cụ calc.eval (R1, core): nhận biểu thức một dòng có đơn vị, phân tích bằng ast với whitelist toán tử và hàm (không eval tự do), đổi đơn vị bằng pint hoặc bảng nội bộ ve_si. Tham số tham chiếu Fact theo id ({fact:U1.vih}) để tự gắn nguồn. Trả GiaTriDanXuat; nếu tham số lấy từ Fact BẠC/ĐỒNG thì tier kết quả cũng hạ theo. Mở rộng CONG_THUC thêm led_r, chia_ap_adc, cong_suat_r, nhiet_ldo, rc_tan_so, tu_tai_thach_anh, sai_so_baud. Thêm vào hiến pháp/skill: 'mọi con số tính ra phải qua calc.eval'. | J53: Các giá trị linh kiện có công thức, tham số và nguồn đi kèm; bớt lỗi số học và lỗi đơn vị. | K53: P1 | L53: M | M53: =IF(K53="P0",IF(OR(L53="L",L53="XL"),"GĐ2","GĐ1"),IF(K53="P1",IF(L53="S","GĐ2","GĐ3"),"GĐ4")) | N53: Thêm một công cụ vào lược đồ tool; cần sandbox an toàn (không eval). | O53: Tỉ lệ con số dẫn xuất trong hiện vật có GiaTriDanXuat; sai số trên bộ 20 bài tính mạch chuẩn | P53: M1-21 | Q53: Chưa làm
A54: M3-09 | B54: 3. Mạch, ERC, HDL/FPGA | C54: Chọn linh kiện / trích datasheet (Agentic RAG) | D54: T13 RAG & trích xuất datasheet | E54: src/eide/tools/knowledge.py:751 (fact.extract), knowledge/docs.py:372 (trich_fact_ung_vien) | F54: fact.extract đọc số bằng regex theo dòng hoặc theo hàng bảng, có số trang và trích đoạn nguyên văn, tầng BẠC. Khi không trích được thì công cụ bảo dừng ('đừng bịa'). Không có công cụ chọn hoặc so sánh linh kiện theo thông số. | G54: Không có vòng Agentic RAG nào: không chấm độ liên quan của trang, không viết lại truy vấn (đồng nghĩa IDD/ICC/supply current), không có đường dự phòng dùng LLM đọc bảng ảnh hay bảng phức tạp kèm kiểm bám nguồn, không đọc điều kiện đo (VDD, T, tần số). Việc chọn LDO hay cảm biến theo yêu cầu (Iout ≥ ΣI, Vdropout, gói) hoàn toàn do mô hình tự nghĩ. | H54: Agentic RAG (CRAG/Self-RAG), Routing | I54: (1) Thêm fact.extract_llm làm đường dự phòng khi regex trả 0 hoặc thiếu khoá mà ERC đòi: LLM đọc trang đã định vị, trả JSON {khoa, gia_tri, don_vi, dieu_kien, trich_nguyen_van}. Sau đó mã kiểm trích_nguyên_văn có xuất hiện nguyên chuỗi trong text trang không và số có nằm trong trích đoạn không, đạt thì giữ (tầng BẠC), trượt thì bỏ. (2) Thêm part.select: từ yêu cầu ràng buộc dạng mã (vd iout_max ≥ 1,2×ΣI), định tuyến nguồn tài liệu cục bộ → doc.search_web → doc.fetch, trích và kiểm như trên, rồi xếp hạng bằng mã. Ra bảng so sánh có trích dẫn và để người chọn (HITL). | J54: Tăng độ phủ Fact cho ERC; chọn linh kiện có căn cứ, truy vết được tới trang datasheet. | K54: P1 | L54: L | M54: =IF(K54="P0",IF(OR(L54="L",L54="XL"),"GĐ2","GĐ1"),IF(K54="P1",IF(L54="S","GĐ2","GĐ3"),"GĐ4")) | N54: Thêm token và độ trễ; LLM trích sai. Giảm rủi ro bằng kiểm bám nguyên văn bằng mã và người xác nhận lên VÀNG. | O54: Recall khoá ERC trên 20 datasheet; tỉ lệ Fact LLM bị loại ở bước kiểm bám; số lời gọi mỗi lần chọn một linh kiện | P54: M5-04 | Q54: Chưa làm
A55: M3-10 | B55: 3. Mạch, ERC, HDL/FPGA | C55: Vòng sinh → ERC → sửa cho thiết kế mạch | D55: T10 ERC & thiết kế mạch | E55: src/eide/hooks/standard.py:303 (ledger_and_lint), kiem_chung.py:19 (_GHI_CHAC_CHAN), tools/ckm.py:766 (board.check) | F55: board.check chỉ chạy khi tác tử tự gọi, hoặc bên trong ckm.build và sch.netlist. Không có hook post_tool nào chạy ERC sau ckm.net_set, ckm.port_set hay khoi.place. _GHI_CHAC_CHAN không có ckm.* hay sch.* nên verifier không bị nhắc khi bản đồ mạch đổi. sch.compose sinh SKiDL TẤT ĐỊNH từ cây, nên phép kiểm đẳng cấu thực chất chỉ kiểm bộ sinh; phần thiết kế thật là việc LLM sửa CKM, và phần đó không có vòng chấm–sửa nào. | G55: Thiếu Evaluator–Optimizer đúng nghĩa: tác tử có thể thêm net, kết lượt và không bao giờ thấy lỗi chặn mới. Không có trần vòng riêng cho việc sửa ERC, nên hoặc không sửa, hoặc quay vòng tới hết ngân sách 40 lời gọi. | H55: Evaluator–Optimizer, Prompt Chaining, Human-in-the-loop | I55: Thêm hook on_post_tool 'erc_delta': sau mỗi ckm.*/khoi.place thành công, chạy ERC.erc (rẻ, không LLM), so với lần trước (lưu trong ctx), rồi gắn vào kết quả công cụ CHỈ những phát hiện blocker/major mới phát sinh, tối đa 3 dòng. Thêm hook on_stop: còn blocker mới chưa được nhắc tới thì cho thêm đúng 1 vòng. Đếm số lần sửa cho cùng một (luat, path); quá 3 lần thì đưa thẻ ask_user thay vì tiếp tục. Thêm ckm.*, sch.write, khoi.place vào _GHI_CHAC_CHAN. | J55: Lỗi được phát hiện ngay tại bước gây ra nó; vòng sửa có trần. | K55: P0 | L55: M | M55: =IF(K55="P0",IF(OR(L55="L",L55="XL"),"GĐ2","GĐ1"),IF(K55="P1",IF(L55="S","GĐ2","GĐ3"),"GĐ4")) | N55: Kết quả công cụ dài thêm; phải giới hạn chỉ phần delta và ≤3 dòng. | O55: Số blocker còn lại lúc kết lượt; số lời gọi trung bình để đưa ERC về 0 blocker; số lần chạm trần 3 vòng | Q55: Xong | R55: Agent (Claude Opus 5) | T55: 07/10/2026 | U55: DEV-342 | V55: 1713 → 1720 | W55: chi phí đo thật: mạch lớn nhất trong kho 187 nút → ERC 7,6 ms mỗi lần ghi. Trần 2000 nút, vượt thì NÓI RA chứ không im lặng bỏ qua | X55: ERC_TU_DONG — TẮT | Y55: cần eval 76 ca + bộ phát lại trước khi bật mặc định
A56: M3-11 | B56: 3. Mạch, ERC, HDL/FPGA | C56: Footprint và đối chiếu BOM | D56: T10 ERC & thiết kế mạch | E56: src/eide/sch/netlist.py:viet_net, knowledge/eda.py:262 (doi_chieu_bom_netlist) | F56: viet_net ghi comp chỉ gồm ref/value/libsource, không có (footprint). eda.py có đọc trường footprint, nhưng doi_chieu_bom_netlist chỉ so ref, giá trị và số lượng. | G56: Netlist xuất ra không làm PCB được nếu chưa gán footprint bằng tay. Lỗi gói sai (SOT-23 hay SOT-223, chân 1 ở đâu) và lệch footprint giữa BOM và sơ đồ không được kiểm. Đây là lỗi hay chỉ lộ ra lúc hàn. | H56: Prompt Chaining (cổng mã) | I56: Thêm trường footprint vào canonical của lá (nguồn: hộ chiếu chip/gói trong Fact 'package', hoặc MPN trong BOM). viet_net ghi (footprint ...) khi có. Thêm luật 'footprint': thiếu footprint thì info; số pad của footprint (từ tên chuẩn KiCad, vd SOIC-8) khác số chân trong Fact pinout thì blocker; footprint trong BOM khác footprint trong sơ đồ thì major. | J56: Netlist dùng được cho bước PCB; bắt sai gói trước khi đặt mạch in. | K56: P2 | L56: M | M56: =IF(K56="P0",IF(OR(L56="L",L56="XL"),"GĐ2","GĐ1"),IF(K56="P1",IF(L56="S","GĐ2","GĐ3"),"GĐ4")) | N56: Cần bảng ánh xạ tên footprint ra số pad. | O56: Tỉ lệ linh kiện có footprint; số lệch gói bắt được trên bộ ca | Q56: Chưa làm
A57: M3-12 | B57: 3. Mạch, ERC, HDL/FPGA | C57: Mô phỏng HDL — đọc PASS/FAIL | D57: T11 HDL/FPGA | E57: src/eide/build/hdl.py:497 (mo_phong) | F57: kq.dat = 'PASS' in UPPER(nguyen_van) và 'FAIL' không có. nguyen_van gộp cả log biên dịch (iverilog/verilator) lẫn log chạy. Mã thoát của vvp/sim bị bỏ qua khi kết luận. Không đếm số ca. | G57: Báo PASS giả khi trong log có chữ BYPASS, tên tệp hay tín hiệu chứa 'pass' (pass_through.v trong một cảnh báo), hoặc khi in 'PASSED 0/5'. Báo FAIL giả khi có tên như FAILSAFE. Bỏ sót $fatal/$error và assertion fail (iverilog in 'FATAL'/'ERROR' kèm mã thoát khác 0) nếu testbench đã in PASS trước đó. Đây là đúng loại 'ô xanh giả' mà dự án đang cố diệt. | H57: Prompt Chaining (cổng mã), Evaluator–Optimizer | I57: Chỉ đọc log CHẠY (kq2.nguyen_van). Dùng giao thức dòng chặt: regex ^\s*(EIDE_)?(PASS|FAIL)\b(.*)$ ở đầu dòng, và khuyến nghị dạng 'TEST <ten> PASS/FAIL' để đếm ca. dat = có ≥1 PASS, 0 FAIL, mã thoát == 0, và không có ^(FATAL|ERROR|%Error|Assertion failed). Trả so_ca_pass/so_ca_fail. Thêm test cho các ca BYPASS, $fatal, mã thoát 1. | J57: Kết luận mô phỏng tin được; chặn PASS giả. | K57: P0 | L57: S | M57: =IF(K57="P0",IF(OR(L57="L",L57="XL"),"GĐ2","GĐ1"),IF(K57="P1",IF(L57="S","GĐ2","GĐ3"),"GĐ4")) | N57: Testbench cũ in 'PASS' giữa dòng sẽ phải sửa. Có thể giữ chế độ tương thích kèm cảnh báo. | O57: Số ca PASS giả/FAIL giả trên bộ 10 log cài sẵn (mục tiêu 0) | P57: M4-16 | Q57: Xong | R57: Agent (Claude Opus 5) | T57: 07/10/2026 | U57: DEV-343 | V57: 1720 → 1732 | W57: 846 bản ghi mô phỏng thật: regex mà KẾ HOẠCH ghi sẵn từ chối oan 588/846 (testbench dự án in 'KET QUA: PASS' — nhãn đứng TRƯỚC từ khoá). Nới đúng một chỗ → 846/846 khớp, vẫn bắt đủ bốn ca PASS giả | X57: không có cờ — sửa lỗi thuần | Y57: —
